Workbook

Sheet T&E_
B2: CC1 | C2: CC2 | D2: Dept Name | E2: FP&A L1 | F2: FP&A L2 | G2: Brand | H2: Year | I2: Data Type | J2: Mgt Report L1 | K2: Mgt Report L2 | L2: Mgt Report L3 | M2: Mgt Report L4 | N2: Mgt Report L5 | O2: Mgt Report L6 | P2: CN Name | Q2: Note1 | R2: Note2 | S2: Jan | T2: Feb | U2: Mar | V2: Apr | W2: May | X2: Jun | Y2: Jul | Z2: Aug | AA2: Sep | AB2: Oct | AC2: Nov | AD2: Dec | AE2: FY | AG2: Totals | AI2: Q1 | AJ2: Q2 | AK2: Q3 | AL2: Q4 | AM2: Total | AN2: check | AP2: 1H | AQ2: 2H | AR2: check
B3: C110101101 | C3: 10101101 | D3: 北一区-Xerava | E3: T&E | F3: T&E | G3: Xerava | H3: 2026 | I3: Budget | J3: Commercial | K3: Mainland | L3: CPO Operations | M3: Sales Team | N3: North 1 | O3: North 1 | P3: 北一区 | S3: =SUMIFS('Sales HC by Dept & T&E Segment'!V:V,'Sales HC by Dept & T&E Segment'!$F:$F,$P3,'Sales HC by Dept & T&E Segment'!$G:$G,$G3) -> 140000 | T3: =SUMIFS('Sales HC by Dept & T&E Segment'!W:W,'Sales HC by Dept & T&E Segment'!$F:$F,$P3,'Sales HC by Dept & T&E Segment'!$G:$G,$G3) -> 140000 | U3: =SUMIFS('Sales HC by Dept & T&E Segment'!X:X,'Sales HC by Dept & T&E Segment'!$F:$F,$P3,'Sales HC by Dept & T&E Segment'!$G:$G,$G3) -> 140000 | V3: =SUMIFS('Sales HC by Dept & T&E Segment'!Y:Y,'Sales HC by Dept & T&E Segment'!$F:$F,$P3,'Sales HC by Dept & T&E Segment'!$G:$G,$G3) -> 140000 | W3: =SUMIFS('Sales HC by Dept & T&E Segment'!Z:Z,'Sales HC by Dept & T&E Segment'!$F:$F,$P3,'Sales HC by Dept & T&E Segment'!$G:$G,$G3) -> 140000 | X3: =SUMIFS('Sales HC by Dept & T&E Segment'!AA:AA,'Sales HC by Dept & T&E Segment'!$F:$F,$P3,'Sales HC by Dept & T&E Segment'!$G:$G,$G3) -> 140000 | Y3: =SUMIFS('Sales HC by Dept & T&E Segment'!AB:AB,'Sales HC by Dept & T&E Segment'!$F:$F,$P3,'Sales HC by Dept & T&E Segment'!$G:$G,$G3) -> 140000 | Z3: =SUMIFS('Sales HC by Dept & T&E Segment'!AC:AC,'Sales HC by Dept & T&E Segment'!$F:$F,$P3,'Sales HC by Dept & T&E Segment'!$G:$G,$G3) -> 140000 | AA3: =SUMIFS('Sales HC by Dept & T&E Segment'!AD:AD,'Sales HC by Dept & T&E Segment'!$F:$F,$P3,'Sales HC by Dept & T&E Segment'!$G:$G,$G3) -> 140000 | AB3: =SUMIFS('Sales HC by Dept & T&E Segment'!AE:AE,'Sales HC by Dept & T&E Segment'!$F:$F,$P3,'Sales HC by Dept & T&E Segment'!$G:$G,$G3) -> 140000 | AC3: =SUMIFS('Sales HC by Dept & T&E Segment'!AF:AF,'Sales HC by Dept & T&E Segment'!$F:$F,$P3,'Sales HC by Dept & T&E Segment'!$G:$G,$G3) -> 140000 | AD3: =SUMIFS('Sales HC by Dept & T&E Segment'!AG:AG,'Sales HC by Dept & T&E Segment'!$F:$F,$P3,'Sales HC by Dept & T&E Segment'!$G:$G,$G3) -> 140000 | AE3: =SUM(S3:AD3) -> 1680000 | AI3: =SUM(S3:U3) -> 420000 | AJ3: =SUM(V3:X3) -> 420000 | AK3: =SUM(Y3:AA3) -> 420000 | AL3: =SUM(AB3:AD3) -> 420000 | AM3: =SUM(AI3:AL3) -> 1680000 | AN3: =AM3-AE3 -> 0 | AP3: =SUM(AI3:AJ3) -> 840000 | AQ3: =SUM(AK3:AL3) -> 840000 | AR3: =AP3+AQ3-AM3 -> 0
B4: C110101201 | C4: 10101201 | D4: 北二区-Xerava | E4: T&E | F4: T&E | G4: Xerava | H4: 2026 | I4: Budget | J4: Commercial | K4: Mainland | L4: CPO Operations | M4: Sales Team | N4: North 2 | O4: North 2 | P4: 北二区 | S4: =SUMIFS('Sales HC by Dept & T&E Segment'!V:V,'Sales HC by Dept & T&E Segment'!$F:$F,$P4,'Sales HC by Dept & T&E Segment'!$G:$G,$G4) -> 56000 | T4: =SUMIFS('Sales HC by Dept & T&E Segment'!W:W,'Sales HC by Dept & T&E Segment'!$F:$F,$P4,'Sales HC by Dept & T&E Segment'!$G:$G,$G4) -> 56000 | U4: =SUMIFS('Sales HC by Dept & T&E Segment'!X:X,'Sales HC by Dept & T&E Segment'!$F:$F,$P4,'Sales HC by Dept & T&E Segment'!$G:$G,$G4) -> 56000 | V4: =SUMIFS('Sales HC by Dept & T&E Segment'!Y:Y,'Sales HC by Dept & T&E Segment'!$F:$F,$P4,'Sales HC by Dept & T&E Segment'!$G:$G,$G4) -> 56000 | W4: =SUMIFS('Sales HC by Dept & T&E Segment'!Z:Z,'Sales HC by Dept & T&E Segment'!$F:$F,$P4,'Sales HC by Dept & T&E Segment'!$G:$G,$G4) -> 56000 | X4: =SUMIFS('Sales HC by Dept & T&E Segment'!AA:AA,'Sales HC by Dept & T&E Segment'!$F:$F,$P4,'Sales HC by Dept & T&E Segment'!$G:$G,$G4) -> 56000 | Y4: =SUMIFS('Sales HC by Dept & T&E Segment'!AB:AB,'Sales HC by Dept & T&E Segment'!$F:$F,$P4,'Sales HC by Dept & T&E Segment'!$G:$G,$G4) -> 56000 | Z4: =SUMIFS('Sales HC by Dept & T&E Segment'!AC:AC,'Sales HC by Dept & T&E Segment'!$F:$F,$P4,'Sales HC by Dept & T&E Segment'!$G:$G,$G4) -> 56000 | AA4: =SUMIFS('Sales HC by Dept & T&E Segment'!AD:AD,'Sales HC by Dept & T&E Segment'!$F:$F,$P4,'Sales HC by Dept & T&E Segment'!$G:$G,$G4) -> 56000 | AB4: =SUMIFS('Sales HC by Dept & T&E Segment'!AE:AE,'Sales HC by Dept & T&E Segment'!$F:$F,$P4,'Sales HC by Dept & T&E Segment'!$G:$G,$G4) -> 56000 | AC4: =SUMIFS('Sales HC by Dept & T&E Segment'!AF:AF,'Sales HC by Dept & T&E Segment'!$F:$F,$P4,'Sales HC by Dept & T&E Segment'!$G:$G,$G4) -> 56000 | AD4: =SUMIFS('Sales HC by Dept & T&E Segment'!AG:AG,'Sales HC by Dept & T&E Segment'!$F:$F,$P4,'Sales HC by Dept & T&E Segment'!$G:$G,$G4) -> 56000 | AE4: =SUM(S4:AD4) -> 672000 | AI4: =SUM(S4:U4) -> 168000 | AJ4: =SUM(V4:X4) -> 168000 | AK4: =SUM(Y4:AA4) -> 168000 | AL4: =SUM(AB4:AD4) -> 168000 | AM4: =SUM(AI4:AL4) -> 672000 | AN4: =AM4-AE4 -> 0 | AP4: =SUM(AI4:AJ4) -> 336000 | AQ4: =SUM(AK4:AL4) -> 336000 | AR4: =AP4+AQ4-AM4 -> 0
B5: C110101301 | C5: 10101301 | D5: 北三区-Xerava | E5: T&E | F5: T&E | G5: Xerava | H5: 2026 | I5: Budget | J5: Commercial | K5: Mainland | L5: CPO Operations | M5: Sales Team | N5: North 3 | O5: North 3 | P5: 北三区 | S5: =SUMIFS('Sales HC by Dept & T&E Segment'!V:V,'Sales HC by Dept & T&E Segment'!$F:$F,$P5,'Sales HC by Dept & T&E Segment'!$G:$G,$G5) -> 92000 | T5: =SUMIFS('Sales HC by Dept & T&E Segment'!W:W,'Sales HC by Dept & T&E Segment'!$F:$F,$P5,'Sales HC by Dept & T&E Segment'!$G:$G,$G5) -> 92000 | U5: =SUMIFS('Sales HC by Dept & T&E Segment'!X:X,'Sales HC by Dept & T&E Segment'!$F:$F,$P5,'Sales HC by Dept & T&E Segment'!$G:$G,$G5) -> 92000 | V5: =SUMIFS('Sales HC by Dept & T&E Segment'!Y:Y,'Sales HC by Dept & T&E Segment'!$F:$F,$P5,'Sales HC by Dept & T&E Segment'!$G:$G,$G5) -> 92000 | W5: =SUMIFS('Sales HC by Dept & T&E Segment'!Z:Z,'Sales HC by Dept & T&E Segment'!$F:$F,$P5,'Sales HC by Dept & T&E Segment'!$G:$G,$G5) -> 92000 | X5: =SUMIFS('Sales HC by Dept & T&E Segment'!AA:AA,'Sales HC by Dept & T&E Segment'!$F:$F,$P5,'Sales HC by Dept & T&E Segment'!$G:$G,$G5) -> 92000 | Y5: =SUMIFS('Sales HC by Dept & T&E Segment'!AB:AB,'Sales HC by Dept & T&E Segment'!$F:$F,$P5,'Sales HC by Dept & T&E Segment'!$G:$G,$G5) -> 92000 | Z5: =SUMIFS('Sales HC by Dept & T&E Segment'!AC:AC,'Sales HC by Dept & T&E Segment'!$F:$F,$P5,'Sales HC by Dept & T&E Segment'!$G:$G,$G5) -> 92000 | AA5: =SUMIFS('Sales HC by Dept & T&E Segment'!AD:AD,'Sales HC by Dept & T&E Segment'!$F:$F,$P5,'Sales HC by Dept & T&E Segment'!$G:$G,$G5) -> 92000 | AB5: =SUMIFS('Sales HC by Dept & T&E Segment'!AE:AE,'Sales HC by Dept & T&E Segment'!$F:$F,$P5,'Sales HC by Dept & T&E Segment'!$G:$G,$G5) -> 92000 | AC5: =SUMIFS('Sales HC by Dept & T&E Segment'!AF:AF,'Sales HC by Dept & T&E Segment'!$F:$F,$P5,'Sales HC by Dept & T&E Segment'!$G:$G,$G5) -> 92000 | AD5: =SUMIFS('Sales HC by Dept & T&E Segment'!AG:AG,'Sales HC by Dept & T&E Segment'!$F:$F,$P5,'Sales HC by Dept & T&E Segment'!$G:$G,$G5) -> 92000 | AE5: =SUM(S5:AD5) -> 1104000 | AI5: =SUM(S5:U5) -> 276000 | AJ5: =SUM(V5:X5) -> 276000 | AK5: =SUM(Y5:AA5) -> 276000 | AL5: =SUM(AB5:AD5) -> 276000 | AM5: =SUM(AI5:AL5) -> 1104000 | AN5: =AM5-AE5 -> 0 | AP5: =SUM(AI5:AJ5) -> 552000 | AQ5: =SUM(AK5:AL5) -> 552000 | AR5: =AP5+AQ5-AM5 -> 0
B6: C110102101 | C6: 10102101 | D6: 东一区-Xerava | E6: T&E | F6: T&E | G6: Xerava | H6: 2026 | I6: Budget | J6: Commercial | K6: Mainland | L6: CPO Operations | M6: Sales Team | N6: East 1 | O6: East 1 | P6: 东一区 | S6: =SUMIFS('Sales HC by Dept & T&E Segment'!V:V,'Sales HC by Dept & T&E Segment'!$F:$F,$P6,'Sales HC by Dept & T&E Segment'!$G:$G,$G6) -> 102000 | T6: =SUMIFS('Sales HC by Dept & T&E Segment'!W:W,'Sales HC by Dept & T&E Segment'!$F:$F,$P6,'Sales HC by Dept & T&E Segment'!$G:$G,$G6) -> 102000 | U6: =SUMIFS('Sales HC by Dept & T&E Segment'!X:X,'Sales HC by Dept & T&E Segment'!$F:$F,$P6,'Sales HC by Dept & T&E Segment'!$G:$G,$G6) -> 102000 | V6: =SUMIFS('Sales HC by Dept & T&E Segment'!Y:Y,'Sales HC by Dept & T&E Segment'!$F:$F,$P6,'Sales HC by Dept & T&E Segment'!$G:$G,$G6) -> 102000 | W6: =SUMIFS('Sales HC by Dept & T&E Segment'!Z:Z,'Sales HC by Dept & T&E Segment'!$F:$F,$P6,'Sales HC by Dept & T&E Segment'!$G:$G,$G6) -> 102000 | X6: =SUMIFS('Sales HC by Dept & T&E Segment'!AA:AA,'Sales HC by Dept & T&E Segment'!$F:$F,$P6,'Sales HC by Dept & T&E Segment'!$G:$G,$G6) -> 102000 | Y6: =SUMIFS('Sales HC by Dept & T&E Segment'!AB:AB,'Sales HC by Dept & T&E Segment'!$F:$F,$P6,'Sales HC by Dept & T&E Segment'!$G:$G,$G6) -> 102000 | Z6: =SUMIFS('Sales HC by Dept & T&E Segment'!AC:AC,'Sales HC by Dept & T&E Segment'!$F:$F,$P6,'Sales HC by Dept & T&E Segment'!$G:$G,$G6) -> 102000 | AA6: =SUMIFS('Sales HC by Dept & T&E Segment'!AD:AD,'Sales HC by Dept & T&E Segment'!$F:$F,$P6,'Sales HC by Dept & T&E Segment'!$G:$G,$G6) -> 102000 | AB6: =SUMIFS('Sales HC by Dept & T&E Segment'!AE:AE,'Sales HC by Dept & T&E Segment'!$F:$F,$P6,'Sales HC by Dept & T&E Segment'!$G:$G,$G6) -> 102000 | AC6: =SUMIFS('Sales HC by Dept & T&E Segment'!AF:AF,'Sales HC by Dept & T&E Segment'!$F:$F,$P6,'Sales HC by Dept & T&E Segment'!$G:$G,$G6) -> 102000 | AD6: =SUMIFS('Sales HC by Dept & T&E Segment'!AG:AG,'Sales HC by Dept & T&E Segment'!$F:$F,$P6,'Sales HC by Dept & T&E Segment'!$G:$G,$G6) -> 102000 | AE6: =SUM(S6:AD6) -> 1224000 | AI6: =SUM(S6:U6) -> 306000 | AJ6: =SUM(V6:X6) -> 306000 | AK6: =SUM(Y6:AA6) -> 306000 | AL6: =SUM(AB6:AD6) -> 306000 | AM6: =SUM(AI6:AL6) -> 1224000 | AN6: =AM6-AE6 -> 0 | AP6: =SUM(AI6:AJ6) -> 612000 | AQ6: =SUM(AK6:AL6) -> 612000 | AR6: =AP6+AQ6-AM6 -> 0
B7: C110102201 | C7: 10102201 | D7: 东二区-Xerava | E7: T&E | F7: T&E | G7: Xerava | H7: 2026 | I7: Budget | J7: Commercial | K7: Mainland | L7: CPO Operations | M7: Sales Team | N7: East 2 | O7: East 2 | P7: 东二区 | S7: =SUMIFS('Sales HC by Dept & T&E Segment'!V:V,'Sales HC by Dept & T&E Segment'!$F:$F,$P7,'Sales HC by Dept & T&E Segment'!$G:$G,$G7) -> 107000 | T7: =SUMIFS('Sales HC by Dept & T&E Segment'!W:W,'Sales HC by Dept & T&E Segment'!$F:$F,$P7,'Sales HC by Dept & T&E Segment'!$G:$G,$G7) -> 107000 | U7: =SUMIFS('Sales HC by Dept & T&E Segment'!X:X,'Sales HC by Dept & T&E Segment'!$F:$F,$P7,'Sales HC by Dept & T&E Segment'!$G:$G,$G7) -> 107000 | V7: =SUMIFS('Sales HC by Dept & T&E Segment'!Y:Y,'Sales HC by Dept & T&E Segment'!$F:$F,$P7,'Sales HC by Dept & T&E Segment'!$G:$G,$G7) -> 107000 | W7: =SUMIFS('Sales HC by Dept & T&E Segment'!Z:Z,'Sales HC by Dept & T&E Segment'!$F:$F,$P7,'Sales HC by Dept & T&E Segment'!$G:$G,$G7) -> 107000 | X7: =SUMIFS('Sales HC by Dept & T&E Segment'!AA:AA,'Sales HC by Dept & T&E Segment'!$F:$F,$P7,'Sales HC by Dept & T&E Segment'!$G:$G,$G7) -> 107000 | Y7: =SUMIFS('Sales HC by Dept & T&E Segment'!AB:AB,'Sales HC by Dept & T&E Segment'!$F:$F,$P7,'Sales HC by Dept & T&E Segment'!$G:$G,$G7) -> 107000 | Z7: =SUMIFS('Sales HC by Dept & T&E Segment'!AC:AC,'Sales HC by Dept & T&E Segment'!$F:$F,$P7,'Sales HC by Dept & T&E Segment'!$G:$G,$G7) -> 107000 | AA7: =SUMIFS('Sales HC by Dept & T&E Segment'!AD:AD,'Sales HC by Dept & T&E Segment'!$F:$F,$P7,'Sales HC by Dept & T&E Segment'!$G:$G,$G7) -> 107000 | AB7: =SUMIFS('Sales HC by Dept & T&E Segment'!AE:AE,'Sales HC by Dept & T&E Segment'!$F:$F,$P7,'Sales HC by Dept & T&E Segment'!$G:$G,$G7) -> 107000 | AC7: =SUMIFS('Sales HC by Dept & T&E Segment'!AF:AF,'Sales HC by Dept & T&E Segment'!$F:$F,$P7,'Sales HC by Dept & T&E Segment'!$G:$G,$G7) -> 107000 | AD7: =SUMIFS('Sales HC by Dept & T&E Segment'!AG:AG,'Sales HC by Dept & T&E Segment'!$F:$F,$P7,'Sales HC by Dept & T&E Segment'!$G:$G,$G7) -> 107000 | AE7: =SUM(S7:AD7) -> 1284000 | AI7: =SUM(S7:U7) -> 321000 | AJ7: =SUM(V7:X7) -> 321000 | AK7: =SUM(Y7:AA7) -> 321000 | AL7: =SUM(AB7:AD7) -> 321000 | AM7: =SUM(AI7:AL7) -> 1284000 | AN7: =AM7-AE7 -> 0 | AP7: =SUM(AI7:AJ7) -> 642000 | AQ7: =SUM(AK7:AL7) -> 642000 | AR7: =AP7+AQ7-AM7 -> 0
B8: C110102301 | C8: 10102301 | D8: 东三区-Xerava | E8: T&E | F8: T&E | G8: Xerava | H8: 2026 | I8: Budget | J8: Commercial | K8: Mainland | L8: CPO Operations | M8: Sales Team | N8: East 3 | O8: East 3 | P8: 东三区 | S8: =SUMIFS('Sales HC by Dept & T&E Segment'!V:V,'Sales HC by Dept & T&E Segment'!$F:$F,$P8,'Sales HC by Dept & T&E Segment'!$G:$G,$G8) -> 89000 | T8: =SUMIFS('Sales HC by Dept & T&E Segment'!W:W,'Sales HC by Dept & T&E Segment'!$F:$F,$P8,'Sales HC by Dept & T&E Segment'!$G:$G,$G8) -> 89000 | U8: =SUMIFS('Sales HC by Dept & T&E Segment'!X:X,'Sales HC by Dept & T&E Segment'!$F:$F,$P8,'Sales HC by Dept & T&E Segment'!$G:$G,$G8) -> 89000 | V8: =SUMIFS('Sales HC by Dept & T&E Segment'!Y:Y,'Sales HC by Dept & T&E Segment'!$F:$F,$P8,'Sales HC by Dept & T&E Segment'!$G:$G,$G8) -> 89000 | W8: =SUMIFS('Sales HC by Dept & T&E Segment'!Z:Z,'Sales HC by Dept & T&E Segment'!$F:$F,$P8,'Sales HC by Dept & T&E Segment'!$G:$G,$G8) -> 89000 | X8: =SUMIFS('Sales HC by Dept & T&E Segment'!AA:AA,'Sales HC by Dept & T&E Segment'!$F:$F,$P8,'Sales HC by Dept & T&E Segment'!$G:$G,$G8) -> 89000 | Y8: =SUMIFS('Sales HC by Dept & T&E Segment'!AB:AB,'Sales HC by Dept & T&E Segment'!$F:$F,$P8,'Sales HC by Dept & T&E Segment'!$G:$G,$G8) -> 89000 | Z8: =SUMIFS('Sales HC by Dept & T&E Segment'!AC:AC,'Sales HC by Dept & T&E Segment'!$F:$F,$P8,'Sales HC by Dept & T&E Segment'!$G:$G,$G8) -> 89000 | AA8: =SUMIFS('Sales HC by Dept & T&E Segment'!AD:AD,'Sales HC by Dept & T&E Segment'!$F:$F,$P8,'Sales HC by Dept & T&E Segment'!$G:$G,$G8) -> 89000 | AB8: =SUMIFS('Sales HC by Dept & T&E Segment'!AE:AE,'Sales HC by Dept & T&E Segment'!$F:$F,$P8,'Sales HC by Dept & T&E Segment'!$G:$G,$G8) -> 89000 | AC8: =SUMIFS('Sales HC by Dept & T&E Segment'!AF:AF,'Sales HC by Dept & T&E Segment'!$F:$F,$P8,'Sales HC by Dept & T&E Segment'!$G:$G,$G8) -> 89000 | AD8: =SUMIFS('Sales HC by Dept & T&E Segment'!AG:AG,'Sales HC by Dept & T&E Segment'!$F:$F,$P8,'Sales HC by Dept & T&E Segment'!$G:$G,$G8) -> 89000 | AE8: =SUM(S8:AD8) -> 1068000 | AI8: =SUM(S8:U8) -> 267000 | AJ8: =SUM(V8:X8) -> 267000 | AK8: =SUM(Y8:AA8) -> 267000 | AL8: =SUM(AB8:AD8) -> 267000 | AM8: =SUM(AI8:AL8) -> 1068000 | AN8: =AM8-AE8 -> 0 | AP8: =SUM(AI8:AJ8) -> 534000 | AQ8: =SUM(AK8:AL8) -> 534000 | AR8: =AP8+AQ8-AM8 -> 0
B9: C110103101 | C9: 10103101 | D9: 华中区-Xerava | E9: T&E | F9: T&E | G9: Xerava | H9: 2026 | I9: Budget | J9: Commercial | K9: Mainland | L9: CPO Operations | M9: Sales Team | N9: Central | O9: Central | P9: 华中区 | S9: =SUMIFS('Sales HC by Dept & T&E Segment'!V:V,'Sales HC by Dept & T&E Segment'!$F:$F,$P9,'Sales HC by Dept & T&E Segment'!$G:$G,$G9) -> 100000 | T9: =SUMIFS('Sales HC by Dept & T&E Segment'!W:W,'Sales HC by Dept & T&E Segment'!$F:$F,$P9,'Sales HC by Dept & T&E Segment'!$G:$G,$G9) -> 100000 | U9: =SUMIFS('Sales HC by Dept & T&E Segment'!X:X,'Sales HC by Dept & T&E Segment'!$F:$F,$P9,'Sales HC by Dept & T&E Segment'!$G:$G,$G9) -> 100000 | V9: =SUMIFS('Sales HC by Dept & T&E Segment'!Y:Y,'Sales HC by Dept & T&E Segment'!$F:$F,$P9,'Sales HC by Dept & T&E Segment'!$G:$G,$G9) -> 100000 | W9: =SUMIFS('Sales HC by Dept & T&E Segment'!Z:Z,'Sales HC by Dept & T&E Segment'!$F:$F,$P9,'Sales HC by Dept & T&E Segment'!$G:$G,$G9) -> 100000 | X9: =SUMIFS('Sales HC by Dept & T&E Segment'!AA:AA,'Sales HC by Dept & T&E Segment'!$F:$F,$P9,'Sales HC by Dept & T&E Segment'!$G:$G,$G9) -> 100000 | Y9: =SUMIFS('Sales HC by Dept & T&E Segment'!AB:AB,'Sales HC by Dept & T&E Segment'!$F:$F,$P9,'Sales HC by Dept & T&E Segment'!$G:$G,$G9) -> 100000 | Z9: =SUMIFS('Sales HC by Dept & T&E Segment'!AC:AC,'Sales HC by Dept & T&E Segment'!$F:$F,$P9,'Sales HC by Dept & T&E Segment'!$G:$G,$G9) -> 100000 | AA9: =SUMIFS('Sales HC by Dept & T&E Segment'!AD:AD,'Sales HC by Dept & T&E Segment'!$F:$F,$P9,'Sales HC by Dept & T&E Segment'!$G:$G,$G9) -> 100000 | AB9: =SUMIFS('Sales HC by Dept & T&E Segment'!AE:AE,'Sales HC by Dept & T&E Segment'!$F:$F,$P9,'Sales HC by Dept & T&E Segment'!$G:$G,$G9) -> 100000 | AC9: =SUMIFS('Sales HC by Dept & T&E Segment'!AF:AF,'Sales HC by Dept & T&E Segment'!$F:$F,$P9,'Sales HC by Dept & T&E Segment'!$G:$G,$G9) -> 100000 | AD9: =SUMIFS('Sales HC by Dept & T&E Segment'!AG:AG,'Sales HC by Dept & T&E Segment'!$F:$F,$P9,'Sales HC by Dept & T&E Segment'!$G:$G,$G9) -> 100000 | AE9: =SUM(S9:AD9) -> 1200000 | AI9: =SUM(S9:U9) -> 300000 | AJ9: =SUM(V9:X9) -> 300000 | AK9: =SUM(Y9:AA9) -> 300000 | AL9: =SUM(AB9:AD9) -> 300000 | AM9: =SUM(AI9:AL9) -> 1200000 | AN9: =AM9-AE9 -> 0 | AP9: =SUM(AI9:AJ9) -> 600000 | AQ9: =SUM(AK9:AL9) -> 600000 | AR9: =AP9+AQ9-AM9 -> 0
B10: C110106101 | C10: 10106101 | D10: 东北区-Xerava | E10: T&E | F10: T&E | G10: Xerava | H10: 2026 | I10: Budget | J10: Commercial | K10: Mainland | L10: CPO Operations | M10: Sales Team | N10: Northeast | O10: Northeast | P10: 东北区 | S10: =SUMIFS('Sales HC by Dept & T&E Segment'!V:V,'Sales HC by Dept & T&E Segment'!$F:$F,$P10,'Sales HC by Dept & T&E Segment'!$G:$G,$G10) -> 51000 | T10: =SUMIFS('Sales HC by Dept & T&E Segment'!W:W,'Sales HC by Dept & T&E Segment'!$F:$F,$P10,'Sales HC by Dept & T&E Segment'!$G:$G,$G10) -> 51000 | U10: =SUMIFS('Sales HC by Dept & T&E Segment'!X:X,'Sales HC by Dept & T&E Segment'!$F:$F,$P10,'Sales HC by Dept & T&E Segment'!$G:$G,$G10) -> 51000 | V10: =SUMIFS('Sales HC by Dept & T&E Segment'!Y:Y,'Sales HC by Dept & T&E Segment'!$F:$F,$P10,'Sales HC by Dept & T&E Segment'!$G:$G,$G10) -> 51000 | W10: =SUMIFS('Sales HC by Dept & T&E Segment'!Z:Z,'Sales HC by Dept & T&E Segment'!$F:$F,$P10,'Sales HC by Dept & T&E Segment'!$G:$G,$G10) -> 51000 | X10: =SUMIFS('Sales HC by Dept & T&E Segment'!AA:AA,'Sales HC by Dept & T&E Segment'!$F:$F,$P10,'Sales HC by Dept & T&E Segment'!$G:$G,$G10) -> 51000 | Y10: =SUMIFS('Sales HC by Dept & T&E Segment'!AB:AB,'Sales HC by Dept & T&E Segment'!$F:$F,$P10,'Sales HC by Dept & T&E Segment'!$G:$G,$G10) -> 51000 | Z10: =SUMIFS('Sales HC by Dept & T&E Segment'!AC:AC,'Sales HC by Dept & T&E Segment'!$F:$F,$P10,'Sales HC by Dept & T&E Segment'!$G:$G,$G10) -> 51000 | AA10: =SUMIFS('Sales HC by Dept & T&E Segment'!AD:AD,'Sales HC by Dept & T&E Segment'!$F:$F,$P10,'Sales HC by Dept & T&E Segment'!$G:$G,$G10) -> 51000 | AB10: =SUMIFS('Sales HC by Dept & T&E Segment'!AE:AE,'Sales HC by Dept & T&E Segment'!$F:$F,$P10,'Sales HC by Dept & T&E Segment'!$G:$G,$G10) -> 51000 | AC10: =SUMIFS('Sales HC by Dept & T&E Segment'!AF:AF,'Sales HC by Dept & T&E Segment'!$F:$F,$P10,'Sales HC by Dept & T&E Segment'!$G:$G,$G10) -> 51000 | AD10: =SUMIFS('Sales HC by Dept & T&E Segment'!AG:AG,'Sales HC by Dept & T&E Segment'!$F:$F,$P10,'Sales HC by Dept & T&E Segment'!$G:$G,$G10) -> 51000 | AE10: =SUM(S10:AD10) -> 612000 | AI10: =SUM(S10:U10) -> 153000 | AJ10: =SUM(V10:X10) -> 153000 | AK10: =SUM(Y10:AA10) -> 153000 | AL10: =SUM(AB10:AD10) -> 153000 | AM10: =SUM(AI10:AL10) -> 612000 | AN10: =AM10-AE10 -> 0 | AP10: =SUM(AI10:AJ10) -> 306000 | AQ10: =SUM(AK10:AL10) -> 306000 | AR10: =AP10+AQ10-AM10 -> 0
B11: C110105101 | C11: 10105101 | D11: 南区-Xerava | E11: T&E | F11: T&E | G11: Xerava | H11: 2026 | I11: Budget | J11: Commercial | K11: Mainland | L11: CPO Operations | M11: Sales Team | N11: South | O11: South | P11: 南区 | S11: =SUMIFS('Sales HC by Dept & T&E Segment'!V:V,'Sales HC by Dept & T&E Segment'!$F:$F,$P11,'Sales HC by Dept & T&E Segment'!$G:$G,$G11) -> 120000 | T11: =SUMIFS('Sales HC by Dept & T&E Segment'!W:W,'Sales HC by Dept & T&E Segment'!$F:$F,$P11,'Sales HC by Dept & T&E Segment'!$G:$G,$G11) -> 120000 | U11: =SUMIFS('Sales HC by Dept & T&E Segment'!X:X,'Sales HC by Dept & T&E Segment'!$F:$F,$P11,'Sales HC by Dept & T&E Segment'!$G:$G,$G11) -> 120000 | V11: =SUMIFS('Sales HC by Dept & T&E Segment'!Y:Y,'Sales HC by Dept & T&E Segment'!$F:$F,$P11,'Sales HC by Dept & T&E Segment'!$G:$G,$G11) -> 120000 | W11: =SUMIFS('Sales HC by Dept & T&E Segment'!Z:Z,'Sales HC by Dept & T&E Segment'!$F:$F,$P11,'Sales HC by Dept & T&E Segment'!$G:$G,$G11) -> 120000 | X11: =SUMIFS('Sales HC by Dept & T&E Segment'!AA:AA,'Sales HC by Dept & T&E Segment'!$F:$F,$P11,'Sales HC by Dept & T&E Segment'!$G:$G,$G11) -> 120000 | Y11: =SUMIFS('Sales HC by Dept & T&E Segment'!AB:AB,'Sales HC by Dept & T&E Segment'!$F:$F,$P11,'Sales HC by Dept & T&E Segment'!$G:$G,$G11) -> 120000 | Z11: =SUMIFS('Sales HC by Dept & T&E Segment'!AC:AC,'Sales HC by Dept & T&E Segment'!$F:$F,$P11,'Sales HC by Dept & T&E Segment'!$G:$G,$G11) -> 120000 | AA11: =SUMIFS('Sales HC by Dept & T&E Segment'!AD:AD,'Sales HC by Dept & T&E Segment'!$F:$F,$P11,'Sales HC by Dept & T&E Segment'!$G:$G,$G11) -> 120000 | AB11: =SUMIFS('Sales HC by Dept & T&E Segment'!AE:AE,'Sales HC by Dept & T&E Segment'!$F:$F,$P11,'Sales HC by Dept & T&E Segment'!$G:$G,$G11) -> 120000 | AC11: =SUMIFS('Sales HC by Dept & T&E Segment'!AF:AF,'Sales HC by Dept & T&E Segment'!$F:$F,$P11,'Sales HC by Dept & T&E Segment'!$G:$G,$G11) -> 120000 | AD11: =SUMIFS('Sales HC by Dept & T&E Segment'!AG:AG,'Sales HC by Dept & T&E Segment'!$F:$F,$P11,'Sales HC by Dept & T&E Segment'!$G:$G,$G11) -> 120000 | AE11: =SUM(S11:AD11) -> 1440000 | AI11: =SUM(S11:U11) -> 360000 | AJ11: =SUM(V11:X11) -> 360000 | AK11: =SUM(Y11:AA11) -> 360000 | AL11: =SUM(AB11:AD11) -> 360000 | AM11: =SUM(AI11:AL11) -> 1440000 | AN11: =AM11-AE11 -> 0 | AP11: =SUM(AI11:AJ11) -> 720000 | AQ11: =SUM(AK11:AL11) -> 720000 | AR11: =AP11+AQ11-AM11 -> 0
B12: C110107101 | C12: 10107101 | D12: 西区-Xerava | E12: T&E | F12: T&E | G12: Xerava | H12: 2026 | I12: Budget | J12: Commercial | K12: Mainland | L12: CPO Operations | M12: Sales Team | N12: West | O12: West | P12: 西区 | S12: =SUMIFS('Sales HC by Dept & T&E Segment'!V:V,'Sales HC by Dept & T&E Segment'!$F:$F,$P12,'Sales HC by Dept & T&E Segment'!$G:$G,$G12) -> 74000 | T12: =SUMIFS('Sales HC by Dept & T&E Segment'!W:W,'Sales HC by Dept & T&E Segment'!$F:$F,$P12,'Sales HC by Dept & T&E Segment'!$G:$G,$G12) -> 74000 | U12: =SUMIFS('Sales HC by Dept & T&E Segment'!X:X,'Sales HC by Dept & T&E Segment'!$F:$F,$P12,'Sales HC by Dept & T&E Segment'!$G:$G,$G12) -> 74000 | V12: =SUMIFS('Sales HC by Dept & T&E Segment'!Y:Y,'Sales HC by Dept & T&E Segment'!$F:$F,$P12,'Sales HC by Dept & T&E Segment'!$G:$G,$G12) -> 74000 | W12: =SUMIFS('Sales HC by Dept & T&E Segment'!Z:Z,'Sales HC by Dept & T&E Segment'!$F:$F,$P12,'Sales HC by Dept & T&E Segment'!$G:$G,$G12) -> 74000 | X12: =SUMIFS('Sales HC by Dept & T&E Segment'!AA:AA,'Sales HC by Dept & T&E Segment'!$F:$F,$P12,'Sales HC by Dept & T&E Segment'!$G:$G,$G12) -> 74000 | Y12: =SUMIFS('Sales HC by Dept & T&E Segment'!AB:AB,'Sales HC by Dept & T&E Segment'!$F:$F,$P12,'Sales HC by Dept & T&E Segment'!$G:$G,$G12) -> 74000 | Z12: =SUMIFS('Sales HC by Dept & T&E Segment'!AC:AC,'Sales HC by Dept & T&E Segment'!$F:$F,$P12,'Sales HC by Dept & T&E Segment'!$G:$G,$G12) -> 74000 | AA12: =SUMIFS('Sales HC by Dept & T&E Segment'!AD:AD,'Sales HC by Dept & T&E Segment'!$F:$F,$P12,'Sales HC by Dept & T&E Segment'!$G:$G,$G12) -> 74000 | AB12: =SUMIFS('Sales HC by Dept & T&E Segment'!AE:AE,'Sales HC by Dept & T&E Segment'!$F:$F,$P12,'Sales HC by Dept & T&E Segment'!$G:$G,$G12) -> 74000 | AC12: =SUMIFS('Sales HC by Dept & T&E Segment'!AF:AF,'Sales HC by Dept & T&E Segment'!$F:$F,$P12,'Sales HC by Dept & T&E Segment'!$G:$G,$G12) -> 74000 | AD12: =SUMIFS('Sales HC by Dept & T&E Segment'!AG:AG,'Sales HC by Dept & T&E Segment'!$F:$F,$P12,'Sales HC by Dept & T&E Segment'!$G:$G,$G12) -> 74000 | AE12: =SUM(S12:AD12) -> 888000 | AG12: =SUM(AE3:AE12) -> 11172000 | AH12: =AG12-'Sales HC by Dept & T&E Segment'!S41 -> 0 | AI12: =SUM(S12:U12) -> 222000 | AJ12: =SUM(V12:X12) -> 222000 | AK12: =SUM(Y12:AA12) -> 222000 | AL12: =SUM(AB12:AD12) -> 222000 | AM12: =SUM(AI12:AL12) -> 888000 | AN12: =AM12-AE12 -> 0 | AP12: =SUM(AI12:AJ12) -> 444000 | AQ12: =SUM(AK12:AL12) -> 444000 | AR12: =AP12+AQ12-AM12 -> 0
B13: C110101102 | C13: 10101102 | D13: 北一区-Nefecon | E13: T&E | F13: T&E | G13: Nefecon | H13: 2026 | I13: Budget | J13: Commercial | K13: Mainland | L13: CPO Operations | M13: Sales Team | N13: North 1 | O13: North 1 | P13: 北一区 | S13: =SUMIFS('Sales HC by Dept & T&E Segment'!V:V,'Sales HC by Dept & T&E Segment'!$F:$F,$P13,'Sales HC by Dept & T&E Segment'!$G:$G,$G13) -> 158000 | T13: =SUMIFS('Sales HC by Dept & T&E Segment'!W:W,'Sales HC by Dept & T&E Segment'!$F:$F,$P13,'Sales HC by Dept & T&E Segment'!$G:$G,$G13) -> 158000 | U13: =SUMIFS('Sales HC by Dept & T&E Segment'!X:X,'Sales HC by Dept & T&E Segment'!$F:$F,$P13,'Sales HC by Dept & T&E Segment'!$G:$G,$G13) -> 158000 | V13: =SUMIFS('Sales HC by Dept & T&E Segment'!Y:Y,'Sales HC by Dept & T&E Segment'!$F:$F,$P13,'Sales HC by Dept & T&E Segment'!$G:$G,$G13) -> 178000 | W13: =SUMIFS('Sales HC by Dept & T&E Segment'!Z:Z,'Sales HC by Dept & T&E Segment'!$F:$F,$P13,'Sales HC by Dept & T&E Segment'!$G:$G,$G13) -> 178000 | X13: =SUMIFS('Sales HC by Dept & T&E Segment'!AA:AA,'Sales HC by Dept & T&E Segment'!$F:$F,$P13,'Sales HC by Dept & T&E Segment'!$G:$G,$G13) -> 178000 | Y13: =SUMIFS('Sales HC by Dept & T&E Segment'!AB:AB,'Sales HC by Dept & T&E Segment'!$F:$F,$P13,'Sales HC by Dept & T&E Segment'!$G:$G,$G13) -> 178000 | Z13: =SUMIFS('Sales HC by Dept & T&E Segment'!AC:AC,'Sales HC by Dept & T&E Segment'!$F:$F,$P13,'Sales HC by Dept & T&E Segment'!$G:$G,$G13) -> 178000 | AA13: =SUMIFS('Sales HC by Dept & T&E Segment'!AD:AD,'Sales HC by Dept & T&E Segment'!$F:$F,$P13,'Sales HC by Dept & T&E Segment'!$G:$G,$G13) -> 178000 | AB13: =SUMIFS('Sales HC by Dept & T&E Segment'!AE:AE,'Sales HC by Dept & T&E Segment'!$F:$F,$P13,'Sales HC by Dept & T&E Segment'!$G:$G,$G13) -> 178000 | AC13: =SUMIFS('Sales HC by Dept & T&E Segment'!AF:AF,'Sales HC by Dept & T&E Segment'!$F:$F,$P13,'Sales HC by Dept & T&E Segment'!$G:$G,$G13) -> 178000 | AD13: =SUMIFS('Sales HC by Dept & T&E Segment'!AG:AG,'Sales HC by Dept & T&E Segment'!$F:$F,$P13,'Sales HC by Dept & T&E Segment'!$G:$G,$G13) -> 178000 | AE13: =SUM(S13:AD13) -> 2076000 | AI13: =SUM(S13:U13) -> 474000 | AJ13: =SUM(V13:X13) -> 534000 | AK13: =SUM(Y13:AA13) -> 534000 | AL13: =SUM(AB13:AD13) -> 534000 | AM13: =SUM(AI13:AL13) -> 2076000 | AN13: =AM13-AE13 -> 0 | AP13: =SUM(AI13:AJ13) -> 1008000 | AQ13: =SUM(AK13:AL13) -> 1068000 | AR13: =AP13+AQ13-AM13 -> 0
B14: C110101202 | C14: 10101202 | D14: 北二区-Nefecon | E14: T&E | F14: T&E | G14: Nefecon | H14: 2026 | I14: Budget | J14: Commercial | K14: Mainland | L14: CPO Operations | M14: Sales Team | N14: North 2 | O14: North 2 | P14: 北二区 | S14: =SUMIFS('Sales HC by Dept & T&E Segment'!V:V,'Sales HC by Dept & T&E Segment'!$F:$F,$P14,'Sales HC by Dept & T&E Segment'!$G:$G,$G14) -> 157000 | T14: =SUMIFS('Sales HC by Dept & T&E Segment'!W:W,'Sales HC by Dept & T&E Segment'!$F:$F,$P14,'Sales HC by Dept & T&E Segment'!$G:$G,$G14) -> 157000 | U14: =SUMIFS('Sales HC by Dept & T&E Segment'!X:X,'Sales HC by Dept & T&E Segment'!$F:$F,$P14,'Sales HC by Dept & T&E Segment'!$G:$G,$G14) -> 157000 | V14: =SUMIFS('Sales HC by Dept & T&E Segment'!Y:Y,'Sales HC by Dept & T&E Segment'!$F:$F,$P14,'Sales HC by Dept & T&E Segment'!$G:$G,$G14) -> 172000 | W14: =SUMIFS('Sales HC by Dept & T&E Segment'!Z:Z,'Sales HC by Dept & T&E Segment'!$F:$F,$P14,'Sales HC by Dept & T&E Segment'!$G:$G,$G14) -> 172000 | X14: =SUMIFS('Sales HC by Dept & T&E Segment'!AA:AA,'Sales HC by Dept & T&E Segment'!$F:$F,$P14,'Sales HC by Dept & T&E Segment'!$G:$G,$G14) -> 172000 | Y14: =SUMIFS('Sales HC by Dept & T&E Segment'!AB:AB,'Sales HC by Dept & T&E Segment'!$F:$F,$P14,'Sales HC by Dept & T&E Segment'!$G:$G,$G14) -> 172000 | Z14: =SUMIFS('Sales HC by Dept & T&E Segment'!AC:AC,'Sales HC by Dept & T&E Segment'!$F:$F,$P14,'Sales HC by Dept & T&E Segment'!$G:$G,$G14) -> 172000 | AA14: =SUMIFS('Sales HC by Dept & T&E Segment'!AD:AD,'Sales HC by Dept & T&E Segment'!$F:$F,$P14,'Sales HC by Dept & T&E Segment'!$G:$G,$G14) -> 172000 | AB14: =SUMIFS('Sales HC by Dept & T&E Segment'!AE:AE,'Sales HC by Dept & T&E Segment'!$F:$F,$P14,'Sales HC by Dept & T&E Segment'!$G:$G,$G14) -> 172000 | AC14: =SUMIFS('Sales HC by Dept & T&E Segment'!AF:AF,'Sales HC by Dept & T&E Segment'!$F:$F,$P14,'Sales HC by Dept & T&E Segment'!$G:$G,$G14) -> 172000 | AD14: =SUMIFS('Sales HC by Dept & T&E Segment'!AG:AG,'Sales HC by Dept & T&E Segment'!$F:$F,$P14,'Sales HC by Dept & T&E Segment'!$G:$G,$G14) -> 172000 | AE14: =SUM(S14:AD14) -> 2019000 | AI14: =SUM(S14:U14) -> 471000 | AJ14: =SUM(V14:X14) -> 516000 | AK14: =SUM(Y14:AA14) -> 516000 | AL14: =SUM(AB14:AD14) -> 516000 | AM14: =SUM(AI14:AL14) -> 2019000 | AN14: =AM14-AE14 -> 0 | AP14: =SUM(AI14:AJ14) -> 987000 | AQ14: =SUM(AK14:AL14) -> 1032000 | AR14: =AP14+AQ14-AM14 -> 0
B15: C110101302 | C15: 10101302 | D15: 北三区-Nefecon | E15: T&E | F15: T&E | G15: Nefecon | H15: 2026 | I15: Budget | J15: Commercial | K15: Mainland | L15: CPO Operations | M15: Sales Team | N15: North 3 | O15: North 3 | P15: 北三区 | S15: =SUMIFS('Sales HC by Dept & T&E Segment'!V:V,'Sales HC by Dept & T&E Segment'!$F:$F,$P15,'Sales HC by Dept & T&E Segment'!$G:$G,$G15) -> 175000 | T15: =SUMIFS('Sales HC by Dept & T&E Segment'!W:W,'Sales HC by Dept & T&E Segment'!$F:$F,$P15,'Sales HC by Dept & T&E Segment'!$G:$G,$G15) -> 175000 | U15: =SUMIFS('Sales HC by Dept & T&E Segment'!X:X,'Sales HC by Dept & T&E Segment'!$F:$F,$P15,'Sales HC by Dept & T&E Segment'!$G:$G,$G15) -> 175000 | V15: =SUMIFS('Sales HC by Dept & T&E Segment'!Y:Y,'Sales HC by Dept & T&E Segment'!$F:$F,$P15,'Sales HC by Dept & T&E Segment'!$G:$G,$G15) -> 190000 | W15: =SUMIFS('Sales HC by Dept & T&E Segment'!Z:Z,'Sales HC by Dept & T&E Segment'!$F:$F,$P15,'Sales HC by Dept & T&E Segment'!$G:$G,$G15) -> 190000 | X15: =SUMIFS('Sales HC by Dept & T&E Segment'!AA:AA,'Sales HC by Dept & T&E Segment'!$F:$F,$P15,'Sales HC by Dept & T&E Segment'!$G:$G,$G15) -> 190000 | Y15: =SUMIFS('Sales HC by Dept & T&E Segment'!AB:AB,'Sales HC by Dept & T&E Segment'!$F:$F,$P15,'Sales HC by Dept & T&E Segment'!$G:$G,$G15) -> 190000 | Z15: =SUMIFS('Sales HC by Dept & T&E Segment'!AC:AC,'Sales HC by Dept & T&E Segment'!$F:$F,$P15,'Sales HC by Dept & T&E Segment'!$G:$G,$G15) -> 190000 | AA15: =SUMIFS('Sales HC by Dept & T&E Segment'!AD:AD,'Sales HC by Dept & T&E Segment'!$F:$F,$P15,'Sales HC by Dept & T&E Segment'!$G:$G,$G15) -> 190000 | AB15: =SUMIFS('Sales HC by Dept & T&E Segment'!AE:AE,'Sales HC by Dept & T&E Segment'!$F:$F,$P15,'Sales HC by Dept & T&E Segment'!$G:$G,$G15) -> 190000 | AC15: =SUMIFS('Sales HC by Dept & T&E Segment'!AF:AF,'Sales HC by Dept & T&E Segment'!$F:$F,$P15,'Sales HC by Dept & T&E Segment'!$G:$G,$G15) -> 190000 | AD15: =SUMIFS('Sales HC by Dept & T&E Segment'!AG:AG,'Sales HC by Dept & T&E Segment'!$F:$F,$P15,'Sales HC by Dept & T&E Segment'!$G:$G,$G15) -> 190000 | AE15: =SUM(S15:AD15) -> 2235000 | AI15: =SUM(S15:U15) -> 525000 | AJ15: =SUM(V15:X15) -> 570000 | AK15: =SUM(Y15:AA15) -> 570000 | AL15: =SUM(AB15:AD15) -> 570000 | AM15: =SUM(AI15:AL15) -> 2235000 | AN15: =AM15-AE15 -> 0 | AP15: =SUM(AI15:AJ15) -> 1095000 | AQ15: =SUM(AK15:AL15) -> 1140000 | AR15: =AP15+AQ15-AM15 -> 0
B16: C110102102 | C16: 10102102 | D16: 东一区-Nefecon | E16: T&E | F16: T&E | G16: Nefecon | H16: 2026 | I16: Budget | J16: Commercial | K16: Mainland | L16: CPO Operations | M16: Sales Team | N16: East 1 | O16: East 1 | P16: 东一区 | S16: =SUMIFS('Sales HC by Dept & T&E Segment'!V:V,'Sales HC by Dept & T&E Segment'!$F:$F,$P16,'Sales HC by Dept & T&E Segment'!$G:$G,$G16) -> 178000 | T16: =SUMIFS('Sales HC by Dept & T&E Segment'!W:W,'Sales HC by Dept & T&E Segment'!$F:$F,$P16,'Sales HC by Dept & T&E Segment'!$G:$G,$G16) -> 178000 | U16: =SUMIFS('Sales HC by Dept & T&E Segment'!X:X,'Sales HC by Dept & T&E Segment'!$F:$F,$P16,'Sales HC by Dept & T&E Segment'!$G:$G,$G16) -> 178000 | V16: =SUMIFS('Sales HC by Dept & T&E Segment'!Y:Y,'Sales HC by Dept & T&E Segment'!$F:$F,$P16,'Sales HC by Dept & T&E Segment'!$G:$G,$G16) -> 203000 | W16: =SUMIFS('Sales HC by Dept & T&E Segment'!Z:Z,'Sales HC by Dept & T&E Segment'!$F:$F,$P16,'Sales HC by Dept & T&E Segment'!$G:$G,$G16) -> 203000 | X16: =SUMIFS('Sales HC by Dept & T&E Segment'!AA:AA,'Sales HC by Dept & T&E Segment'!$F:$F,$P16,'Sales HC by Dept & T&E Segment'!$G:$G,$G16) -> 203000 | Y16: =SUMIFS('Sales HC by Dept & T&E Segment'!AB:AB,'Sales HC by Dept & T&E Segment'!$F:$F,$P16,'Sales HC by Dept & T&E Segment'!$G:$G,$G16) -> 203000 | Z16: =SUMIFS('Sales HC by Dept & T&E Segment'!AC:AC,'Sales HC by Dept & T&E Segment'!$F:$F,$P16,'Sales HC by Dept & T&E Segment'!$G:$G,$G16) -> 203000 | AA16: =SUMIFS('Sales HC by Dept & T&E Segment'!AD:AD,'Sales HC by Dept & T&E Segment'!$F:$F,$P16,'Sales HC by Dept & T&E Segment'!$G:$G,$G16) -> 203000 | AB16: =SUMIFS('Sales HC by Dept & T&E Segment'!AE:AE,'Sales HC by Dept & T&E Segment'!$F:$F,$P16,'Sales HC by Dept & T&E Segment'!$G:$G,$G16) -> 203000 | AC16: =SUMIFS('Sales HC by Dept & T&E Segment'!AF:AF,'Sales HC by Dept & T&E Segment'!$F:$F,$P16,'Sales HC by Dept & T&E Segment'!$G:$G,$G16) -> 203000 | AD16: =SUMIFS('Sales HC by Dept & T&E Segment'!AG:AG,'Sales HC by Dept & T&E Segment'!$F:$F,$P16,'Sales HC by Dept & T&E Segment'!$G:$G,$G16) -> 203000 | AE16: =SUM(S16:AD16) -> 2361000 | AI16: =SUM(S16:U16) -> 534000 | AJ16: =SUM(V16:X16) -> 609000 | AK16: =SUM(Y16:AA16) -> 609000 | AL16: =SUM(AB16:AD16) -> 609000 | AM16: =SUM(AI16:AL16) -> 2361000 | AN16: =AM16-AE16 -> 0 | AP16: =SUM(AI16:AJ16) -> 1143000 | AQ16: =SUM(AK16:AL16) -> 1218000 | AR16: =AP16+AQ16-AM16 -> 0
B17: C110102202 | C17: 10102202 | D17: 东二区-Nefecon | E17: T&E | F17: T&E | G17: Nefecon | H17: 2026 | I17: Budget | J17: Commercial | K17: Mainland | L17: CPO Operations | M17: Sales Team | N17: East 2 | O17: East 2 | P17: 东二区 | S17: =SUMIFS('Sales HC by Dept & T&E Segment'!V:V,'Sales HC by Dept & T&E Segment'!$F:$F,$P17,'Sales HC by Dept & T&E Segment'!$G:$G,$G17) -> 265000 | T17: =SUMIFS('Sales HC by Dept & T&E Segment'!W:W,'Sales HC by Dept & T&E Segment'!$F:$F,$P17,'Sales HC by Dept & T&E Segment'!$G:$G,$G17) -> 265000 | U17: =SUMIFS('Sales HC by Dept & T&E Segment'!X:X,'Sales HC by Dept & T&E Segment'!$F:$F,$P17,'Sales HC by Dept & T&E Segment'!$G:$G,$G17) -> 265000 | V17: =SUMIFS('Sales HC by Dept & T&E Segment'!Y:Y,'Sales HC by Dept & T&E Segment'!$F:$F,$P17,'Sales HC by Dept & T&E Segment'!$G:$G,$G17) -> 299000 | W17: =SUMIFS('Sales HC by Dept & T&E Segment'!Z:Z,'Sales HC by Dept & T&E Segment'!$F:$F,$P17,'Sales HC by Dept & T&E Segment'!$G:$G,$G17) -> 299000 | X17: =SUMIFS('Sales HC by Dept & T&E Segment'!AA:AA,'Sales HC by Dept & T&E Segment'!$F:$F,$P17,'Sales HC by Dept & T&E Segment'!$G:$G,$G17) -> 299000 | Y17: =SUMIFS('Sales HC by Dept & T&E Segment'!AB:AB,'Sales HC by Dept & T&E Segment'!$F:$F,$P17,'Sales HC by Dept & T&E Segment'!$G:$G,$G17) -> 299000 | Z17: =SUMIFS('Sales HC by Dept & T&E Segment'!AC:AC,'Sales HC by Dept & T&E Segment'!$F:$F,$P17,'Sales HC by Dept & T&E Segment'!$G:$G,$G17) -> 299000 | AA17: =SUMIFS('Sales HC by Dept & T&E Segment'!AD:AD,'Sales HC by Dept & T&E Segment'!$F:$F,$P17,'Sales HC by Dept & T&E Segment'!$G:$G,$G17) -> 299000 | AB17: =SUMIFS('Sales HC by Dept & T&E Segment'!AE:AE,'Sales HC by Dept & T&E Segment'!$F:$F,$P17,'Sales HC by Dept & T&E Segment'!$G:$G,$G17) -> 299000 | AC17: =SUMIFS('Sales HC by Dept & T&E Segment'!AF:AF,'Sales HC by Dept & T&E Segment'!$F:$F,$P17,'Sales HC by Dept & T&E Segment'!$G:$G,$G17) -> 299000 | AD17: =SUMIFS('Sales HC by Dept & T&E Segment'!AG:AG,'Sales HC by Dept & T&E Segment'!$F:$F,$P17,'Sales HC by Dept & T&E Segment'!$G:$G,$G17) -> 299000 | AE17: =SUM(S17:AD17) -> 3486000 | AI17: =SUM(S17:U17) -> 795000 | AJ17: =SUM(V17:X17) -> 897000 | AK17: =SUM(Y17:AA17) -> 897000 | AL17: =SUM(AB17:AD17) -> 897000 | AM17: =SUM(AI17:AL17) -> 3486000 | AN17: =AM17-AE17 -> 0 | AP17: =SUM(AI17:AJ17) -> 1692000 | AQ17: =SUM(AK17:AL17) -> 1794000 | AR17: =AP17+AQ17-AM17 -> 0
B18: C110102302 | C18: 10102302 | D18: 东三区-Nefecon | E18: T&E | F18: T&E | G18: Nefecon | H18: 2026 | I18: Budget | J18: Commercial | K18: Mainland | L18: CPO Operations | M18: Sales Team | N18: East 3 | O18: East 3 | P18: 东三区 | S18: =SUMIFS('Sales HC by Dept & T&E Segment'!V:V,'Sales HC by Dept & T&E Segment'!$F:$F,$P18,'Sales HC by Dept & T&E Segment'!$G:$G,$G18) -> 183000 | T18: =SUMIFS('Sales HC by Dept & T&E Segment'!W:W,'Sales HC by Dept & T&E Segment'!$F:$F,$P18,'Sales HC by Dept & T&E Segment'!$G:$G,$G18) -> 183000 | U18: =SUMIFS('Sales HC by Dept & T&E Segment'!X:X,'Sales HC by Dept & T&E Segment'!$F:$F,$P18,'Sales HC by Dept & T&E Segment'!$G:$G,$G18) -> 183000 | V18: =SUMIFS('Sales HC by Dept & T&E Segment'!Y:Y,'Sales HC by Dept & T&E Segment'!$F:$F,$P18,'Sales HC by Dept & T&E Segment'!$G:$G,$G18) -> 223000 | W18: =SUMIFS('Sales HC by Dept & T&E Segment'!Z:Z,'Sales HC by Dept & T&E Segment'!$F:$F,$P18,'Sales HC by Dept & T&E Segment'!$G:$G,$G18) -> 223000 | X18: =SUMIFS('Sales HC by Dept & T&E Segment'!AA:AA,'Sales HC by Dept & T&E Segment'!$F:$F,$P18,'Sales HC by Dept & T&E Segment'!$G:$G,$G18) -> 223000 | Y18: =SUMIFS('Sales HC by Dept & T&E Segment'!AB:AB,'Sales HC by Dept & T&E Segment'!$F:$F,$P18,'Sales HC by Dept & T&E Segment'!$G:$G,$G18) -> 223000 | Z18: =SUMIFS('Sales HC by Dept & T&E Segment'!AC:AC,'Sales HC by Dept & T&E Segment'!$F:$F,$P18,'Sales HC by Dept & T&E Segment'!$G:$G,$G18) -> 223000 | AA18: =SUMIFS('Sales HC by Dept & T&E Segment'!AD:AD,'Sales HC by Dept & T&E Segment'!$F:$F,$P18,'Sales HC by Dept & T&E Segment'!$G:$G,$G18) -> 223000 | AB18: =SUMIFS('Sales HC by Dept & T&E Segment'!AE:AE,'Sales HC by Dept & T&E Segment'!$F:$F,$P18,'Sales HC by Dept & T&E Segment'!$G:$G,$G18) -> 223000 | AC18: =SUMIFS('Sales HC by Dept & T&E Segment'!AF:AF,'Sales HC by Dept & T&E Segment'!$F:$F,$P18,'Sales HC by Dept & T&E Segment'!$G:$G,$G18) -> 223000 | AD18: =SUMIFS('Sales HC by Dept & T&E Segment'!AG:AG,'Sales HC by Dept & T&E Segment'!$F:$F,$P18,'Sales HC by Dept & T&E Segment'!$G:$G,$G18) -> 223000 | AE18: =SUM(S18:AD18) -> 2556000 | AI18: =SUM(S18:U18) -> 549000 | AJ18: =SUM(V18:X18) -> 669000 | AK18: =SUM(Y18:AA18) -> 669000 | AL18: =SUM(AB18:AD18) -> 669000 | AM18: =SUM(AI18:AL18) -> 2556000 | AN18: =AM18-AE18 -> 0 | AP18: =SUM(AI18:AJ18) -> 1218000 | AQ18: =SUM(AK18:AL18) -> 1338000 | AR18: =AP18+AQ18-AM18 -> 0
B19: C110103102 | C19: 10103102 | D19: 华中区-Nefecon | E19: T&E | F19: T&E | G19: Nefecon | H19: 2026 | I19: Budget | J19: Commercial | K19: Mainland | L19: CPO Operations | M19: Sales Team | N19: Central | O19: Central | P19: 华中区 | S19: =SUMIFS('Sales HC by Dept & T&E Segment'!V:V,'Sales HC by Dept & T&E Segment'!$F:$F,$P19,'Sales HC by Dept & T&E Segment'!$G:$G,$G19) -> 246000 | T19: =SUMIFS('Sales HC by Dept & T&E Segment'!W:W,'Sales HC by Dept & T&E Segment'!$F:$F,$P19,'Sales HC by Dept & T&E Segment'!$G:$G,$G19) -> 246000 | U19: =SUMIFS('Sales HC by Dept & T&E Segment'!X:X,'Sales HC by Dept & T&E Segment'!$F:$F,$P19,'Sales HC by Dept & T&E Segment'!$G:$G,$G19) -> 246000 | V19: =SUMIFS('Sales HC by Dept & T&E Segment'!Y:Y,'Sales HC by Dept & T&E Segment'!$F:$F,$P19,'Sales HC by Dept & T&E Segment'!$G:$G,$G19) -> 300000 | W19: =SUMIFS('Sales HC by Dept & T&E Segment'!Z:Z,'Sales HC by Dept & T&E Segment'!$F:$F,$P19,'Sales HC by Dept & T&E Segment'!$G:$G,$G19) -> 300000 | X19: =SUMIFS('Sales HC by Dept & T&E Segment'!AA:AA,'Sales HC by Dept & T&E Segment'!$F:$F,$P19,'Sales HC by Dept & T&E Segment'!$G:$G,$G19) -> 300000 | Y19: =SUMIFS('Sales HC by Dept & T&E Segment'!AB:AB,'Sales HC by Dept & T&E Segment'!$F:$F,$P19,'Sales HC by Dept & T&E Segment'!$G:$G,$G19) -> 300000 | Z19: =SUMIFS('Sales HC by Dept & T&E Segment'!AC:AC,'Sales HC by Dept & T&E Segment'!$F:$F,$P19,'Sales HC by Dept & T&E Segment'!$G:$G,$G19) -> 300000 | AA19: =SUMIFS('Sales HC by Dept & T&E Segment'!AD:AD,'Sales HC by Dept & T&E Segment'!$F:$F,$P19,'Sales HC by Dept & T&E Segment'!$G:$G,$G19) -> 300000 | AB19: =SUMIFS('Sales HC by Dept & T&E Segment'!AE:AE,'Sales HC by Dept & T&E Segment'!$F:$F,$P19,'Sales HC by Dept & T&E Segment'!$G:$G,$G19) -> 300000 | AC19: =SUMIFS('Sales HC by Dept & T&E Segment'!AF:AF,'Sales HC by Dept & T&E Segment'!$F:$F,$P19,'Sales HC by Dept & T&E Segment'!$G:$G,$G19) -> 300000 | AD19: =SUMIFS('Sales HC by Dept & T&E Segment'!AG:AG,'Sales HC by Dept & T&E Segment'!$F:$F,$P19,'Sales HC by Dept & T&E Segment'!$G:$G,$G19) -> 300000 | AE19: =SUM(S19:AD19) -> 3438000 | AI19: =SUM(S19:U19) -> 738000 | AJ19: =SUM(V19:X19) -> 900000 | AK19: =SUM(Y19:AA19) -> 900000 | AL19: =SUM(AB19:AD19) -> 900000 | AM19: =SUM(AI19:AL19) -> 3438000 | AN19: =AM19-AE19 -> 0 | AP19: =SUM(AI19:AJ19) -> 1638000 | AQ19: =SUM(AK19:AL19) -> 1800000 | AR19: =AP19+AQ19-AM19 -> 0
B20: C110106102 | C20: 10106102 | D20: 东北区-Nefecon | E20: T&E | F20: T&E | G20: Nefecon | H20: 2026 | I20: Budget | J20: Commercial | K20: Mainland | L20: CPO Operations | M20: Sales Team | N20: Northeast | O20: Northeast | P20: 东北区 | S20: =SUMIFS('Sales HC by Dept & T&E Segment'!V:V,'Sales HC by Dept & T&E Segment'!$F:$F,$P20,'Sales HC by Dept & T&E Segment'!$G:$G,$G20) -> 124000 | T20: =SUMIFS('Sales HC by Dept & T&E Segment'!W:W,'Sales HC by Dept & T&E Segment'!$F:$F,$P20,'Sales HC by Dept & T&E Segment'!$G:$G,$G20) -> 124000 | U20: =SUMIFS('Sales HC by Dept & T&E Segment'!X:X,'Sales HC by Dept & T&E Segment'!$F:$F,$P20,'Sales HC by Dept & T&E Segment'!$G:$G,$G20) -> 124000 | V20: =SUMIFS('Sales HC by Dept & T&E Segment'!Y:Y,'Sales HC by Dept & T&E Segment'!$F:$F,$P20,'Sales HC by Dept & T&E Segment'!$G:$G,$G20) -> 159000 | W20: =SUMIFS('Sales HC by Dept & T&E Segment'!Z:Z,'Sales HC by Dept & T&E Segment'!$F:$F,$P20,'Sales HC by Dept & T&E Segment'!$G:$G,$G20) -> 159000 | X20: =SUMIFS('Sales HC by Dept & T&E Segment'!AA:AA,'Sales HC by Dept & T&E Segment'!$F:$F,$P20,'Sales HC by Dept & T&E Segment'!$G:$G,$G20) -> 159000 | Y20: =SUMIFS('Sales HC by Dept & T&E Segment'!AB:AB,'Sales HC by Dept & T&E Segment'!$F:$F,$P20,'Sales HC by Dept & T&E Segment'!$G:$G,$G20) -> 159000 | Z20: =SUMIFS('Sales HC by Dept & T&E Segment'!AC:AC,'Sales HC by Dept & T&E Segment'!$F:$F,$P20,'Sales HC by Dept & T&E Segment'!$G:$G,$G20) -> 159000 | AA20: =SUMIFS('Sales HC by Dept & T&E Segment'!AD:AD,'Sales HC by Dept & T&E Segment'!$F:$F,$P20,'Sales HC by Dept & T&E Segment'!$G:$G,$G20) -> 159000 | AB20: =SUMIFS('Sales HC by Dept & T&E Segment'!AE:AE,'Sales HC by Dept & T&E Segment'!$F:$F,$P20,'Sales HC by Dept & T&E Segment'!$G:$G,$G20) -> 159000 | AC20: =SUMIFS('Sales HC by Dept & T&E Segment'!AF:AF,'Sales HC by Dept & T&E Segment'!$F:$F,$P20,'Sales HC by Dept & T&E Segment'!$G:$G,$G20) -> 159000 | AD20: =SUMIFS('Sales HC by Dept & T&E Segment'!AG:AG,'Sales HC by Dept & T&E Segment'!$F:$F,$P20,'Sales HC by Dept & T&E Segment'!$G:$G,$G20) -> 159000 | AE20: =SUM(S20:AD20) -> 1803000 | AI20: =SUM(S20:U20) -> 372000 | AJ20: =SUM(V20:X20) -> 477000 | AK20: =SUM(Y20:AA20) -> 477000 | AL20: =SUM(AB20:AD20) -> 477000 | AM20: =SUM(AI20:AL20) -> 1803000 | AN20: =AM20-AE20 -> 0 | AP20: =SUM(AI20:AJ20) -> 849000 | AQ20: =SUM(AK20:AL20) -> 954000 | AR20: =AP20+AQ20-AM20 -> 0
B21: C110105102 | C21: 10105102 | D21: 南区-Nefecon | E21: T&E | F21: T&E | G21: Nefecon | H21: 2026 | I21: Budget | J21: Commercial | K21: Mainland | L21: CPO Operations | M21: Sales Team | N21: South | O21: South | P21: 南区 | S21: =SUMIFS('Sales HC by Dept & T&E Segment'!V:V,'Sales HC by Dept & T&E Segment'!$F:$F,$P21,'Sales HC by Dept & T&E Segment'!$G:$G,$G21) -> 226000 | T21: =SUMIFS('Sales HC by Dept & T&E Segment'!W:W,'Sales HC by Dept & T&E Segment'!$F:$F,$P21,'Sales HC by Dept & T&E Segment'!$G:$G,$G21) -> 226000 | U21: =SUMIFS('Sales HC by Dept & T&E Segment'!X:X,'Sales HC by Dept & T&E Segment'!$F:$F,$P21,'Sales HC by Dept & T&E Segment'!$G:$G,$G21) -> 226000 | V21: =SUMIFS('Sales HC by Dept & T&E Segment'!Y:Y,'Sales HC by Dept & T&E Segment'!$F:$F,$P21,'Sales HC by Dept & T&E Segment'!$G:$G,$G21) -> 259000 | W21: =SUMIFS('Sales HC by Dept & T&E Segment'!Z:Z,'Sales HC by Dept & T&E Segment'!$F:$F,$P21,'Sales HC by Dept & T&E Segment'!$G:$G,$G21) -> 259000 | X21: =SUMIFS('Sales HC by Dept & T&E Segment'!AA:AA,'Sales HC by Dept & T&E Segment'!$F:$F,$P21,'Sales HC by Dept & T&E Segment'!$G:$G,$G21) -> 259000 | Y21: =SUMIFS('Sales HC by Dept & T&E Segment'!AB:AB,'Sales HC by Dept & T&E Segment'!$F:$F,$P21,'Sales HC by Dept & T&E Segment'!$G:$G,$G21) -> 259000 | Z21: =SUMIFS('Sales HC by Dept & T&E Segment'!AC:AC,'Sales HC by Dept & T&E Segment'!$F:$F,$P21,'Sales HC by Dept & T&E Segment'!$G:$G,$G21) -> 259000 | AA21: =SUMIFS('Sales HC by Dept & T&E Segment'!AD:AD,'Sales HC by Dept & T&E Segment'!$F:$F,$P21,'Sales HC by Dept & T&E Segment'!$G:$G,$G21) -> 259000 | AB21: =SUMIFS('Sales HC by Dept & T&E Segment'!AE:AE,'Sales HC by Dept & T&E Segment'!$F:$F,$P21,'Sales HC by Dept & T&E Segment'!$G:$G,$G21) -> 259000 | AC21: =SUMIFS('Sales HC by Dept & T&E Segment'!AF:AF,'Sales HC by Dept & T&E Segment'!$F:$F,$P21,'Sales HC by Dept & T&E Segment'!$G:$G,$G21) -> 259000 | AD21: =SUMIFS('Sales HC by Dept & T&E Segment'!AG:AG,'Sales HC by Dept & T&E Segment'!$F:$F,$P21,'Sales HC by Dept & T&E Segment'!$G:$G,$G21) -> 259000 | AE21: =SUM(S21:AD21) -> 3009000 | AI21: =SUM(S21:U21) -> 678000 | AJ21: =SUM(V21:X21) -> 777000 | AK21: =SUM(Y21:AA21) -> 777000 | AL21: =SUM(AB21:AD21) -> 777000 | AM21: =SUM(AI21:AL21) -> 3009000 | AN21: =AM21-AE21 -> 0 | AP21: =SUM(AI21:AJ21) -> 1455000 | AQ21: =SUM(AK21:AL21) -> 1554000 | AR21: =AP21+AQ21-AM21 -> 0
B22: C110107102 | C22: 10107102 | D22: 西区-Nefecon | E22: T&E | F22: T&E | G22: Nefecon | H22: 2026 | I22: Budget | J22: Commercial | K22: Mainland | L22: CPO Operations | M22: Sales Team | N22: West | O22: West | P22: 西区 | S22: =SUMIFS('Sales HC by Dept & T&E Segment'!V:V,'Sales HC by Dept & T&E Segment'!$F:$F,$P22,'Sales HC by Dept & T&E Segment'!$G:$G,$G22) -> 197000 | T22: =SUMIFS('Sales HC by Dept & T&E Segment'!W:W,'Sales HC by Dept & T&E Segment'!$F:$F,$P22,'Sales HC by Dept & T&E Segment'!$G:$G,$G22) -> 197000 | U22: =SUMIFS('Sales HC by Dept & T&E Segment'!X:X,'Sales HC by Dept & T&E Segment'!$F:$F,$P22,'Sales HC by Dept & T&E Segment'!$G:$G,$G22) -> 197000 | V22: =SUMIFS('Sales HC by Dept & T&E Segment'!Y:Y,'Sales HC by Dept & T&E Segment'!$F:$F,$P22,'Sales HC by Dept & T&E Segment'!$G:$G,$G22) -> 237000 | W22: =SUMIFS('Sales HC by Dept & T&E Segment'!Z:Z,'Sales HC by Dept & T&E Segment'!$F:$F,$P22,'Sales HC by Dept & T&E Segment'!$G:$G,$G22) -> 237000 | X22: =SUMIFS('Sales HC by Dept & T&E Segment'!AA:AA,'Sales HC by Dept & T&E Segment'!$F:$F,$P22,'Sales HC by Dept & T&E Segment'!$G:$G,$G22) -> 237000 | Y22: =SUMIFS('Sales HC by Dept & T&E Segment'!AB:AB,'Sales HC by Dept & T&E Segment'!$F:$F,$P22,'Sales HC by Dept & T&E Segment'!$G:$G,$G22) -> 237000 | Z22: =SUMIFS('Sales HC by Dept & T&E Segment'!AC:AC,'Sales HC by Dept & T&E Segment'!$F:$F,$P22,'Sales HC by Dept & T&E Segment'!$G:$G,$G22) -> 237000 | AA22: =SUMIFS('Sales HC by Dept & T&E Segment'!AD:AD,'Sales HC by Dept & T&E Segment'!$F:$F,$P22,'Sales HC by Dept & T&E Segment'!$G:$G,$G22) -> 237000 | AB22: =SUMIFS('Sales HC by Dept & T&E Segment'!AE:AE,'Sales HC by Dept & T&E Segment'!$F:$F,$P22,'Sales HC by Dept & T&E Segment'!$G:$G,$G22) -> 237000 | AC22: =SUMIFS('Sales HC by Dept & T&E Segment'!AF:AF,'Sales HC by Dept & T&E Segment'!$F:$F,$P22,'Sales HC by Dept & T&E Segment'!$G:$G,$G22) -> 237000 | AD22: =SUMIFS('Sales HC by Dept & T&E Segment'!AG:AG,'Sales HC by Dept & T&E Segment'!$F:$F,$P22,'Sales HC by Dept & T&E Segment'!$G:$G,$G22) -> 237000 | AE22: =SUM(S22:AD22) -> 2724000 | AG22: =SUM(AE13:AE22) -> 25707000 | AH22: =AG22-'Sales HC by Dept & T&E Segment'!S99 -> 0 | AI22: =SUM(S22:U22) -> 591000 | AJ22: =SUM(V22:X22) -> 711000 | AK22: =SUM(Y22:AA22) -> 711000 | AL22: =SUM(AB22:AD22) -> 711000 | AM22: =SUM(AI22:AL22) -> 2724000 | AN22: =AM22-AE22 -> 0 | AP22: =SUM(AI22:AJ22) -> 1302000 | AQ22: =SUM(AK22:AL22) -> 1422000 | AR22: =AP22+AQ22-AM22 -> 0
B23: C110110100 | C23: 10110100 | D23: Velsipity Sales | E23: T&E | F23: T&E | G23: Velsipity | H23: 2026 | I23: Budget | J23: Commercial | K23: Mainland | L23: CPO Operations | M23: Sales Team | N23: Velsipity Sales | O23: Velsipity Sales | P23: Velsipity Sales | S23: 539000 | T23: 539000 | U23: 539000 | V23: 639000 | W23: 639000 | X23: 639000 | Y23: 839000 | Z23: 839000 | AA23: 839000 | AB23: 1239000 | AC23: 1239000 | AD23: 1239000 | AE23: =SUM(S23:AD23) -> 9768000 | AG23: =AE23 -> 9768000 | AH23: =AE23-'Sales HC by Dept & T&E Segment'!S5 -> 0 | AI23: =SUM(S23:U23) -> 1617000 | AJ23: =SUM(V23:X23) -> 1917000 | AK23: =SUM(Y23:AA23) -> 2517000 | AL23: =SUM(AB23:AD23) -> 3717000 | AM23: =SUM(AI23:AL23) -> 9768000 | AN23: =AM23-AE23 -> 0 | AP23: =SUM(AI23:AJ23) -> 3534000 | AQ23: =SUM(AK23:AL23) -> 6234000 | AR23: =AP23+AQ23-AM23 -> 0
B25: C110005300 | C25: 10005300 | D25: CPO General | E25: T&E | F25: T&E | G25: Nefecon | H25: 2026 | I25: Budget | J25: Commercial | K25: Mainland | L25: CPO Operations | M25: CPO General | N25: CPO General | O25: CPO General | P25: CPO General | Q25: T&E Buffer | S25: 12604.167 | T25: 12604.167 | U25: 12604.167 | V25: 12604.167 | W25: 12604.167 | X25: 12604.167 | Y25: 12604.167 | Z25: 12604.167 | AA25: 12604.167 | AB25: 12604.167 | AC25: 12604.167 | AD25: 12604.167 | AE25: =SUM(S25:AD25) -> 151250 | AI25: =SUM(S25:U25) -> 37812.5 | AJ25: =SUM(V25:X25) -> 37812.5 | AK25: =SUM(Y25:AA25) -> 37812.5 | AL25: =SUM(AB25:AD25) -> 37812.5 | AM25: =SUM(AI25:AL25) -> 151250 | AN25: =AM25-AE25 -> 0 | AP25: =SUM(AI25:AJ25) -> 75625 | AQ25: =SUM(AK25:AL25) -> 75625 | AR25: =AP25+AQ25-AM25 -> 0
B29: CC1 | C29: CC2 | D29: Dept Name | E29: FP&A L1 | F29: FP&A L2 | G29: Brand | H29: Year | I29: Data Type | J29: Mgt Report L1 | K29: Mgt Report L2 | L29: Mgt Report L3 | M29: Mgt Report L4 | N29: Mgt Report L5 | O29: Mgt Report L6 | P29: CN Name | Q29: Note1 | R29: Note2 | S29: Jan | T29: Feb | U29: Mar | V29: Apr | W29: May | X29: Jun | Y29: Jul | Z29: Aug | AA29: Sep | AB29: Oct | AC29: Nov | AD29: Dec | AE29: FY
B30: C110101101 | C30: 10101101 | D30: 北一区-Xerava | E30: A&P | F30: A&P | G30: Xerava | H30: 2026 | I30: Budget | J30: Commercial | K30: Mainland | L30: CPO Operations | M30: Sales Team | N30: North 1 | O30: North 1 | P30: 北一区 | Q30: 科室会 | R30: 科室会 | S30: =SUMIFS('Sales HC by Dept & T&E Segment'!AL:AL,'Sales HC by Dept & T&E Segment'!$F:$F,$P30,'Sales HC by Dept & T&E Segment'!$G:$G,$G30) -> 75000 | T30: =SUMIFS('Sales HC by Dept & T&E Segment'!AM:AM,'Sales HC by Dept & T&E Segment'!$F:$F,$P30,'Sales HC by Dept & T&E Segment'!$G:$G,$G30) -> 75000 | U30: =SUMIFS('Sales HC by Dept & T&E Segment'!AN:AN,'Sales HC by Dept & T&E Segment'!$F:$F,$P30,'Sales HC by Dept & T&E Segment'!$G:$G,$G30) -> 75000 | V30: =SUMIFS('Sales HC by Dept & T&E Segment'!AO:AO,'Sales HC by Dept & T&E Segment'!$F:$F,$P30,'Sales HC by Dept & T&E Segment'!$G:$G,$G30) -> 75000 | W30: =SUMIFS('Sales HC by Dept & T&E Segment'!AP:AP,'Sales HC by Dept & T&E Segment'!$F:$F,$P30,'Sales HC by Dept & T&E Segment'!$G:$G,$G30) -> 75000 | X30: =SUMIFS('Sales HC by Dept & T&E Segment'!AQ:AQ,'Sales HC by Dept & T&E Segment'!$F:$F,$P30,'Sales HC by Dept & T&E Segment'!$G:$G,$G30) -> 75000 | Y30: =SUMIFS('Sales HC by Dept & T&E Segment'!AR:AR,'Sales HC by Dept & T&E Segment'!$F:$F,$P30,'Sales HC by Dept & T&E Segment'!$G:$G,$G30) -> 75000 | Z30: =SUMIFS('Sales HC by Dept & T&E Segment'!AS:AS,'Sales HC by Dept & T&E Segment'!$F:$F,$P30,'Sales HC by Dept & T&E Segment'!$G:$G,$G30) -> 75000 | AA30: =SUMIFS('Sales HC by Dept & T&E Segment'!AT:AT,'Sales HC by Dept & T&E Segment'!$F:$F,$P30,'Sales HC by Dept & T&E Segment'!$G:$G,$G30) -> 75000 | AB30: =SUMIFS('Sales HC by Dept & T&E Segment'!AU:AU,'Sales HC by Dept & T&E Segment'!$F:$F,$P30,'Sales HC by Dept & T&E Segment'!$G:$G,$G30) -> 75000 | AC30: =SUMIFS('Sales HC by Dept & T&E Segment'!AV:AV,'Sales HC by Dept & T&E Segment'!$F:$F,$P30,'Sales HC by Dept & T&E Segment'!$G:$G,$G30) -> 75000 | AD30: =SUMIFS('Sales HC by Dept & T&E Segment'!AW:AW,'Sales HC by Dept & T&E Segment'!$F:$F,$P30,'Sales HC by Dept & T&E Segment'!$G:$G,$G30) -> 75000 | AE30: =SUM(S30:AD30) -> 900000 | AI30: =SUM(S30:U30) -> 225000 | AJ30: =SUM(V30:X30) -> 225000 | AK30: =SUM(Y30:AA30) -> 225000 | AL30: =SUM(AB30:AD30) -> 225000 | AM30: =SUM(AI30:AL30) -> 900000 | AN30: =AM30-AE30 -> 0 | AP30: =SUM(AI30:AJ30) -> 450000 | AQ30: =SUM(AK30:AL30) -> 450000 | AR30: =AP30+AQ30-AM30 -> 0
B31: C110101201 | C31: 10101201 | D31: 北二区-Xerava | E31: A&P | F31: A&P | G31: Xerava | H31: 2026 | I31: Budget | J31: Commercial | K31: Mainland | L31: CPO Operations | M31: Sales Team | N31: North 2 | O31: North 2 | P31: 北二区 | Q31: 科室会 | R31: 科室会 | S31: =SUMIFS('Sales HC by Dept & T&E Segment'!AL:AL,'Sales HC by Dept & T&E Segment'!$F:$F,$P31,'Sales HC by Dept & T&E Segment'!$G:$G,$G31) -> 30000 | T31: =SUMIFS('Sales HC by Dept & T&E Segment'!AM:AM,'Sales HC by Dept & T&E Segment'!$F:$F,$P31,'Sales HC by Dept & T&E Segment'!$G:$G,$G31) -> 30000 | U31: =SUMIFS('Sales HC by Dept & T&E Segment'!AN:AN,'Sales HC by Dept & T&E Segment'!$F:$F,$P31,'Sales HC by Dept & T&E Segment'!$G:$G,$G31) -> 30000 | V31: =SUMIFS('Sales HC by Dept & T&E Segment'!AO:AO,'Sales HC by Dept & T&E Segment'!$F:$F,$P31,'Sales HC by Dept & T&E Segment'!$G:$G,$G31) -> 30000 | W31: =SUMIFS('Sales HC by Dept & T&E Segment'!AP:AP,'Sales HC by Dept & T&E Segment'!$F:$F,$P31,'Sales HC by Dept & T&E Segment'!$G:$G,$G31) -> 30000 | X31: =SUMIFS('Sales HC by Dept & T&E Segment'!AQ:AQ,'Sales HC by Dept & T&E Segment'!$F:$F,$P31,'Sales HC by Dept & T&E Segment'!$G:$G,$G31) -> 30000 | Y31: =SUMIFS('Sales HC by Dept & T&E Segment'!AR:AR,'Sales HC by Dept & T&E Segment'!$F:$F,$P31,'Sales HC by Dept & T&E Segment'!$G:$G,$G31) -> 30000 | Z31: =SUMIFS('Sales HC by Dept & T&E Segment'!AS:AS,'Sales HC by Dept & T&E Segment'!$F:$F,$P31,'Sales HC by Dept & T&E Segment'!$G:$G,$G31) -> 30000 | AA31: =SUMIFS('Sales HC by Dept & T&E Segment'!AT:AT,'Sales HC by Dept & T&E Segment'!$F:$F,$P31,'Sales HC by Dept & T&E Segment'!$G:$G,$G31) -> 30000 | AB31: =SUMIFS('Sales HC by Dept & T&E Segment'!AU:AU,'Sales HC by Dept & T&E Segment'!$F:$F,$P31,'Sales HC by Dept & T&E Segment'!$G:$G,$G31) -> 30000 | AC31: =SUMIFS('Sales HC by Dept & T&E Segment'!AV:AV,'Sales HC by Dept & T&E Segment'!$F:$F,$P31,'Sales HC by Dept & T&E Segment'!$G:$G,$G31) -> 30000 | AD31: =SUMIFS('Sales HC by Dept & T&E Segment'!AW:AW,'Sales HC by Dept & T&E Segment'!$F:$F,$P31,'Sales HC by Dept & T&E Segment'!$G:$G,$G31) -> 30000 | AE31: =SUM(S31:AD31) -> 360000 | AI31: =SUM(S31:U31) -> 90000 | AJ31: =SUM(V31:X31) -> 90000 | AK31: =SUM(Y31:AA31) -> 90000 | AL31: =SUM(AB31:AD31) -> 90000 | AM31: =SUM(AI31:AL31) -> 360000 | AN31: =AM31-AE31 -> 0 | AP31: =SUM(AI31:AJ31) -> 180000 | AQ31: =SUM(AK31:AL31) -> 180000 | AR31: =AP31+AQ31-AM31 -> 0
B32: C110101301 | C32: 10101301 | D32: 北三区-Xerava | E32: A&P | F32: A&P | G32: Xerava | H32: 2026 | I32: Budget | J32: Commercial | K32: Mainland | L32: CPO Operations | M32: Sales Team | N32: North 3 | O32: North 3 | P32: 北三区 | Q32: 科室会 | R32: 科室会 | S32: =SUMIFS('Sales HC by Dept & T&E Segment'!AL:AL,'Sales HC by Dept & T&E Segment'!$F:$F,$P32,'Sales HC by Dept & T&E Segment'!$G:$G,$G32) -> 48000 | T32: =SUMIFS('Sales HC by Dept & T&E Segment'!AM:AM,'Sales HC by Dept & T&E Segment'!$F:$F,$P32,'Sales HC by Dept & T&E Segment'!$G:$G,$G32) -> 48000 | U32: =SUMIFS('Sales HC by Dept & T&E Segment'!AN:AN,'Sales HC by Dept & T&E Segment'!$F:$F,$P32,'Sales HC by Dept & T&E Segment'!$G:$G,$G32) -> 48000 | V32: =SUMIFS('Sales HC by Dept & T&E Segment'!AO:AO,'Sales HC by Dept & T&E Segment'!$F:$F,$P32,'Sales HC by Dept & T&E Segment'!$G:$G,$G32) -> 48000 | W32: =SUMIFS('Sales HC by Dept & T&E Segment'!AP:AP,'Sales HC by Dept & T&E Segment'!$F:$F,$P32,'Sales HC by Dept & T&E Segment'!$G:$G,$G32) -> 48000 | X32: =SUMIFS('Sales HC by Dept & T&E Segment'!AQ:AQ,'Sales HC by Dept & T&E Segment'!$F:$F,$P32,'Sales HC by Dept & T&E Segment'!$G:$G,$G32) -> 48000 | Y32: =SUMIFS('Sales HC by Dept & T&E Segment'!AR:AR,'Sales HC by Dept & T&E Segment'!$F:$F,$P32,'Sales HC by Dept & T&E Segment'!$G:$G,$G32) -> 48000 | Z32: =SUMIFS('Sales HC by Dept & T&E Segment'!AS:AS,'Sales HC by Dept & T&E Segment'!$F:$F,$P32,'Sales HC by Dept & T&E Segment'!$G:$G,$G32) -> 48000 | AA32: =SUMIFS('Sales HC by Dept & T&E Segment'!AT:AT,'Sales HC by Dept & T&E Segment'!$F:$F,$P32,'Sales HC by Dept & T&E Segment'!$G:$G,$G32) -> 48000 | AB32: =SUMIFS('Sales HC by Dept & T&E Segment'!AU:AU,'Sales HC by Dept & T&E Segment'!$F:$F,$P32,'Sales HC by Dept & T&E Segment'!$G:$G,$G32) -> 48000 | AC32: =SUMIFS('Sales HC by Dept & T&E Segment'!AV:AV,'Sales HC by Dept & T&E Segment'!$F:$F,$P32,'Sales HC by Dept & T&E Segment'!$G:$G,$G32) -> 48000 | AD32: =SUMIFS('Sales HC by Dept & T&E Segment'!AW:AW,'Sales HC by Dept & T&E Segment'!$F:$F,$P32,'Sales HC by Dept & T&E Segment'!$G:$G,$G32) -> 48000 | AE32: =SUM(S32:AD32) -> 576000 | AI32: =SUM(S32:U32) -> 144000 | AJ32: =SUM(V32:X32) -> 144000 | AK32: =SUM(Y32:AA32) -> 144000 | AL32: =SUM(AB32:AD32) -> 144000 | AM32: =SUM(AI32:AL32) -> 576000 | AN32: =AM32-AE32 -> 0 | AP32: =SUM(AI32:AJ32) -> 288000 | AQ32: =SUM(AK32:AL32) -> 288000 | AR32: =AP32+AQ32-AM32 -> 0
B33: C110102101 | C33: 10102101 | D33: 东一区-Xerava | E33: A&P | F33: A&P | G33: Xerava | H33: 2026 | I33: Budget | J33: Commercial | K33: Mainland | L33: CPO Operations | M33: Sales Team | N33: East 1 | O33: East 1 | P33: 东一区 | Q33: 科室会 | R33: 科室会 | S33: =SUMIFS('Sales HC by Dept & T&E Segment'!AL:AL,'Sales HC by Dept & T&E Segment'!$F:$F,$P33,'Sales HC by Dept & T&E Segment'!$G:$G,$G33) -> 54000 | T33: =SUMIFS('Sales HC by Dept & T&E Segment'!AM:AM,'Sales HC by Dept & T&E Segment'!$F:$F,$P33,'Sales HC by Dept & T&E Segment'!$G:$G,$G33) -> 54000 | U33: =SUMIFS('Sales HC by Dept & T&E Segment'!AN:AN,'Sales HC by Dept & T&E Segment'!$F:$F,$P33,'Sales HC by Dept & T&E Segment'!$G:$G,$G33) -> 54000 | V33: =SUMIFS('Sales HC by Dept & T&E Segment'!AO:AO,'Sales HC by Dept & T&E Segment'!$F:$F,$P33,'Sales HC by Dept & T&E Segment'!$G:$G,$G33) -> 54000 | W33: =SUMIFS('Sales HC by Dept & T&E Segment'!AP:AP,'Sales HC by Dept & T&E Segment'!$F:$F,$P33,'Sales HC by Dept & T&E Segment'!$G:$G,$G33) -> 54000 | X33: =SUMIFS('Sales HC by Dept & T&E Segment'!AQ:AQ,'Sales HC by Dept & T&E Segment'!$F:$F,$P33,'Sales HC by Dept & T&E Segment'!$G:$G,$G33) -> 54000 | Y33: =SUMIFS('Sales HC by Dept & T&E Segment'!AR:AR,'Sales HC by Dept & T&E Segment'!$F:$F,$P33,'Sales HC by Dept & T&E Segment'!$G:$G,$G33) -> 54000 | Z33: =SUMIFS('Sales HC by Dept & T&E Segment'!AS:AS,'Sales HC by Dept & T&E Segment'!$F:$F,$P33,'Sales HC by Dept & T&E Segment'!$G:$G,$G33) -> 54000 | AA33: =SUMIFS('Sales HC by Dept & T&E Segment'!AT:AT,'Sales HC by Dept & T&E Segment'!$F:$F,$P33,'Sales HC by Dept & T&E Segment'!$G:$G,$G33) -> 54000 | AB33: =SUMIFS('Sales HC by Dept & T&E Segment'!AU:AU,'Sales HC by Dept & T&E Segment'!$F:$F,$P33,'Sales HC by Dept & T&E Segment'!$G:$G,$G33) -> 54000 | AC33: =SUMIFS('Sales HC by Dept & T&E Segment'!AV:AV,'Sales HC by Dept & T&E Segment'!$F:$F,$P33,'Sales HC by Dept & T&E Segment'!$G:$G,$G33) -> 54000 | AD33: =SUMIFS('Sales HC by Dept & T&E Segment'!AW:AW,'Sales HC by Dept & T&E Segment'!$F:$F,$P33,'Sales HC by Dept & T&E Segment'!$G:$G,$G33) -> 54000 | AE33: =SUM(S33:AD33) -> 648000 | AI33: =SUM(S33:U33) -> 162000 | AJ33: =SUM(V33:X33) -> 162000 | AK33: =SUM(Y33:AA33) -> 162000 | AL33: =SUM(AB33:AD33) -> 162000 | AM33: =SUM(AI33:AL33) -> 648000 | AN33: =AM33-AE33 -> 0 | AP33: =SUM(AI33:AJ33) -> 324000 | AQ33: =SUM(AK33:AL33) -> 324000 | AR33: =AP33+AQ33-AM33 -> 0
B34: C110102201 | C34: 10102201 | D34: 东二区-Xerava | E34: A&P | F34: A&P | G34: Xerava | H34: 2026 | I34: Budget | J34: Commercial | K34: Mainland | L34: CPO Operations | M34: Sales Team | N34: East 2 | O34: East 2 | P34: 东二区 | Q34: 科室会 | R34: 科室会 | S34: =SUMIFS('Sales HC by Dept & T&E Segment'!AL:AL,'Sales HC by Dept & T&E Segment'!$F:$F,$P34,'Sales HC by Dept & T&E Segment'!$G:$G,$G34) -> 57000 | T34: =SUMIFS('Sales HC by Dept & T&E Segment'!AM:AM,'Sales HC by Dept & T&E Segment'!$F:$F,$P34,'Sales HC by Dept & T&E Segment'!$G:$G,$G34) -> 57000 | U34: =SUMIFS('Sales HC by Dept & T&E Segment'!AN:AN,'Sales HC by Dept & T&E Segment'!$F:$F,$P34,'Sales HC by Dept & T&E Segment'!$G:$G,$G34) -> 57000 | V34: =SUMIFS('Sales HC by Dept & T&E Segment'!AO:AO,'Sales HC by Dept & T&E Segment'!$F:$F,$P34,'Sales HC by Dept & T&E Segment'!$G:$G,$G34) -> 57000 | W34: =SUMIFS('Sales HC by Dept & T&E Segment'!AP:AP,'Sales HC by Dept & T&E Segment'!$F:$F,$P34,'Sales HC by Dept & T&E Segment'!$G:$G,$G34) -> 57000 | X34: =SUMIFS('Sales HC by Dept & T&E Segment'!AQ:AQ,'Sales HC by Dept & T&E Segment'!$F:$F,$P34,'Sales HC by Dept & T&E Segment'!$G:$G,$G34) -> 57000 | Y34: =SUMIFS('Sales HC by Dept & T&E Segment'!AR:AR,'Sales HC by Dept & T&E Segment'!$F:$F,$P34,'Sales HC by Dept & T&E Segment'!$G:$G,$G34) -> 57000 | Z34: =SUMIFS('Sales HC by Dept & T&E Segment'!AS:AS,'Sales HC by Dept & T&E Segment'!$F:$F,$P34,'Sales HC by Dept & T&E Segment'!$G:$G,$G34) -> 57000 | AA34: =SUMIFS('Sales HC by Dept & T&E Segment'!AT:AT,'Sales HC by Dept & T&E Segment'!$F:$F,$P34,'Sales HC by Dept & T&E Segment'!$G:$G,$G34) -> 57000 | AB34: =SUMIFS('Sales HC by Dept & T&E Segment'!AU:AU,'Sales HC by Dept & T&E Segment'!$F:$F,$P34,'Sales HC by Dept & T&E Segment'!$G:$G,$G34) -> 57000 | AC34: =SUMIFS('Sales HC by Dept & T&E Segment'!AV:AV,'Sales HC by Dept & T&E Segment'!$F:$F,$P34,'Sales HC by Dept & T&E Segment'!$G:$G,$G34) -> 57000 | AD34: =SUMIFS('Sales HC by Dept & T&E Segment'!AW:AW,'Sales HC by Dept & T&E Segment'!$F:$F,$P34,'Sales HC by Dept & T&E Segment'!$G:$G,$G34) -> 57000 | AE34: =SUM(S34:AD34) -> 684000 | AI34: =SUM(S34:U34) -> 171000 | AJ34: =SUM(V34:X34) -> 171000 | AK34: =SUM(Y34:AA34) -> 171000 | AL34: =SUM(AB34:AD34) -> 171000 | AM34: =SUM(AI34:AL34) -> 684000 | AN34: =AM34-AE34 -> 0 | AP34: =SUM(AI34:AJ34) -> 342000 | AQ34: =SUM(AK34:AL34) -> 342000 | AR34: =AP34+AQ34-AM34 -> 0
B35: C110102301 | C35: 10102301 | D35: 东三区-Xerava | E35: A&P | F35: A&P | G35: Xerava | H35: 2026 | I35: Budget | J35: Commercial | K35: Mainland | L35: CPO Operations | M35: Sales Team | N35: East 3 | O35: East 3 | P35: 东三区 | Q35: 科室会 | R35: 科室会 | S35: =SUMIFS('Sales HC by Dept & T&E Segment'!AL:AL,'Sales HC by Dept & T&E Segment'!$F:$F,$P35,'Sales HC by Dept & T&E Segment'!$G:$G,$G35) -> 48000 | T35: =SUMIFS('Sales HC by Dept & T&E Segment'!AM:AM,'Sales HC by Dept & T&E Segment'!$F:$F,$P35,'Sales HC by Dept & T&E Segment'!$G:$G,$G35) -> 48000 | U35: =SUMIFS('Sales HC by Dept & T&E Segment'!AN:AN,'Sales HC by Dept & T&E Segment'!$F:$F,$P35,'Sales HC by Dept & T&E Segment'!$G:$G,$G35) -> 48000 | V35: =SUMIFS('Sales HC by Dept & T&E Segment'!AO:AO,'Sales HC by Dept & T&E Segment'!$F:$F,$P35,'Sales HC by Dept & T&E Segment'!$G:$G,$G35) -> 48000 | W35: =SUMIFS('Sales HC by Dept & T&E Segment'!AP:AP,'Sales HC by Dept & T&E Segment'!$F:$F,$P35,'Sales HC by Dept & T&E Segment'!$G:$G,$G35) -> 48000 | X35: =SUMIFS('Sales HC by Dept & T&E Segment'!AQ:AQ,'Sales HC by Dept & T&E Segment'!$F:$F,$P35,'Sales HC by Dept & T&E Segment'!$G:$G,$G35) -> 48000 | Y35: =SUMIFS('Sales HC by Dept & T&E Segment'!AR:AR,'Sales HC by Dept & T&E Segment'!$F:$F,$P35,'Sales HC by Dept & T&E Segment'!$G:$G,$G35) -> 48000 | Z35: =SUMIFS('Sales HC by Dept & T&E Segment'!AS:AS,'Sales HC by Dept & T&E Segment'!$F:$F,$P35,'Sales HC by Dept & T&E Segment'!$G:$G,$G35) -> 48000 | AA35: =SUMIFS('Sales HC by Dept & T&E Segment'!AT:AT,'Sales HC by Dept & T&E Segment'!$F:$F,$P35,'Sales HC by Dept & T&E Segment'!$G:$G,$G35) -> 48000 | AB35: =SUMIFS('Sales HC by Dept & T&E Segment'!AU:AU,'Sales HC by Dept & T&E Segment'!$F:$F,$P35,'Sales HC by Dept & T&E Segment'!$G:$G,$G35) -> 48000 | AC35: =SUMIFS('Sales HC by Dept & T&E Segment'!AV:AV,'Sales HC by Dept & T&E Segment'!$F:$F,$P35,'Sales HC by Dept & T&E Segment'!$G:$G,$G35) -> 48000 | AD35: =SUMIFS('Sales HC by Dept & T&E Segment'!AW:AW,'Sales HC by Dept & T&E Segment'!$F:$F,$P35,'Sales HC by Dept & T&E Segment'!$G:$G,$G35) -> 48000 | AE35: =SUM(S35:AD35) -> 576000 | AI35: =SUM(S35:U35) -> 144000 | AJ35: =SUM(V35:X35) -> 144000 | AK35: =SUM(Y35:AA35) -> 144000 | AL35: =SUM(AB35:AD35) -> 144000 | AM35: =SUM(AI35:AL35) -> 576000 | AN35: =AM35-AE35 -> 0 | AP35: =SUM(AI35:AJ35) -> 288000 | AQ35: =SUM(AK35:AL35) -> 288000 | AR35: =AP35+AQ35-AM35 -> 0
B36: C110103101 | C36: 10103101 | D36: 华中区-Xerava | E36: A&P | F36: A&P | G36: Xerava | H36: 2026 | I36: Budget | J36: Commercial | K36: Mainland | L36: CPO Operations | M36: Sales Team | N36: Central | O36: Central | P36: 华中区 | Q36: 科室会 | R36: 科室会 | S36: =SUMIFS('Sales HC by Dept & T&E Segment'!AL:AL,'Sales HC by Dept & T&E Segment'!$F:$F,$P36,'Sales HC by Dept & T&E Segment'!$G:$G,$G36) -> 51000 | T36: =SUMIFS('Sales HC by Dept & T&E Segment'!AM:AM,'Sales HC by Dept & T&E Segment'!$F:$F,$P36,'Sales HC by Dept & T&E Segment'!$G:$G,$G36) -> 51000 | U36: =SUMIFS('Sales HC by Dept & T&E Segment'!AN:AN,'Sales HC by Dept & T&E Segment'!$F:$F,$P36,'Sales HC by Dept & T&E Segment'!$G:$G,$G36) -> 51000 | V36: =SUMIFS('Sales HC by Dept & T&E Segment'!AO:AO,'Sales HC by Dept & T&E Segment'!$F:$F,$P36,'Sales HC by Dept & T&E Segment'!$G:$G,$G36) -> 51000 | W36: =SUMIFS('Sales HC by Dept & T&E Segment'!AP:AP,'Sales HC by Dept & T&E Segment'!$F:$F,$P36,'Sales HC by Dept & T&E Segment'!$G:$G,$G36) -> 51000 | X36: =SUMIFS('Sales HC by Dept & T&E Segment'!AQ:AQ,'Sales HC by Dept & T&E Segment'!$F:$F,$P36,'Sales HC by Dept & T&E Segment'!$G:$G,$G36) -> 51000 | Y36: =SUMIFS('Sales HC by Dept & T&E Segment'!AR:AR,'Sales HC by Dept & T&E Segment'!$F:$F,$P36,'Sales HC by Dept & T&E Segment'!$G:$G,$G36) -> 51000 | Z36: =SUMIFS('Sales HC by Dept & T&E Segment'!AS:AS,'Sales HC by Dept & T&E Segment'!$F:$F,$P36,'Sales HC by Dept & T&E Segment'!$G:$G,$G36) -> 51000 | AA36: =SUMIFS('Sales HC by Dept & T&E Segment'!AT:AT,'Sales HC by Dept & T&E Segment'!$F:$F,$P36,'Sales HC by Dept & T&E Segment'!$G:$G,$G36) -> 51000 | AB36: =SUMIFS('Sales HC by Dept & T&E Segment'!AU:AU,'Sales HC by Dept & T&E Segment'!$F:$F,$P36,'Sales HC by Dept & T&E Segment'!$G:$G,$G36) -> 51000 | AC36: =SUMIFS('Sales HC by Dept & T&E Segment'!AV:AV,'Sales HC by Dept & T&E Segment'!$F:$F,$P36,'Sales HC by Dept & T&E Segment'!$G:$G,$G36) -> 51000 | AD36: =SUMIFS('Sales HC by Dept & T&E Segment'!AW:AW,'Sales HC by Dept & T&E Segment'!$F:$F,$P36,'Sales HC by Dept & T&E Segment'!$G:$G,$G36) -> 51000 | AE36: =SUM(S36:AD36) -> 612000 | AI36: =SUM(S36:U36) -> 153000 | AJ36: =SUM(V36:X36) -> 153000 | AK36: =SUM(Y36:AA36) -> 153000 | AL36: =SUM(AB36:AD36) -> 153000 | AM36: =SUM(AI36:AL36) -> 612000 | AN36: =AM36-AE36 -> 0 | AP36: =SUM(AI36:AJ36) -> 306000 | AQ36: =SUM(AK36:AL36) -> 306000 | AR36: =AP36+AQ36-AM36 -> 0
B37: C110106101 | C37: 10106101 | D37: 东北区-Xerava | E37: A&P | F37: A&P | G37: Xerava | H37: 2026 | I37: Budget | J37: Commercial | K37: Mainland | L37: CPO Operations | M37: Sales Team | N37: Northeast | O37: Northeast | P37: 东北区 | Q37: 科室会 | R37: 科室会 | S37: =SUMIFS('Sales HC by Dept & T&E Segment'!AL:AL,'Sales HC by Dept & T&E Segment'!$F:$F,$P37,'Sales HC by Dept & T&E Segment'!$G:$G,$G37) -> 27000 | T37: =SUMIFS('Sales HC by Dept & T&E Segment'!AM:AM,'Sales HC by Dept & T&E Segment'!$F:$F,$P37,'Sales HC by Dept & T&E Segment'!$G:$G,$G37) -> 27000 | U37: =SUMIFS('Sales HC by Dept & T&E Segment'!AN:AN,'Sales HC by Dept & T&E Segment'!$F:$F,$P37,'Sales HC by Dept & T&E Segment'!$G:$G,$G37) -> 27000 | V37: =SUMIFS('Sales HC by Dept & T&E Segment'!AO:AO,'Sales HC by Dept & T&E Segment'!$F:$F,$P37,'Sales HC by Dept & T&E Segment'!$G:$G,$G37) -> 27000 | W37: =SUMIFS('Sales HC by Dept & T&E Segment'!AP:AP,'Sales HC by Dept & T&E Segment'!$F:$F,$P37,'Sales HC by Dept & T&E Segment'!$G:$G,$G37) -> 27000 | X37: =SUMIFS('Sales HC by Dept & T&E Segment'!AQ:AQ,'Sales HC by Dept & T&E Segment'!$F:$F,$P37,'Sales HC by Dept & T&E Segment'!$G:$G,$G37) -> 27000 | Y37: =SUMIFS('Sales HC by Dept & T&E Segment'!AR:AR,'Sales HC by Dept & T&E Segment'!$F:$F,$P37,'Sales HC by Dept & T&E Segment'!$G:$G,$G37) -> 27000 | Z37: =SUMIFS('Sales HC by Dept & T&E Segment'!AS:AS,'Sales HC by Dept & T&E Segment'!$F:$F,$P37,'Sales HC by Dept & T&E Segment'!$G:$G,$G37) -> 27000 | AA37: =SUMIFS('Sales HC by Dept & T&E Segment'!AT:AT,'Sales HC by Dept & T&E Segment'!$F:$F,$P37,'Sales HC by Dept & T&E Segment'!$G:$G,$G37) -> 27000 | AB37: =SUMIFS('Sales HC by Dept & T&E Segment'!AU:AU,'Sales HC by Dept & T&E Segment'!$F:$F,$P37,'Sales HC by Dept & T&E Segment'!$G:$G,$G37) -> 27000 | AC37: =SUMIFS('Sales HC by Dept & T&E Segment'!AV:AV,'Sales HC by Dept & T&E Segment'!$F:$F,$P37,'Sales HC by Dept & T&E Segment'!$G:$G,$G37) -> 27000 | AD37: =SUMIFS('Sales HC by Dept & T&E Segment'!AW:AW,'Sales HC by Dept & T&E Segment'!$F:$F,$P37,'Sales HC by Dept & T&E Segment'!$G:$G,$G37) -> 27000 | AE37: =SUM(S37:AD37) -> 324000 | AI37: =SUM(S37:U37) -> 81000 | AJ37: =SUM(V37:X37) -> 81000 | AK37: =SUM(Y37:AA37) -> 81000 | AL37: =SUM(AB37:AD37) -> 81000 | AM37: =SUM(AI37:AL37) -> 324000 | AN37: =AM37-AE37 -> 0 | AP37: =SUM(AI37:AJ37) -> 162000 | AQ37: =SUM(AK37:AL37) -> 162000 | AR37: =AP37+AQ37-AM37 -> 0
B38: C110105101 | C38: 10105101 | D38: 南区-Xerava | E38: A&P | F38: A&P | G38: Xerava | H38: 2026 | I38: Budget | J38: Commercial | K38: Mainland | L38: CPO Operations | M38: Sales Team | N38: South | O38: South | P38: 南区 | Q38: 科室会 | R38: 科室会 | S38: =SUMIFS('Sales HC by Dept & T&E Segment'!AL:AL,'Sales HC by Dept & T&E Segment'!$F:$F,$P38,'Sales HC by Dept & T&E Segment'!$G:$G,$G38) -> 63000 | T38: =SUMIFS('Sales HC by Dept & T&E Segment'!AM:AM,'Sales HC by Dept & T&E Segment'!$F:$F,$P38,'Sales HC by Dept & T&E Segment'!$G:$G,$G38) -> 63000 | U38: =SUMIFS('Sales HC by Dept & T&E Segment'!AN:AN,'Sales HC by Dept & T&E Segment'!$F:$F,$P38,'Sales HC by Dept & T&E Segment'!$G:$G,$G38) -> 63000 | V38: =SUMIFS('Sales HC by Dept & T&E Segment'!AO:AO,'Sales HC by Dept & T&E Segment'!$F:$F,$P38,'Sales HC by Dept & T&E Segment'!$G:$G,$G38) -> 63000 | W38: =SUMIFS('Sales HC by Dept & T&E Segment'!AP:AP,'Sales HC by Dept & T&E Segment'!$F:$F,$P38,'Sales HC by Dept & T&E Segment'!$G:$G,$G38) -> 63000 | X38: =SUMIFS('Sales HC by Dept & T&E Segment'!AQ:AQ,'Sales HC by Dept & T&E Segment'!$F:$F,$P38,'Sales HC by Dept & T&E Segment'!$G:$G,$G38) -> 63000 | Y38: =SUMIFS('Sales HC by Dept & T&E Segment'!AR:AR,'Sales HC by Dept & T&E Segment'!$F:$F,$P38,'Sales HC by Dept & T&E Segment'!$G:$G,$G38) -> 63000 | Z38: =SUMIFS('Sales HC by Dept & T&E Segment'!AS:AS,'Sales HC by Dept & T&E Segment'!$F:$F,$P38,'Sales HC by Dept & T&E Segment'!$G:$G,$G38) -> 63000 | AA38: =SUMIFS('Sales HC by Dept & T&E Segment'!AT:AT,'Sales HC by Dept & T&E Segment'!$F:$F,$P38,'Sales HC by Dept & T&E Segment'!$G:$G,$G38) -> 63000 | AB38: =SUMIFS('Sales HC by Dept & T&E Segment'!AU:AU,'Sales HC by Dept & T&E Segment'!$F:$F,$P38,'Sales HC by Dept & T&E Segment'!$G:$G,$G38) -> 63000 | AC38: =SUMIFS('Sales HC by Dept & T&E Segment'!AV:AV,'Sales HC by Dept & T&E Segment'!$F:$F,$P38,'Sales HC by Dept & T&E Segment'!$G:$G,$G38) -> 63000 | AD38: =SUMIFS('Sales HC by Dept & T&E Segment'!AW:AW,'Sales HC by Dept & T&E Segment'!$F:$F,$P38,'Sales HC by Dept & T&E Segment'!$G:$G,$G38) -> 63000 | AE38: =SUM(S38:AD38) -> 756000 | AI38: =SUM(S38:U38) -> 189000 | AJ38: =SUM(V38:X38) -> 189000 | AK38: =SUM(Y38:AA38) -> 189000 | AL38: =SUM(AB38:AD38) -> 189000 | AM38: =SUM(AI38:AL38) -> 756000 | AN38: =AM38-AE38 -> 0 | AP38: =SUM(AI38:AJ38) -> 378000 | AQ38: =SUM(AK38:AL38) -> 378000 | AR38: =AP38+AQ38-AM38 -> 0
B39: C110107101 | C39: 10107101 | D39: 西区-Xerava | E39: A&P | F39: A&P | G39: Xerava | H39: 2026 | I39: Budget | J39: Commercial | K39: Mainland | L39: CPO Operations | M39: Sales Team | N39: West | O39: West | P39: 西区 | Q39: 科室会 | R39: 科室会 | S39: =SUMIFS('Sales HC by Dept & T&E Segment'!AL:AL,'Sales HC by Dept & T&E Segment'!$F:$F,$P39,'Sales HC by Dept & T&E Segment'!$G:$G,$G39) -> 39000 | T39: =SUMIFS('Sales HC by Dept & T&E Segment'!AM:AM,'Sales HC by Dept & T&E Segment'!$F:$F,$P39,'Sales HC by Dept & T&E Segment'!$G:$G,$G39) -> 39000 | U39: =SUMIFS('Sales HC by Dept & T&E Segment'!AN:AN,'Sales HC by Dept & T&E Segment'!$F:$F,$P39,'Sales HC by Dept & T&E Segment'!$G:$G,$G39) -> 39000 | V39: =SUMIFS('Sales HC by Dept & T&E Segment'!AO:AO,'Sales HC by Dept & T&E Segment'!$F:$F,$P39,'Sales HC by Dept & T&E Segment'!$G:$G,$G39) -> 39000 | W39: =SUMIFS('Sales HC by Dept & T&E Segment'!AP:AP,'Sales HC by Dept & T&E Segment'!$F:$F,$P39,'Sales HC by Dept & T&E Segment'!$G:$G,$G39) -> 39000 | X39: =SUMIFS('Sales HC by Dept & T&E Segment'!AQ:AQ,'Sales HC by Dept & T&E Segment'!$F:$F,$P39,'Sales HC by Dept & T&E Segment'!$G:$G,$G39) -> 39000 | Y39: =SUMIFS('Sales HC by Dept & T&E Segment'!AR:AR,'Sales HC by Dept & T&E Segment'!$F:$F,$P39,'Sales HC by Dept & T&E Segment'!$G:$G,$G39) -> 39000 | Z39: =SUMIFS('Sales HC by Dept & T&E Segment'!AS:AS,'Sales HC by Dept & T&E Segment'!$F:$F,$P39,'Sales HC by Dept & T&E Segment'!$G:$G,$G39) -> 39000 | AA39: =SUMIFS('Sales HC by Dept & T&E Segment'!AT:AT,'Sales HC by Dept & T&E Segment'!$F:$F,$P39,'Sales HC by Dept & T&E Segment'!$G:$G,$G39) -> 39000 | AB39: =SUMIFS('Sales HC by Dept & T&E Segment'!AU:AU,'Sales HC by Dept & T&E Segment'!$F:$F,$P39,'Sales HC by Dept & T&E Segment'!$G:$G,$G39) -> 39000 | AC39: =SUMIFS('Sales HC by Dept & T&E Segment'!AV:AV,'Sales HC by Dept & T&E Segment'!$F:$F,$P39,'Sales HC by Dept & T&E Segment'!$G:$G,$G39) -> 39000 | AD39: =SUMIFS('Sales HC by Dept & T&E Segment'!AW:AW,'Sales HC by Dept & T&E Segment'!$F:$F,$P39,'Sales HC by Dept & T&E Segment'!$G:$G,$G39) -> 39000 | AE39: =SUM(S39:AD39) -> 468000 | AI39: =SUM(S39:U39) -> 117000 | AJ39: =SUM(V39:X39) -> 117000 | AK39: =SUM(Y39:AA39) -> 117000 | AL39: =SUM(AB39:AD39) -> 117000 | AM39: =SUM(AI39:AL39) -> 468000 | AN39: =AM39-AE39 -> 0 | AP39: =SUM(AI39:AJ39) -> 234000 | AQ39: =SUM(AK39:AL39) -> 234000 | AR39: =AP39+AQ39-AM39 -> 0
B40: C110101102 | C40: 10101102 | D40: 北一区-Nefecon | E40: A&P | F40: A&P | G40: Nefecon | H40: 2026 | I40: Budget | J40: Commercial | K40: Mainland | L40: CPO Operations | M40: Sales Team | N40: North 1 | O40: North 1 | P40: 北一区 | Q40: 科室会 | R40: 科室会 | S40: =SUMIFS('Sales HC by Dept & T&E Segment'!AL:AL,'Sales HC by Dept & T&E Segment'!$F:$F,$P40,'Sales HC by Dept & T&E Segment'!$G:$G,$G40) -> 73500 | T40: =SUMIFS('Sales HC by Dept & T&E Segment'!AM:AM,'Sales HC by Dept & T&E Segment'!$F:$F,$P40,'Sales HC by Dept & T&E Segment'!$G:$G,$G40) -> 73500 | U40: =SUMIFS('Sales HC by Dept & T&E Segment'!AN:AN,'Sales HC by Dept & T&E Segment'!$F:$F,$P40,'Sales HC by Dept & T&E Segment'!$G:$G,$G40) -> 73500 | V40: =SUMIFS('Sales HC by Dept & T&E Segment'!AO:AO,'Sales HC by Dept & T&E Segment'!$F:$F,$P40,'Sales HC by Dept & T&E Segment'!$G:$G,$G40) -> 85500 | W40: =SUMIFS('Sales HC by Dept & T&E Segment'!AP:AP,'Sales HC by Dept & T&E Segment'!$F:$F,$P40,'Sales HC by Dept & T&E Segment'!$G:$G,$G40) -> 85500 | X40: =SUMIFS('Sales HC by Dept & T&E Segment'!AQ:AQ,'Sales HC by Dept & T&E Segment'!$F:$F,$P40,'Sales HC by Dept & T&E Segment'!$G:$G,$G40) -> 85500 | Y40: =SUMIFS('Sales HC by Dept & T&E Segment'!AR:AR,'Sales HC by Dept & T&E Segment'!$F:$F,$P40,'Sales HC by Dept & T&E Segment'!$G:$G,$G40) -> 85500 | Z40: =SUMIFS('Sales HC by Dept & T&E Segment'!AS:AS,'Sales HC by Dept & T&E Segment'!$F:$F,$P40,'Sales HC by Dept & T&E Segment'!$G:$G,$G40) -> 85500 | AA40: =SUMIFS('Sales HC by Dept & T&E Segment'!AT:AT,'Sales HC by Dept & T&E Segment'!$F:$F,$P40,'Sales HC by Dept & T&E Segment'!$G:$G,$G40) -> 85500 | AB40: =SUMIFS('Sales HC by Dept & T&E Segment'!AU:AU,'Sales HC by Dept & T&E Segment'!$F:$F,$P40,'Sales HC by Dept & T&E Segment'!$G:$G,$G40) -> 85500 | AC40: =SUMIFS('Sales HC by Dept & T&E Segment'!AV:AV,'Sales HC by Dept & T&E Segment'!$F:$F,$P40,'Sales HC by Dept & T&E Segment'!$G:$G,$G40) -> 85500 | AD40: =SUMIFS('Sales HC by Dept & T&E Segment'!AW:AW,'Sales HC by Dept & T&E Segment'!$F:$F,$P40,'Sales HC by Dept & T&E Segment'!$G:$G,$G40) -> 85500 | AE40: =SUM(S40:AD40) -> 990000 | AI40: =SUM(S40:U40) -> 220500 | AJ40: =SUM(V40:X40) -> 256500 | AK40: =SUM(Y40:AA40) -> 256500 | AL40: =SUM(AB40:AD40) -> 256500 | AM40: =SUM(AI40:AL40) -> 990000 | AN40: =AM40-AE40 -> 0 | AP40: =SUM(AI40:AJ40) -> 477000 | AQ40: =SUM(AK40:AL40) -> 513000 | AR40: =AP40+AQ40-AM40 -> 0
B41: C110101202 | C41: 10101202 | D41: 北二区-Nefecon | E41: A&P | F41: A&P | G41: Nefecon | H41: 2026 | I41: Budget | J41: Commercial | K41: Mainland | L41: CPO Operations | M41: Sales Team | N41: North 2 | O41: North 2 | P41: 北二区 | Q41: 科室会 | R41: 科室会 | S41: =SUMIFS('Sales HC by Dept & T&E Segment'!AL:AL,'Sales HC by Dept & T&E Segment'!$F:$F,$P41,'Sales HC by Dept & T&E Segment'!$G:$G,$G41) -> 70500 | T41: =SUMIFS('Sales HC by Dept & T&E Segment'!AM:AM,'Sales HC by Dept & T&E Segment'!$F:$F,$P41,'Sales HC by Dept & T&E Segment'!$G:$G,$G41) -> 70500 | U41: =SUMIFS('Sales HC by Dept & T&E Segment'!AN:AN,'Sales HC by Dept & T&E Segment'!$F:$F,$P41,'Sales HC by Dept & T&E Segment'!$G:$G,$G41) -> 70500 | V41: =SUMIFS('Sales HC by Dept & T&E Segment'!AO:AO,'Sales HC by Dept & T&E Segment'!$F:$F,$P41,'Sales HC by Dept & T&E Segment'!$G:$G,$G41) -> 79500 | W41: =SUMIFS('Sales HC by Dept & T&E Segment'!AP:AP,'Sales HC by Dept & T&E Segment'!$F:$F,$P41,'Sales HC by Dept & T&E Segment'!$G:$G,$G41) -> 79500 | X41: =SUMIFS('Sales HC by Dept & T&E Segment'!AQ:AQ,'Sales HC by Dept & T&E Segment'!$F:$F,$P41,'Sales HC by Dept & T&E Segment'!$G:$G,$G41) -> 79500 | Y41: =SUMIFS('Sales HC by Dept & T&E Segment'!AR:AR,'Sales HC by Dept & T&E Segment'!$F:$F,$P41,'Sales HC by Dept & T&E Segment'!$G:$G,$G41) -> 79500 | Z41: =SUMIFS('Sales HC by Dept & T&E Segment'!AS:AS,'Sales HC by Dept & T&E Segment'!$F:$F,$P41,'Sales HC by Dept & T&E Segment'!$G:$G,$G41) -> 79500 | AA41: =SUMIFS('Sales HC by Dept & T&E Segment'!AT:AT,'Sales HC by Dept & T&E Segment'!$F:$F,$P41,'Sales HC by Dept & T&E Segment'!$G:$G,$G41) -> 79500 | AB41: =SUMIFS('Sales HC by Dept & T&E Segment'!AU:AU,'Sales HC by Dept & T&E Segment'!$F:$F,$P41,'Sales HC by Dept & T&E Segment'!$G:$G,$G41) -> 79500 | AC41: =SUMIFS('Sales HC by Dept & T&E Segment'!AV:AV,'Sales HC by Dept & T&E Segment'!$F:$F,$P41,'Sales HC by Dept & T&E Segment'!$G:$G,$G41) -> 79500 | AD41: =SUMIFS('Sales HC by Dept & T&E Segment'!AW:AW,'Sales HC by Dept & T&E Segment'!$F:$F,$P41,'Sales HC by Dept & T&E Segment'!$G:$G,$G41) -> 79500 | AE41: =SUM(S41:AD41) -> 927000 | AI41: =SUM(S41:U41) -> 211500 | AJ41: =SUM(V41:X41) -> 238500 | AK41: =SUM(Y41:AA41) -> 238500 | AL41: =SUM(AB41:AD41) -> 238500 | AM41: =SUM(AI41:AL41) -> 927000 | AN41: =AM41-AE41 -> 0 | AP41: =SUM(AI41:AJ41) -> 450000 | AQ41: =SUM(AK41:AL41) -> 477000 | AR41: =AP41+AQ41-AM41 -> 0
... B49: C110107102 | C49: 10107102 | D49: 西区-Nefecon | E49: A&P | F49: A&P | G49: Nefecon | H49: 2026 | I49: Budget | J49: Commercial | K49: Mainland | L49: CPO Operations | M49: Sales Team | N49: West | O49: West | P49: 西区 | Q49: 科室会 | R49: 科室会 | S49: =SUMIFS('Sales HC by Dept & T&E Segment'!AL:AL,'Sales HC by Dept & T&E Segment'!$F:$F,$P49,'Sales HC by Dept & T&E Segment'!$G:$G,$G49) -> 94500 | T49: =SUMIFS('Sales HC by Dept & T&E Segment'!AM:AM,'Sales HC by Dept & T&E Segment'!$F:$F,$P49,'Sales HC by Dept & T&E Segment'!$G:$G,$G49) -> 94500 | U49: =SUMIFS('Sales HC by Dept & T&E Segment'!AN:AN,'Sales HC by Dept & T&E Segment'!$F:$F,$P49,'Sales HC by Dept & T&E Segment'!$G:$G,$G49) -> 94500 | V49: =SUMIFS('Sales HC by Dept & T&E Segment'!AO:AO,'Sales HC by Dept & T&E Segment'!$F:$F,$P49,'Sales HC by Dept & T&E Segment'!$G:$G,$G49) -> 118500 | W49: =SUMIFS('Sales HC by Dept & T&E Segment'!AP:AP,'Sales HC by Dept & T&E Segment'!$F:$F,$P49,'Sales HC by Dept & T&E Segment'!$G:$G,$G49) -> 118500 | X49: =SUMIFS('Sales HC by Dept & T&E Segment'!AQ:AQ,'Sales HC by Dept & T&E Segment'!$F:$F,$P49,'Sales HC by Dept & T&E Segment'!$G:$G,$G49) -> 118500 | Y49: =SUMIFS('Sales HC by Dept & T&E Segment'!AR:AR,'Sales HC by Dept & T&E Segment'!$F:$F,$P49,'Sales HC by Dept & T&E Segment'!$G:$G,$G49) -> 118500 | Z49: =SUMIFS('Sales HC by Dept & T&E Segment'!AS:AS,'Sales HC by Dept & T&E Segment'!$F:$F,$P49,'Sales HC by Dept & T&E Segment'!$G:$G,$G49) -> 118500 | AA49: =SUMIFS('Sales HC by Dept & T&E Segment'!AT:AT,'Sales HC by Dept & T&E Segment'!$F:$F,$P49,'Sales HC by Dept & T&E Segment'!$G:$G,$G49) -> 118500 | AB49: =SUMIFS('Sales HC by Dept & T&E Segment'!AU:AU,'Sales HC by Dept & T&E Segment'!$F:$F,$P49,'Sales HC by Dept & T&E Segment'!$G:$G,$G49) -> 118500 | AC49: =SUMIFS('Sales HC by Dept & T&E Segment'!AV:AV,'Sales HC by Dept & T&E Segment'!$F:$F,$P49,'Sales HC by Dept & T&E Segment'!$G:$G,$G49) -> 118500 | AD49: =SUMIFS('Sales HC by Dept & T&E Segment'!AW:AW,'Sales HC by Dept & T&E Segment'!$F:$F,$P49,'Sales HC by Dept & T&E Segment'!$G:$G,$G49) -> 118500 | AE49: =SUM(S49:AD49) -> 1350000 | AI49: =SUM(S49:U49) -> 283500 | AJ49: =SUM(V49:X49) -> 355500 | AK49: =SUM(Y49:AA49) -> 355500 | AL49: =SUM(AB49:AD49) -> 355500 | AM49: =SUM(AI49:AL49) -> 1350000 | AN49: =AM49-AE49 -> 0 | AP49: =SUM(AI49:AJ49) -> 639000 | AQ49: =SUM(AK49:AL49) -> 711000 | AR49: =AP49+AQ49-AM49 -> 0
B50: C110110100 | C50: 10110100 | D50: Velsipity Sales | E50: A&P | F50: A&P | G50: Velsipity | H50: 2026 | I50: Budget | J50: Commercial | K50: Mainland | L50: CPO Operations | M50: Sales Team | N50: Velsipity Sales | O50: Velsipity Sales | P50: Velsipity Sales | Q50: 科室会 | R50: 科室会 | S50: =SUMIFS('Sales HC by Dept & T&E Segment'!AL:AL,'Sales HC by Dept & T&E Segment'!$F:$F,$P50,'Sales HC by Dept & T&E Segment'!$G:$G,$G50) -> 0 | T50: =SUMIFS('Sales HC by Dept & T&E Segment'!AM:AM,'Sales HC by Dept & T&E Segment'!$F:$F,$P50,'Sales HC by Dept & T&E Segment'!$G:$G,$G50) -> 0 | U50: =SUMIFS('Sales HC by Dept & T&E Segment'!AN:AN,'Sales HC by Dept & T&E Segment'!$F:$F,$P50,'Sales HC by Dept & T&E Segment'!$G:$G,$G50) -> 0 | V50: =SUMIFS('Sales HC by Dept & T&E Segment'!AO:AO,'Sales HC by Dept & T&E Segment'!$F:$F,$P50,'Sales HC by Dept & T&E Segment'!$G:$G,$G50) -> 256500 | W50: =SUMIFS('Sales HC by Dept & T&E Segment'!AP:AP,'Sales HC by Dept & T&E Segment'!$F:$F,$P50,'Sales HC by Dept & T&E Segment'!$G:$G,$G50) -> 256500 | X50: =SUMIFS('Sales HC by Dept & T&E Segment'!AQ:AQ,'Sales HC by Dept & T&E Segment'!$F:$F,$P50,'Sales HC by Dept & T&E Segment'!$G:$G,$G50) -> 256500 | Y50: =SUMIFS('Sales HC by Dept & T&E Segment'!AR:AR,'Sales HC by Dept & T&E Segment'!$F:$F,$P50,'Sales HC by Dept & T&E Segment'!$G:$G,$G50) -> 376500 | Z50: =SUMIFS('Sales HC by Dept & T&E Segment'!AS:AS,'Sales HC by Dept & T&E Segment'!$F:$F,$P50,'Sales HC by Dept & T&E Segment'!$G:$G,$G50) -> 376500 | AA50: =SUMIFS('Sales HC by Dept & T&E Segment'!AT:AT,'Sales HC by Dept & T&E Segment'!$F:$F,$P50,'Sales HC by Dept & T&E Segment'!$G:$G,$G50) -> 376500 | AB50: =SUMIFS('Sales HC by Dept & T&E Segment'!AU:AU,'Sales HC by Dept & T&E Segment'!$F:$F,$P50,'Sales HC by Dept & T&E Segment'!$G:$G,$G50) -> 616500 | AC50: =SUMIFS('Sales HC by Dept & T&E Segment'!AV:AV,'Sales HC by Dept & T&E Segment'!$F:$F,$P50,'Sales HC by Dept & T&E Segment'!$G:$G,$G50) -> 616500 | AD50: =SUMIFS('Sales HC by Dept & T&E Segment'!AW:AW,'Sales HC by Dept & T&E Segment'!$F:$F,$P50,'Sales HC by Dept & T&E Segment'!$G:$G,$G50) -> 616500 | AE50: =SUM(S50:AD50) -> 3748500 | AI50: =SUM(S50:U50) -> 0 | AJ50: =SUM(V50:X50) -> 769500 | AK50: =SUM(Y50:AA50) -> 1129500 | AL50: =SUM(AB50:AD50) -> 1849500 | AM50: =SUM(AI50:AL50) -> 3748500 | AN50: =AM50-AE50 -> 0 | AP50: =SUM(AI50:AJ50) -> 769500 | AQ50: =SUM(AK50:AL50) -> 2979000 | AR50: =AP50+AQ50-AM50 -> 0
B53: CC1 | C53: CC2 | D53: Dept Name | E53: FP&A L1 | F53: FP&A L2 | G53: Brand | H53: Year | I53: Data Type | J53: Mgt Report L1 | K53: Mgt Report L2 | L53: Mgt Report L3 | M53: Mgt Report L4 | N53: Mgt Report L5 | O53: Mgt Report L6 | P53: CN Name | Q53: Note1 | R53: Note2 | S53: Jan | T53: Feb | U53: Mar | V53: Apr | W53: May | X53: Jun | Y53: Jul | Z53: Aug | AA53: Sep | AB53: Oct | AC53: Nov | AD53: Dec | AE53: FY
B54: C110101101 | C54: 10101101 | D54: 北一区-Xerava | E54: A&P | F54: A&P | G54: Xerava | H54: 2026 | I54: Budget | J54: Commercial | K54: Mainland | L54: CPO Operations | M54: Sales Team | N54: North 1 | O54: North 1 | P54: 北一区 | Q54: 其他会 | R54: 其他会 | S54: =S78-S30 -> #REF! | T54: =T78-T30 -> #REF! | U54: =U78-U30 -> #REF! | V54: =V78-V30 -> #REF! | W54: =W78-W30 -> #REF! | X54: =X78-X30 -> #REF! | Y54: =Y78-Y30 -> #REF! | Z54: =Z78-Z30 -> #REF! | ... AD54: =AD78-AD30 -> #REF! | AE54: =SUM(S54:AD54) -> #REF! | AI54: =SUM(S54:U54) -> #REF! | AJ54: =SUM(V54:X54) -> #REF! | AK54: =SUM(Y54:AA54) -> #REF! | AL54: =SUM(AB54:AD54) -> #REF! | AM54: =SUM(AI54:AL54) -> #REF! | AN54: =AM54-AE54 -> #REF! | AP54: =SUM(AI54:AJ54) -> #REF! | AQ54: =SUM(AK54:AL54) -> #REF! | AR54: =AP54+AQ54-AM54 -> #REF!
B55: C110101201 | C55: 10101201 | D55: 北二区-Xerava | E55: A&P | F55: A&P | G55: Xerava | H55: 2026 | I55: Budget | J55: Commercial | K55: Mainland | L55: CPO Operations | M55: Sales Team | N55: North 2 | O55: North 2 | P55: 北二区 | Q55: 其他会 | R55: 其他会 | S55: =S79-S31 -> #REF! | T55: =T79-T31 -> #REF! | U55: =U79-U31 -> #REF! | V55: =V79-V31 -> #REF! | W55: =W79-W31 -> #REF! | X55: =X79-X31 -> #REF! | Y55: =Y79-Y31 -> #REF! | Z55: =Z79-Z31 -> #REF! | ... AD55: =AD79-AD31 -> #REF! | AE55: =SUM(S55:AD55) -> #REF! | AI55: =SUM(S55:U55) -> #REF! | AJ55: =SUM(V55:X55) -> #REF! | AK55: =SUM(Y55:AA55) -> #REF! | AL55: =SUM(AB55:AD55) -> #REF! | AM55: =SUM(AI55:AL55) -> #REF! | AN55: =AM55-AE55 -> #REF! | AP55: =SUM(AI55:AJ55) -> #REF! | AQ55: =SUM(AK55:AL55) -> #REF! | AR55: =AP55+AQ55-AM55 -> #REF!
B56: C110101301 | C56: 10101301 | D56: 北三区-Xerava | E56: A&P | F56: A&P | G56: Xerava | H56: 2026 | I56: Budget | J56: Commercial | K56: Mainland | L56: CPO Operations | M56: Sales Team | N56: North 3 | O56: North 3 | P56: 北三区 | Q56: 其他会 | R56: 其他会 | S56: =S80-S32 -> #REF! | T56: =T80-T32 -> #REF! | U56: =U80-U32 -> #REF! | V56: =V80-V32 -> #REF! | W56: =W80-W32 -> #REF! | X56: =X80-X32 -> #REF! | Y56: =Y80-Y32 -> #REF! | Z56: =Z80-Z32 -> #REF! | ... AD56: =AD80-AD32 -> #REF! | AE56: =SUM(S56:AD56) -> #REF! | AI56: =SUM(S56:U56) -> #REF! | AJ56: =SUM(V56:X56) -> #REF! | AK56: =SUM(Y56:AA56) -> #REF! | AL56: =SUM(AB56:AD56) -> #REF! | AM56: =SUM(AI56:AL56) -> #REF! | AN56: =AM56-AE56 -> #REF! | AP56: =SUM(AI56:AJ56) -> #REF! | AQ56: =SUM(AK56:AL56) -> #REF! | AR56: =AP56+AQ56-AM56 -> #REF!
B57: C110102101 | C57: 10102101 | D57: 东一区-Xerava | E57: A&P | F57: A&P | G57: Xerava | H57: 2026 | I57: Budget | J57: Commercial | K57: Mainland | L57: CPO Operations | M57: Sales Team | N57: East 1 | O57: East 1 | P57: 东一区 | Q57: 其他会 | R57: 其他会 | S57: =S81-S33 -> #REF! | T57: =T81-T33 -> #REF! | U57: =U81-U33 -> #REF! | V57: =V81-V33 -> #REF! | W57: =W81-W33 -> #REF! | X57: =X81-X33 -> #REF! | Y57: =Y81-Y33 -> #REF! | Z57: =Z81-Z33 -> #REF! | ... AD57: =AD81-AD33 -> #REF! | AE57: =SUM(S57:AD57) -> #REF! | AI57: =SUM(S57:U57) -> #REF! | AJ57: =SUM(V57:X57) -> #REF! | AK57: =SUM(Y57:AA57) -> #REF! | AL57: =SUM(AB57:AD57) -> #REF! | AM57: =SUM(AI57:AL57) -> #REF! | AN57: =AM57-AE57 -> #REF! | AP57: =SUM(AI57:AJ57) -> #REF! | AQ57: =SUM(AK57:AL57) -> #REF! | AR57: =AP57+AQ57-AM57 -> #REF!
B58: C110102201 | C58: 10102201 | D58: 东二区-Xerava | E58: A&P | F58: A&P | G58: Xerava | H58: 2026 | I58: Budget | J58: Commercial | K58: Mainland | L58: CPO Operations | M58: Sales Team | N58: East 2 | O58: East 2 | P58: 东二区 | Q58: 其他会 | R58: 其他会 | S58: =S82-S34 -> #REF! | T58: =T82-T34 -> #REF! | U58: =U82-U34 -> #REF! | V58: =V82-V34 -> #REF! | W58: =W82-W34 -> #REF! | X58: =X82-X34 -> #REF! | Y58: =Y82-Y34 -> #REF! | Z58: =Z82-Z34 -> #REF! | ... AD58: =AD82-AD34 -> #REF! | AE58: =SUM(S58:AD58) -> #REF! | AI58: =SUM(S58:U58) -> #REF! | AJ58: =SUM(V58:X58) -> #REF! | AK58: =SUM(Y58:AA58) -> #REF! | AL58: =SUM(AB58:AD58) -> #REF! | AM58: =SUM(AI58:AL58) -> #REF! | AN58: =AM58-AE58 -> #REF! | AP58: =SUM(AI58:AJ58) -> #REF! | AQ58: =SUM(AK58:AL58) -> #REF! | AR58: =AP58+AQ58-AM58 -> #REF!
B59: C110102301 | C59: 10102301 | D59: 东三区-Xerava | E59: A&P | F59: A&P | G59: Xerava | H59: 2026 | I59: Budget | J59: Commercial | K59: Mainland | L59: CPO Operations | M59: Sales Team | N59: East 3 | O59: East 3 | P59: 东三区 | Q59: 其他会 | R59: 其他会 | S59: =S83-S35 -> #REF! | T59: =T83-T35 -> #REF! | U59: =U83-U35 -> #REF! | V59: =V83-V35 -> #REF! | W59: =W83-W35 -> #REF! | X59: =X83-X35 -> #REF! | Y59: =Y83-Y35 -> #REF! | Z59: =Z83-Z35 -> #REF! | ... AD59: =AD83-AD35 -> #REF! | AE59: =SUM(S59:AD59) -> #REF! | AI59: =SUM(S59:U59) -> #REF! | AJ59: =SUM(V59:X59) -> #REF! | AK59: =SUM(Y59:AA59) -> #REF! | AL59: =SUM(AB59:AD59) -> #REF! | AM59: =SUM(AI59:AL59) -> #REF! | AN59: =AM59-AE59 -> #REF! | AP59: =SUM(AI59:AJ59) -> #REF! | AQ59: =SUM(AK59:AL59) -> #REF! | AR59: =AP59+AQ59-AM59 -> #REF!
B60: C110103101 | C60: 10103101 | D60: 华中区-Xerava | E60: A&P | F60: A&P | G60: Xerava | H60: 2026 | I60: Budget | J60: Commercial | K60: Mainland | L60: CPO Operations | M60: Sales Team | N60: Central | O60: Central | P60: 华中区 | Q60: 其他会 | R60: 其他会 | S60: =S84-S36 -> #REF! | T60: =T84-T36 -> #REF! | U60: =U84-U36 -> #REF! | V60: =V84-V36 -> #REF! | W60: =W84-W36 -> #REF! | X60: =X84-X36 -> #REF! | Y60: =Y84-Y36 -> #REF! | Z60: =Z84-Z36 -> #REF! | ... AD60: =AD84-AD36 -> #REF! | AE60: =SUM(S60:AD60) -> #REF! | AI60: =SUM(S60:U60) -> #REF! | AJ60: =SUM(V60:X60) -> #REF! | AK60: =SUM(Y60:AA60) -> #REF! | AL60: =SUM(AB60:AD60) -> #REF! | AM60: =SUM(AI60:AL60) -> #REF! | AN60: =AM60-AE60 -> #REF! | AP60: =SUM(AI60:AJ60) -> #REF! | AQ60: =SUM(AK60:AL60) -> #REF! | AR60: =AP60+AQ60-AM60 -> #REF!
B61: C110106101 | C61: 10106101 | D61: 东北区-Xerava | E61: A&P | F61: A&P | G61: Xerava | H61: 2026 | I61: Budget | J61: Commercial | K61: Mainland | L61: CPO Operations | M61: Sales Team | N61: Northeast | O61: Northeast | P61: 东北区 | Q61: 其他会 | R61: 其他会 | S61: =S85-S37 -> #REF! | T61: =T85-T37 -> #REF! | U61: =U85-U37 -> #REF! | V61: =V85-V37 -> #REF! | W61: =W85-W37 -> #REF! | X61: =X85-X37 -> #REF! | Y61: =Y85-Y37 -> #REF! | Z61: =Z85-Z37 -> #REF! | ... AD61: =AD85-AD37 -> #REF! | AE61: =SUM(S61:AD61) -> #REF! | AI61: =SUM(S61:U61) -> #REF! | AJ61: =SUM(V61:X61) -> #REF! | AK61: =SUM(Y61:AA61) -> #REF! | AL61: =SUM(AB61:AD61) -> #REF! | AM61: =SUM(AI61:AL61) -> #REF! | AN61: =AM61-AE61 -> #REF! | AP61: =SUM(AI61:AJ61) -> #REF! | AQ61: =SUM(AK61:AL61) -> #REF! | AR61: =AP61+AQ61-AM61 -> #REF!
B62: C110105101 | C62: 10105101 | D62: 南区-Xerava | E62: A&P | F62: A&P | G62: Xerava | H62: 2026 | I62: Budget | J62: Commercial | K62: Mainland | L62: CPO Operations | M62: Sales Team | N62: South | O62: South | P62: 南区 | Q62: 其他会 | R62: 其他会 | S62: =S86-S38 -> #REF! | T62: =T86-T38 -> #REF! | U62: =U86-U38 -> #REF! | V62: =V86-V38 -> #REF! | W62: =W86-W38 -> #REF! | X62: =X86-X38 -> #REF! | Y62: =Y86-Y38 -> #REF! | Z62: =Z86-Z38 -> #REF! | ... AD62: =AD86-AD38 -> #REF! | AE62: =SUM(S62:AD62) -> #REF! | AI62: =SUM(S62:U62) -> #REF! | AJ62: =SUM(V62:X62) -> #REF! | AK62: =SUM(Y62:AA62) -> #REF! | AL62: =SUM(AB62:AD62) -> #REF! | AM62: =SUM(AI62:AL62) -> #REF! | AN62: =AM62-AE62 -> #REF! | AP62: =SUM(AI62:AJ62) -> #REF! | AQ62: =SUM(AK62:AL62) -> #REF! | AR62: =AP62+AQ62-AM62 -> #REF!
B63: C110107101 | C63: 10107101 | D63: 西区-Xerava | E63: A&P | F63: A&P | G63: Xerava | H63: 2026 | I63: Budget | J63: Commercial | K63: Mainland | L63: CPO Operations | M63: Sales Team | N63: West | O63: West | P63: 西区 | Q63: 其他会 | R63: 其他会 | S63: =S87-S39 -> #REF! | T63: =T87-T39 -> #REF! | U63: =U87-U39 -> #REF! | V63: =V87-V39 -> #REF! | W63: =W87-W39 -> #REF! | X63: =X87-X39 -> #REF! | Y63: =Y87-Y39 -> #REF! | Z63: =Z87-Z39 -> #REF! | ... AD63: =AD87-AD39 -> #REF! | AE63: =SUM(S63:AD63) -> #REF! | AI63: =SUM(S63:U63) -> #REF! | AJ63: =SUM(V63:X63) -> #REF! | AK63: =SUM(Y63:AA63) -> #REF! | AL63: =SUM(AB63:AD63) -> #REF! | AM63: =SUM(AI63:AL63) -> #REF! | AN63: =AM63-AE63 -> #REF! | AP63: =SUM(AI63:AJ63) -> #REF! | AQ63: =SUM(AK63:AL63) -> #REF! | AR63: =AP63+AQ63-AM63 -> #REF!
B64: C110101102 | C64: 10101102 | D64: 北一区-Nefecon | E64: A&P | F64: A&P | G64: Nefecon | H64: 2026 | I64: Budget | J64: Commercial | K64: Mainland | L64: CPO Operations | M64: Sales Team | N64: North 1 | O64: North 1 | P64: 北一区 | Q64: 其他会 | R64: 其他会 | S64: =S88-S40 -> #REF! | T64: =T88-T40 -> #REF! | U64: =U88-U40 -> #REF! | V64: =V88-V40 -> #REF! | W64: =W88-W40 -> #REF! | X64: =X88-X40 -> #REF! | Y64: =Y88-Y40 -> #REF! | Z64: =Z88-Z40 -> #REF! | ... AD64: =AD88-AD40 -> #REF! | AE64: =SUM(S64:AD64) -> #REF! | AI64: =SUM(S64:U64) -> #REF! | AJ64: =SUM(V64:X64) -> #REF! | AK64: =SUM(Y64:AA64) -> #REF! | AL64: =SUM(AB64:AD64) -> #REF! | AM64: =SUM(AI64:AL64) -> #REF! | AN64: =AM64-AE64 -> #REF! | AP64: =SUM(AI64:AJ64) -> #REF! | AQ64: =SUM(AK64:AL64) -> #REF! | AR64: =AP64+AQ64-AM64 -> #REF!
B65: C110101202 | C65: 10101202 | D65: 北二区-Nefecon | E65: A&P | F65: A&P | G65: Nefecon | H65: 2026 | I65: Budget | J65: Commercial | K65: Mainland | L65: CPO Operations | M65: Sales Team | N65: North 2 | O65: North 2 | P65: 北二区 | Q65: 其他会 | R65: 其他会 | S65: =S89-S41 -> #REF! | T65: =T89-T41 -> #REF! | U65: =U89-U41 -> #REF! | V65: =V89-V41 -> #REF! | W65: =W89-W41 -> #REF! | X65: =X89-X41 -> #REF! | Y65: =Y89-Y41 -> #REF! | Z65: =Z89-Z41 -> #REF! | ... AD65: =AD89-AD41 -> #REF! | AE65: =SUM(S65:AD65) -> #REF! | AI65: =SUM(S65:U65) -> #REF! | AJ65: =SUM(V65:X65) -> #REF! | AK65: =SUM(Y65:AA65) -> #REF! | AL65: =SUM(AB65:AD65) -> #REF! | AM65: =SUM(AI65:AL65) -> #REF! | AN65: =AM65-AE65 -> #REF! | AP65: =SUM(AI65:AJ65) -> #REF! | AQ65: =SUM(AK65:AL65) -> #REF! | AR65: =AP65+AQ65-AM65 -> #REF!
... B73: C110107102 | C73: 10107102 | D73: 西区-Nefecon | E73: A&P | F73: A&P | G73: Nefecon | H73: 2026 | I73: Budget | J73: Commercial | K73: Mainland | L73: CPO Operations | M73: Sales Team | N73: West | O73: West | P73: 西区 | Q73: 其他会 | R73: 其他会 | S73: =S97-S49 -> #REF! | T73: =T97-T49 -> #REF! | U73: =U97-U49 -> #REF! | V73: =V97-V49 -> #REF! | W73: =W97-W49 -> #REF! | X73: =X97-X49 -> #REF! | Y73: =Y97-Y49 -> #REF! | Z73: =Z97-Z49 -> #REF! | ... AD73: =AD97-AD49 -> #REF! | AE73: =SUM(S73:AD73) -> #REF! | AI73: =SUM(S73:U73) -> #REF! | AJ73: =SUM(V73:X73) -> #REF! | AK73: =SUM(Y73:AA73) -> #REF! | AL73: =SUM(AB73:AD73) -> #REF! | AM73: =SUM(AI73:AL73) -> #REF! | AN73: =AM73-AE73 -> #REF! | AP73: =SUM(AI73:AJ73) -> #REF! | AQ73: =SUM(AK73:AL73) -> #REF! | AR73: =AP73+AQ73-AM73 -> #REF!
B74: C110110100 | C74: 10110100 | D74: Velsipity Sales | E74: A&P | F74: A&P | G74: Velsipity | H74: 2026 | I74: Budget | J74: Commercial | K74: Mainland | L74: CPO Operations | M74: Sales Team | N74: Velsipity Sales | O74: Velsipity Sales | P74: Velsipity Sales | Q74: 其他会 | R74: 其他会 | S74: =S98-S50 -> #REF! | T74: =T98-T50 -> #REF! | U74: =U98-U50 -> #REF! | V74: =V98-V50 -> #REF! | W74: =W98-W50 -> #REF! | X74: =X98-X50 -> #REF! | Y74: =Y98-Y50 -> #REF! | Z74: =Z98-Z50 -> #REF! | ... AD74: =AD98-AD50 -> #REF! | AE74: =SUM(S74:AD74) -> #REF! | AI74: =SUM(S74:U74) -> #REF! | AJ74: =SUM(V74:X74) -> #REF! | AK74: =SUM(Y74:AA74) -> #REF! | AL74: =SUM(AB74:AD74) -> #REF! | AM74: =SUM(AI74:AL74) -> #REF! | AN74: =AM74-AE74 -> #REF! | AP74: =SUM(AI74:AJ74) -> #REF! | AQ74: =SUM(AK74:AL74) -> #REF! | AR74: =AP74+AQ74-AM74 -> #REF!
B77: CC1 | C77: CC2 | D77: Dept Name | E77: FP&A L1 | F77: FP&A L2 | G77: Brand | H77: Year | I77: Data Type | J77: Mgt Report L1 | K77: Mgt Report L2 | L77: Mgt Report L3 | M77: Mgt Report L4 | N77: Mgt Report L5 | O77: Mgt Report L6 | P77: CN Name | Q77: Note1 | R77: Note2 | S77: Jan | T77: Feb | U77: Mar | V77: Apr | W77: May | X77: Jun | Y77: Jul | Z77: Aug | AA77: Sep | AB77: Oct | AC77: Nov | AD77: Dec | AE77: FY
B78: C110101101 | C78: 10101101 | D78: 北一区-Xerava | E78: A&P | F78: A&P | G78: Xerava | H78: 2026 | I78: Budget | J78: Commercial | K78: Mainland | L78: CPO Operations | M78: Sales Team | N78: North 1 | O78: North 1 | P78: 北一区 | Q78: A&P汇总 | R78: A&P汇总 | S78: =SUMIFS('1. Velsipity Summary'!CN:CN,'1. Velsipity Summary'!#REF!,$P78,'1. Velsipity Summary'!$CM:$CM,$G78) -> #REF! | T78: =SUMIFS('1. Velsipity Summary'!CO:CO,'1. Velsipity Summary'!#REF!,$P78,'1. Velsipity Summary'!$CM:$CM,$G78) -> #REF! | U78: =SUMIFS('1. Velsipity Summary'!CP:CP,'1. Velsipity Summary'!#REF!,$P78,'1. Velsipity Summary'!$CM:$CM,$G78) -> #REF! | V78: =SUMIFS('1. Velsipity Summary'!CQ:CQ,'1. Velsipity Summary'!#REF!,$P78,'1. Velsipity Summary'!$CM:$CM,$G78) -> #REF! | W78: =SUMIFS('1. Velsipity Summary'!CR:CR,'1. Velsipity Summary'!#REF!,$P78,'1. Velsipity Summary'!$CM:$CM,$G78) -> #REF! | X78: =SUMIFS('1. Velsipity Summary'!CS:CS,'1. Velsipity Summary'!#REF!,$P78,'1. Velsipity Summary'!$CM:$CM,$G78) -> #REF! | Y78: =SUMIFS('1. Velsipity Summary'!CT:CT,'1. Velsipity Summary'!#REF!,$P78,'1. Velsipity Summary'!$CM:$CM,$G78) -> #REF! | Z78: =SUMIFS('1. Velsipity Summary'!CU:CU,'1. Velsipity Summary'!#REF!,$P78,'1. Velsipity Summary'!$CM:$CM,$G78) -> #REF! | AA78: =SUMIFS('1. Velsipity Summary'!CV:CV,'1. Velsipity Summary'!#REF!,$P78,'1. Velsipity Summary'!$CM:$CM,$G78) -> #REF! | AB78: =SUMIFS('1. Velsipity Summary'!CW:CW,'1. Velsipity Summary'!#REF!,$P78,'1. Velsipity Summary'!$CM:$CM,$G78) -> #REF! | AC78: =SUMIFS('1. Velsipity Summary'!CX:CX,'1. Velsipity Summary'!#REF!,$P78,'1. Velsipity Summary'!$CM:$CM,$G78) -> #REF! | AD78: =SUMIFS('1. Velsipity Summary'!CY:CY,'1. Velsipity Summary'!#REF!,$P78,'1. Velsipity Summary'!$CM:$CM,$G78) -> #REF! | AE78: =SUM(S78:AD78) -> #REF! | AI78: =SUM(S78:U78) -> #REF! | AJ78: =SUM(V78:X78) -> #REF! | AK78: =SUM(Y78:AA78) -> #REF! | AL78: =SUM(AB78:AD78) -> #REF! | AM78: =SUM(AI78:AL78) -> #REF! | AN78: =AM78-AE78 -> #REF! | AP78: =SUM(AI78:AJ78) -> #REF! | AQ78: =SUM(AK78:AL78) -> #REF! | AR78: =AP78+AQ78-AM78 -> #REF!
B79: C110101201 | C79: 10101201 | D79: 北二区-Xerava | E79: A&P | F79: A&P | G79: Xerava | H79: 2026 | I79: Budget | J79: Commercial | K79: Mainland | L79: CPO Operations | M79: Sales Team | N79: North 2 | O79: North 2 | P79: 北二区 | Q79: A&P汇总 | R79: A&P汇总 | S79: =SUMIFS('1. Velsipity Summary'!CN:CN,'1. Velsipity Summary'!#REF!,$P79,'1. Velsipity Summary'!$CM:$CM,$G79) -> #REF! | T79: =SUMIFS('1. Velsipity Summary'!CO:CO,'1. Velsipity Summary'!#REF!,$P79,'1. Velsipity Summary'!$CM:$CM,$G79) -> #REF! | U79: =SUMIFS('1. Velsipity Summary'!CP:CP,'1. Velsipity Summary'!#REF!,$P79,'1. Velsipity Summary'!$CM:$CM,$G79) -> #REF! | V79: =SUMIFS('1. Velsipity Summary'!CQ:CQ,'1. Velsipity Summary'!#REF!,$P79,'1. Velsipity Summary'!$CM:$CM,$G79) -> #REF! | W79: =SUMIFS('1. Velsipity Summary'!CR:CR,'1. Velsipity Summary'!#REF!,$P79,'1. Velsipity Summary'!$CM:$CM,$G79) -> #REF! | X79: =SUMIFS('1. Velsipity Summary'!CS:CS,'1. Velsipity Summary'!#REF!,$P79,'1. Velsipity Summary'!$CM:$CM,$G79) -> #REF! | Y79: =SUMIFS('1. Velsipity Summary'!CT:CT,'1. Velsipity Summary'!#REF!,$P79,'1. Velsipity Summary'!$CM:$CM,$G79) -> #REF! | Z79: =SUMIFS('1. Velsipity Summary'!CU:CU,'1. Velsipity Summary'!#REF!,$P79,'1. Velsipity Summary'!$CM:$CM,$G79) -> #REF! | AA79: =SUMIFS('1. Velsipity Summary'!CV:CV,'1. Velsipity Summary'!#REF!,$P79,'1. Velsipity Summary'!$CM:$CM,$G79) -> #REF! | AB79: =SUMIFS('1. Velsipity Summary'!CW:CW,'1. Velsipity Summary'!#REF!,$P79,'1. Velsipity Summary'!$CM:$CM,$G79) -> #REF! | AC79: =SUMIFS('1. Velsipity Summary'!CX:CX,'1. Velsipity Summary'!#REF!,$P79,'1. Velsipity Summary'!$CM:$CM,$G79) -> #REF! | AD79: =SUMIFS('1. Velsipity Summary'!CY:CY,'1. Velsipity Summary'!#REF!,$P79,'1. Velsipity Summary'!$CM:$CM,$G79) -> #REF! | AE79: =SUM(S79:AD79) -> #REF! | AI79: =SUM(S79:U79) -> #REF! | AJ79: =SUM(V79:X79) -> #REF! | AK79: =SUM(Y79:AA79) -> #REF! | AL79: =SUM(AB79:AD79) -> #REF! | AM79: =SUM(AI79:AL79) -> #REF! | AN79: =AM79-AE79 -> #REF! | AP79: =SUM(AI79:AJ79) -> #REF! | AQ79: =SUM(AK79:AL79) -> #REF! | AR79: =AP79+AQ79-AM79 -> #REF!
B80: C110101301 | C80: 10101301 | D80: 北三区-Xerava | E80: A&P | F80: A&P | G80: Xerava | H80: 2026 | I80: Budget | J80: Commercial | K80: Mainland | L80: CPO Operations | M80: Sales Team | N80: North 3 | O80: North 3 | P80: 北三区 | Q80: A&P汇总 | R80: A&P汇总 | S80: =SUMIFS('1. Velsipity Summary'!CN:CN,'1. Velsipity Summary'!#REF!,$P80,'1. Velsipity Summary'!$CM:$CM,$G80) -> #REF! | T80: =SUMIFS('1. Velsipity Summary'!CO:CO,'1. Velsipity Summary'!#REF!,$P80,'1. Velsipity Summary'!$CM:$CM,$G80) -> #REF! | U80: =SUMIFS('1. Velsipity Summary'!CP:CP,'1. Velsipity Summary'!#REF!,$P80,'1. Velsipity Summary'!$CM:$CM,$G80) -> #REF! | V80: =SUMIFS('1. Velsipity Summary'!CQ:CQ,'1. Velsipity Summary'!#REF!,$P80,'1. Velsipity Summary'!$CM:$CM,$G80) -> #REF! | W80: =SUMIFS('1. Velsipity Summary'!CR:CR,'1. Velsipity Summary'!#REF!,$P80,'1. Velsipity Summary'!$CM:$CM,$G80) -> #REF! | X80: =SUMIFS('1. Velsipity Summary'!CS:CS,'1. Velsipity Summary'!#REF!,$P80,'1. Velsipity Summary'!$CM:$CM,$G80) -> #REF! | Y80: =SUMIFS('1. Velsipity Summary'!CT:CT,'1. Velsipity Summary'!#REF!,$P80,'1. Velsipity Summary'!$CM:$CM,$G80) -> #REF! | Z80: =SUMIFS('1. Velsipity Summary'!CU:CU,'1. Velsipity Summary'!#REF!,$P80,'1. Velsipity Summary'!$CM:$CM,$G80) -> #REF! | AA80: =SUMIFS('1. Velsipity Summary'!CV:CV,'1. Velsipity Summary'!#REF!,$P80,'1. Velsipity Summary'!$CM:$CM,$G80) -> #REF! | AB80: =SUMIFS('1. Velsipity Summary'!CW:CW,'1. Velsipity Summary'!#REF!,$P80,'1. Velsipity Summary'!$CM:$CM,$G80) -> #REF! | AC80: =SUMIFS('1. Velsipity Summary'!CX:CX,'1. Velsipity Summary'!#REF!,$P80,'1. Velsipity Summary'!$CM:$CM,$G80) -> #REF! | AD80: =SUMIFS('1. Velsipity Summary'!CY:CY,'1. Velsipity Summary'!#REF!,$P80,'1. Velsipity Summary'!$CM:$CM,$G80) -> #REF! | AE80: =SUM(S80:AD80) -> #REF! | AI80: =SUM(S80:U80) -> #REF! | AJ80: =SUM(V80:X80) -> #REF! | AK80: =SUM(Y80:AA80) -> #REF! | AL80: =SUM(AB80:AD80) -> #REF! | AM80: =SUM(AI80:AL80) -> #REF! | AN80: =AM80-AE80 -> #REF! | AP80: =SUM(AI80:AJ80) -> #REF! | AQ80: =SUM(AK80:AL80) -> #REF! | AR80: =AP80+AQ80-AM80 -> #REF!
B81: C110102101 | C81: 10102101 | D81: 东一区-Xerava | E81: A&P | F81: A&P | G81: Xerava | H81: 2026 | I81: Budget | J81: Commercial | K81: Mainland | L81: CPO Operations | M81: Sales Team | N81: East 1 | O81: East 1 | P81: 东一区 | Q81: A&P汇总 | R81: A&P汇总 | S81: =SUMIFS('1. Velsipity Summary'!CN:CN,'1. Velsipity Summary'!#REF!,$P81,'1. Velsipity Summary'!$CM:$CM,$G81) -> #REF! | T81: =SUMIFS('1. Velsipity Summary'!CO:CO,'1. Velsipity Summary'!#REF!,$P81,'1. Velsipity Summary'!$CM:$CM,$G81) -> #REF! | U81: =SUMIFS('1. Velsipity Summary'!CP:CP,'1. Velsipity Summary'!#REF!,$P81,'1. Velsipity Summary'!$CM:$CM,$G81) -> #REF! | V81: =SUMIFS('1. Velsipity Summary'!CQ:CQ,'1. Velsipity Summary'!#REF!,$P81,'1. Velsipity Summary'!$CM:$CM,$G81) -> #REF! | W81: =SUMIFS('1. Velsipity Summary'!CR:CR,'1. Velsipity Summary'!#REF!,$P81,'1. Velsipity Summary'!$CM:$CM,$G81) -> #REF! | X81: =SUMIFS('1. Velsipity Summary'!CS:CS,'1. Velsipity Summary'!#REF!,$P81,'1. Velsipity Summary'!$CM:$CM,$G81) -> #REF! | Y81: =SUMIFS('1. Velsipity Summary'!CT:CT,'1. Velsipity Summary'!#REF!,$P81,'1. Velsipity Summary'!$CM:$CM,$G81) -> #REF! | Z81: =SUMIFS('1. Velsipity Summary'!CU:CU,'1. Velsipity Summary'!#REF!,$P81,'1. Velsipity Summary'!$CM:$CM,$G81) -> #REF! | AA81: =SUMIFS('1. Velsipity Summary'!CV:CV,'1. Velsipity Summary'!#REF!,$P81,'1. Velsipity Summary'!$CM:$CM,$G81) -> #REF! | AB81: =SUMIFS('1. Velsipity Summary'!CW:CW,'1. Velsipity Summary'!#REF!,$P81,'1. Velsipity Summary'!$CM:$CM,$G81) -> #REF! | AC81: =SUMIFS('1. Velsipity Summary'!CX:CX,'1. Velsipity Summary'!#REF!,$P81,'1. Velsipity Summary'!$CM:$CM,$G81) -> #REF! | AD81: =SUMIFS('1. Velsipity Summary'!CY:CY,'1. Velsipity Summary'!#REF!,$P81,'1. Velsipity Summary'!$CM:$CM,$G81) -> #REF! | AE81: =SUM(S81:AD81) -> #REF! | AI81: =SUM(S81:U81) -> #REF! | AJ81: =SUM(V81:X81) -> #REF! | AK81: =SUM(Y81:AA81) -> #REF! | AL81: =SUM(AB81:AD81) -> #REF! | AM81: =SUM(AI81:AL81) -> #REF! | AN81: =AM81-AE81 -> #REF! | AP81: =SUM(AI81:AJ81) -> #REF! | AQ81: =SUM(AK81:AL81) -> #REF! | AR81: =AP81+AQ81-AM81 -> #REF!
B82: C110102201 | C82: 10102201 | D82: 东二区-Xerava | E82: A&P | F82: A&P | G82: Xerava | H82: 2026 | I82: Budget | J82: Commercial | K82: Mainland | L82: CPO Operations | M82: Sales Team | N82: East 2 | O82: East 2 | P82: 东二区 | Q82: A&P汇总 | R82: A&P汇总 | S82: =SUMIFS('1. Velsipity Summary'!CN:CN,'1. Velsipity Summary'!#REF!,$P82,'1. Velsipity Summary'!$CM:$CM,$G82) -> #REF! | T82: =SUMIFS('1. Velsipity Summary'!CO:CO,'1. Velsipity Summary'!#REF!,$P82,'1. Velsipity Summary'!$CM:$CM,$G82) -> #REF! | U82: =SUMIFS('1. Velsipity Summary'!CP:CP,'1. Velsipity Summary'!#REF!,$P82,'1. Velsipity Summary'!$CM:$CM,$G82) -> #REF! | V82: =SUMIFS('1. Velsipity Summary'!CQ:CQ,'1. Velsipity Summary'!#REF!,$P82,'1. Velsipity Summary'!$CM:$CM,$G82) -> #REF! | W82: =SUMIFS('1. Velsipity Summary'!CR:CR,'1. Velsipity Summary'!#REF!,$P82,'1. Velsipity Summary'!$CM:$CM,$G82) -> #REF! | X82: =SUMIFS('1. Velsipity Summary'!CS:CS,'1. Velsipity Summary'!#REF!,$P82,'1. Velsipity Summary'!$CM:$CM,$G82) -> #REF! | Y82: =SUMIFS('1. Velsipity Summary'!CT:CT,'1. Velsipity Summary'!#REF!,$P82,'1. Velsipity Summary'!$CM:$CM,$G82) -> #REF! | Z82: =SUMIFS('1. Velsipity Summary'!CU:CU,'1. Velsipity Summary'!#REF!,$P82,'1. Velsipity Summary'!$CM:$CM,$G82) -> #REF! | AA82: =SUMIFS('1. Velsipity Summary'!CV:CV,'1. Velsipity Summary'!#REF!,$P82,'1. Velsipity Summary'!$CM:$CM,$G82) -> #REF! | AB82: =SUMIFS('1. Velsipity Summary'!CW:CW,'1. Velsipity Summary'!#REF!,$P82,'1. Velsipity Summary'!$CM:$CM,$G82) -> #REF! | AC82: =SUMIFS('1. Velsipity Summary'!CX:CX,'1. Velsipity Summary'!#REF!,$P82,'1. Velsipity Summary'!$CM:$CM,$G82) -> #REF! | AD82: =SUMIFS('1. Velsipity Summary'!CY:CY,'1. Velsipity Summary'!#REF!,$P82,'1. Velsipity Summary'!$CM:$CM,$G82) -> #REF! | AE82: =SUM(S82:AD82) -> #REF! | AI82: =SUM(S82:U82) -> #REF! | AJ82: =SUM(V82:X82) -> #REF! | AK82: =SUM(Y82:AA82) -> #REF! | AL82: =SUM(AB82:AD82) -> #REF! | AM82: =SUM(AI82:AL82) -> #REF! | AN82: =AM82-AE82 -> #REF! | AP82: =SUM(AI82:AJ82) -> #REF! | AQ82: =SUM(AK82:AL82) -> #REF! | AR82: =AP82+AQ82-AM82 -> #REF!
B83: C110102301 | C83: 10102301 | D83: 东三区-Xerava | E83: A&P | F83: A&P | G83: Xerava | H83: 2026 | I83: Budget | J83: Commercial | K83: Mainland | L83: CPO Operations | M83: Sales Team | N83: East 3 | O83: East 3 | P83: 东三区 | Q83: A&P汇总 | R83: A&P汇总 | S83: =SUMIFS('1. Velsipity Summary'!CN:CN,'1. Velsipity Summary'!#REF!,$P83,'1. Velsipity Summary'!$CM:$CM,$G83) -> #REF! | T83: =SUMIFS('1. Velsipity Summary'!CO:CO,'1. Velsipity Summary'!#REF!,$P83,'1. Velsipity Summary'!$CM:$CM,$G83) -> #REF! | U83: =SUMIFS('1. Velsipity Summary'!CP:CP,'1. Velsipity Summary'!#REF!,$P83,'1. Velsipity Summary'!$CM:$CM,$G83) -> #REF! | V83: =SUMIFS('1. Velsipity Summary'!CQ:CQ,'1. Velsipity Summary'!#REF!,$P83,'1. Velsipity Summary'!$CM:$CM,$G83) -> #REF! | W83: =SUMIFS('1. Velsipity Summary'!CR:CR,'1. Velsipity Summary'!#REF!,$P83,'1. Velsipity Summary'!$CM:$CM,$G83) -> #REF! | X83: =SUMIFS('1. Velsipity Summary'!CS:CS,'1. Velsipity Summary'!#REF!,$P83,'1. Velsipity Summary'!$CM:$CM,$G83) -> #REF! | Y83: =SUMIFS('1. Velsipity Summary'!CT:CT,'1. Velsipity Summary'!#REF!,$P83,'1. Velsipity Summary'!$CM:$CM,$G83) -> #REF! | Z83: =SUMIFS('1. Velsipity Summary'!CU:CU,'1. Velsipity Summary'!#REF!,$P83,'1. Velsipity Summary'!$CM:$CM,$G83) -> #REF! | AA83: =SUMIFS('1. Velsipity Summary'!CV:CV,'1. Velsipity Summary'!#REF!,$P83,'1. Velsipity Summary'!$CM:$CM,$G83) -> #REF! | AB83: =SUMIFS('1. Velsipity Summary'!CW:CW,'1. Velsipity Summary'!#REF!,$P83,'1. Velsipity Summary'!$CM:$CM,$G83) -> #REF! | AC83: =SUMIFS('1. Velsipity Summary'!CX:CX,'1. Velsipity Summary'!#REF!,$P83,'1. Velsipity Summary'!$CM:$CM,$G83) -> #REF! | AD83: =SUMIFS('1. Velsipity Summary'!CY:CY,'1. Velsipity Summary'!#REF!,$P83,'1. Velsipity Summary'!$CM:$CM,$G83) -> #REF! | AE83: =SUM(S83:AD83) -> #REF! | AI83: =SUM(S83:U83) -> #REF! | AJ83: =SUM(V83:X83) -> #REF! | AK83: =SUM(Y83:AA83) -> #REF! | AL83: =SUM(AB83:AD83) -> #REF! | AM83: =SUM(AI83:AL83) -> #REF! | AN83: =AM83-AE83 -> #REF! | AP83: =SUM(AI83:AJ83) -> #REF! | AQ83: =SUM(AK83:AL83) -> #REF! | AR83: =AP83+AQ83-AM83 -> #REF!
B84: C110103101 | C84: 10103101 | D84: 华中区-Xerava | E84: A&P | F84: A&P | G84: Xerava | H84: 2026 | I84: Budget | J84: Commercial | K84: Mainland | L84: CPO Operations | M84: Sales Team | N84: Central | O84: Central | P84: 华中区 | Q84: A&P汇总 | R84: A&P汇总 | S84: =SUMIFS('1. Velsipity Summary'!CN:CN,'1. Velsipity Summary'!#REF!,$P84,'1. Velsipity Summary'!$CM:$CM,$G84) -> #REF! | T84: =SUMIFS('1. Velsipity Summary'!CO:CO,'1. Velsipity Summary'!#REF!,$P84,'1. Velsipity Summary'!$CM:$CM,$G84) -> #REF! | U84: =SUMIFS('1. Velsipity Summary'!CP:CP,'1. Velsipity Summary'!#REF!,$P84,'1. Velsipity Summary'!$CM:$CM,$G84) -> #REF! | V84: =SUMIFS('1. Velsipity Summary'!CQ:CQ,'1. Velsipity Summary'!#REF!,$P84,'1. Velsipity Summary'!$CM:$CM,$G84) -> #REF! | W84: =SUMIFS('1. Velsipity Summary'!CR:CR,'1. Velsipity Summary'!#REF!,$P84,'1. Velsipity Summary'!$CM:$CM,$G84) -> #REF! | X84: =SUMIFS('1. Velsipity Summary'!CS:CS,'1. Velsipity Summary'!#REF!,$P84,'1. Velsipity Summary'!$CM:$CM,$G84) -> #REF! | Y84: =SUMIFS('1. Velsipity Summary'!CT:CT,'1. Velsipity Summary'!#REF!,$P84,'1. Velsipity Summary'!$CM:$CM,$G84) -> #REF! | Z84: =SUMIFS('1. Velsipity Summary'!CU:CU,'1. Velsipity Summary'!#REF!,$P84,'1. Velsipity Summary'!$CM:$CM,$G84) -> #REF! | AA84: =SUMIFS('1. Velsipity Summary'!CV:CV,'1. Velsipity Summary'!#REF!,$P84,'1. Velsipity Summary'!$CM:$CM,$G84) -> #REF! | AB84: =SUMIFS('1. Velsipity Summary'!CW:CW,'1. Velsipity Summary'!#REF!,$P84,'1. Velsipity Summary'!$CM:$CM,$G84) -> #REF! | AC84: =SUMIFS('1. Velsipity Summary'!CX:CX,'1. Velsipity Summary'!#REF!,$P84,'1. Velsipity Summary'!$CM:$CM,$G84) -> #REF! | AD84: =SUMIFS('1. Velsipity Summary'!CY:CY,'1. Velsipity Summary'!#REF!,$P84,'1. Velsipity Summary'!$CM:$CM,$G84) -> #REF! | AE84: =SUM(S84:AD84) -> #REF! | AI84: =SUM(S84:U84) -> #REF! | AJ84: =SUM(V84:X84) -> #REF! | AK84: =SUM(Y84:AA84) -> #REF! | AL84: =SUM(AB84:AD84) -> #REF! | AM84: =SUM(AI84:AL84) -> #REF! | AN84: =AM84-AE84 -> #REF! | AP84: =SUM(AI84:AJ84) -> #REF! | AQ84: =SUM(AK84:AL84) -> #REF! | AR84: =AP84+AQ84-AM84 -> #REF!
B85: C110106101 | C85: 10106101 | D85: 东北区-Xerava | E85: A&P | F85: A&P | G85: Xerava | H85: 2026 | I85: Budget | J85: Commercial | K85: Mainland | L85: CPO Operations | M85: Sales Team | N85: Northeast | O85: Northeast | P85: 东北区 | Q85: A&P汇总 | R85: A&P汇总 | S85: =SUMIFS('1. Velsipity Summary'!CN:CN,'1. Velsipity Summary'!#REF!,$P85,'1. Velsipity Summary'!$CM:$CM,$G85) -> #REF! | T85: =SUMIFS('1. Velsipity Summary'!CO:CO,'1. Velsipity Summary'!#REF!,$P85,'1. Velsipity Summary'!$CM:$CM,$G85) -> #REF! | U85: =SUMIFS('1. Velsipity Summary'!CP:CP,'1. Velsipity Summary'!#REF!,$P85,'1. Velsipity Summary'!$CM:$CM,$G85) -> #REF! | V85: =SUMIFS('1. Velsipity Summary'!CQ:CQ,'1. Velsipity Summary'!#REF!,$P85,'1. Velsipity Summary'!$CM:$CM,$G85) -> #REF! | W85: =SUMIFS('1. Velsipity Summary'!CR:CR,'1. Velsipity Summary'!#REF!,$P85,'1. Velsipity Summary'!$CM:$CM,$G85) -> #REF! | X85: =SUMIFS('1. Velsipity Summary'!CS:CS,'1. Velsipity Summary'!#REF!,$P85,'1. Velsipity Summary'!$CM:$CM,$G85) -> #REF! | Y85: =SUMIFS('1. Velsipity Summary'!CT:CT,'1. Velsipity Summary'!#REF!,$P85,'1. Velsipity Summary'!$CM:$CM,$G85) -> #REF! | Z85: =SUMIFS('1. Velsipity Summary'!CU:CU,'1. Velsipity Summary'!#REF!,$P85,'1. Velsipity Summary'!$CM:$CM,$G85) -> #REF! | AA85: =SUMIFS('1. Velsipity Summary'!CV:CV,'1. Velsipity Summary'!#REF!,$P85,'1. Velsipity Summary'!$CM:$CM,$G85) -> #REF! | AB85: =SUMIFS('1. Velsipity Summary'!CW:CW,'1. Velsipity Summary'!#REF!,$P85,'1. Velsipity Summary'!$CM:$CM,$G85) -> #REF! | AC85: =SUMIFS('1. Velsipity Summary'!CX:CX,'1. Velsipity Summary'!#REF!,$P85,'1. Velsipity Summary'!$CM:$CM,$G85) -> #REF! | AD85: =SUMIFS('1. Velsipity Summary'!CY:CY,'1. Velsipity Summary'!#REF!,$P85,'1. Velsipity Summary'!$CM:$CM,$G85) -> #REF! | AE85: =SUM(S85:AD85) -> #REF! | AI85: =SUM(S85:U85) -> #REF! | AJ85: =SUM(V85:X85) -> #REF! | AK85: =SUM(Y85:AA85) -> #REF! | AL85: =SUM(AB85:AD85) -> #REF! | AM85: =SUM(AI85:AL85) -> #REF! | AN85: =AM85-AE85 -> #REF! | AP85: =SUM(AI85:AJ85) -> #REF! | AQ85: =SUM(AK85:AL85) -> #REF! | AR85: =AP85+AQ85-AM85 -> #REF!
B86: C110105101 | C86: 10105101 | D86: 南区-Xerava | E86: A&P | F86: A&P | G86: Xerava | H86: 2026 | I86: Budget | J86: Commercial | K86: Mainland | L86: CPO Operations | M86: Sales Team | N86: South | O86: South | P86: 南区 | Q86: A&P汇总 | R86: A&P汇总 | S86: =SUMIFS('1. Velsipity Summary'!CN:CN,'1. Velsipity Summary'!#REF!,$P86,'1. Velsipity Summary'!$CM:$CM,$G86) -> #REF! | T86: =SUMIFS('1. Velsipity Summary'!CO:CO,'1. Velsipity Summary'!#REF!,$P86,'1. Velsipity Summary'!$CM:$CM,$G86) -> #REF! | U86: =SUMIFS('1. Velsipity Summary'!CP:CP,'1. Velsipity Summary'!#REF!,$P86,'1. Velsipity Summary'!$CM:$CM,$G86) -> #REF! | V86: =SUMIFS('1. Velsipity Summary'!CQ:CQ,'1. Velsipity Summary'!#REF!,$P86,'1. Velsipity Summary'!$CM:$CM,$G86) -> #REF! | W86: =SUMIFS('1. Velsipity Summary'!CR:CR,'1. Velsipity Summary'!#REF!,$P86,'1. Velsipity Summary'!$CM:$CM,$G86) -> #REF! | X86: =SUMIFS('1. Velsipity Summary'!CS:CS,'1. Velsipity Summary'!#REF!,$P86,'1. Velsipity Summary'!$CM:$CM,$G86) -> #REF! | Y86: =SUMIFS('1. Velsipity Summary'!CT:CT,'1. Velsipity Summary'!#REF!,$P86,'1. Velsipity Summary'!$CM:$CM,$G86) -> #REF! | Z86: =SUMIFS('1. Velsipity Summary'!CU:CU,'1. Velsipity Summary'!#REF!,$P86,'1. Velsipity Summary'!$CM:$CM,$G86) -> #REF! | AA86: =SUMIFS('1. Velsipity Summary'!CV:CV,'1. Velsipity Summary'!#REF!,$P86,'1. Velsipity Summary'!$CM:$CM,$G86) -> #REF! | AB86: =SUMIFS('1. Velsipity Summary'!CW:CW,'1. Velsipity Summary'!#REF!,$P86,'1. Velsipity Summary'!$CM:$CM,$G86) -> #REF! | AC86: =SUMIFS('1. Velsipity Summary'!CX:CX,'1. Velsipity Summary'!#REF!,$P86,'1. Velsipity Summary'!$CM:$CM,$G86) -> #REF! | AD86: =SUMIFS('1. Velsipity Summary'!CY:CY,'1. Velsipity Summary'!#REF!,$P86,'1. Velsipity Summary'!$CM:$CM,$G86) -> #REF! | AE86: =SUM(S86:AD86) -> #REF! | AI86: =SUM(S86:U86) -> #REF! | AJ86: =SUM(V86:X86) -> #REF! | AK86: =SUM(Y86:AA86) -> #REF! | AL86: =SUM(AB86:AD86) -> #REF! | AM86: =SUM(AI86:AL86) -> #REF! | AN86: =AM86-AE86 -> #REF! | AP86: =SUM(AI86:AJ86) -> #REF! | AQ86: =SUM(AK86:AL86) -> #REF! | AR86: =AP86+AQ86-AM86 -> #REF!
B87: C110107101 | C87: 10107101 | D87: 西区-Xerava | E87: A&P | F87: A&P | G87: Xerava | H87: 2026 | I87: Budget | J87: Commercial | K87: Mainland | L87: CPO Operations | M87: Sales Team | N87: West | O87: West | P87: 西区 | Q87: A&P汇总 | R87: A&P汇总 | S87: =SUMIFS('1. Velsipity Summary'!CN:CN,'1. Velsipity Summary'!#REF!,$P87,'1. Velsipity Summary'!$CM:$CM,$G87) -> #REF! | T87: =SUMIFS('1. Velsipity Summary'!CO:CO,'1. Velsipity Summary'!#REF!,$P87,'1. Velsipity Summary'!$CM:$CM,$G87) -> #REF! | U87: =SUMIFS('1. Velsipity Summary'!CP:CP,'1. Velsipity Summary'!#REF!,$P87,'1. Velsipity Summary'!$CM:$CM,$G87) -> #REF! | V87: =SUMIFS('1. Velsipity Summary'!CQ:CQ,'1. Velsipity Summary'!#REF!,$P87,'1. Velsipity Summary'!$CM:$CM,$G87) -> #REF! | W87: =SUMIFS('1. Velsipity Summary'!CR:CR,'1. Velsipity Summary'!#REF!,$P87,'1. Velsipity Summary'!$CM:$CM,$G87) -> #REF! | X87: =SUMIFS('1. Velsipity Summary'!CS:CS,'1. Velsipity Summary'!#REF!,$P87,'1. Velsipity Summary'!$CM:$CM,$G87) -> #REF! | Y87: =SUMIFS('1. Velsipity Summary'!CT:CT,'1. Velsipity Summary'!#REF!,$P87,'1. Velsipity Summary'!$CM:$CM,$G87) -> #REF! | Z87: =SUMIFS('1. Velsipity Summary'!CU:CU,'1. Velsipity Summary'!#REF!,$P87,'1. Velsipity Summary'!$CM:$CM,$G87) -> #REF! | AA87: =SUMIFS('1. Velsipity Summary'!CV:CV,'1. Velsipity Summary'!#REF!,$P87,'1. Velsipity Summary'!$CM:$CM,$G87) -> #REF! | AB87: =SUMIFS('1. Velsipity Summary'!CW:CW,'1. Velsipity Summary'!#REF!,$P87,'1. Velsipity Summary'!$CM:$CM,$G87) -> #REF! | AC87: =SUMIFS('1. Velsipity Summary'!CX:CX,'1. Velsipity Summary'!#REF!,$P87,'1. Velsipity Summary'!$CM:$CM,$G87) -> #REF! | AD87: =SUMIFS('1. Velsipity Summary'!CY:CY,'1. Velsipity Summary'!#REF!,$P87,'1. Velsipity Summary'!$CM:$CM,$G87) -> #REF! | AE87: =SUM(S87:AD87) -> #REF! | AG87: =SUM(AE78:AE87) -> #REF! | AH87: =AG87-'1. Velsipity Summary'!CZ25 -> #REF! | AI87: =SUM(S87:U87) -> #REF! | AJ87: =SUM(V87:X87) -> #REF! | AK87: =SUM(Y87:AA87) -> #REF! | AL87: =SUM(AB87:AD87) -> #REF! | AM87: =SUM(AI87:AL87) -> #REF! | AN87: =AM87-AE87 -> #REF! | AP87: =SUM(AI87:AJ87) -> #REF! | AQ87: =SUM(AK87:AL87) -> #REF! | AR87: =AP87+AQ87-AM87 -> #REF!
B88: C110101102 | C88: 10101102 | D88: 北一区-Nefecon | E88: A&P | F88: A&P | G88: Nefecon | H88: 2026 | I88: Budget | J88: Commercial | K88: Mainland | L88: CPO Operations | M88: Sales Team | N88: North 1 | O88: North 1 | P88: 北一区 | Q88: A&P汇总 | R88: A&P汇总 | S88: =SUMIFS('1. Velsipity Summary'!CN:CN,'1. Velsipity Summary'!#REF!,$P88,'1. Velsipity Summary'!$CM:$CM,$G88) -> #REF! | T88: =SUMIFS('1. Velsipity Summary'!CO:CO,'1. Velsipity Summary'!#REF!,$P88,'1. Velsipity Summary'!$CM:$CM,$G88) -> #REF! | U88: =SUMIFS('1. Velsipity Summary'!CP:CP,'1. Velsipity Summary'!#REF!,$P88,'1. Velsipity Summary'!$CM:$CM,$G88) -> #REF! | V88: =SUMIFS('1. Velsipity Summary'!CQ:CQ,'1. Velsipity Summary'!#REF!,$P88,'1. Velsipity Summary'!$CM:$CM,$G88) -> #REF! | W88: =SUMIFS('1. Velsipity Summary'!CR:CR,'1. Velsipity Summary'!#REF!,$P88,'1. Velsipity Summary'!$CM:$CM,$G88) -> #REF! | X88: =SUMIFS('1. Velsipity Summary'!CS:CS,'1. Velsipity Summary'!#REF!,$P88,'1. Velsipity Summary'!$CM:$CM,$G88) -> #REF! | Y88: =SUMIFS('1. Velsipity Summary'!CT:CT,'1. Velsipity Summary'!#REF!,$P88,'1. Velsipity Summary'!$CM:$CM,$G88) -> #REF! | Z88: =SUMIFS('1. Velsipity Summary'!CU:CU,'1. Velsipity Summary'!#REF!,$P88,'1. Velsipity Summary'!$CM:$CM,$G88) -> #REF! | AA88: =SUMIFS('1. Velsipity Summary'!CV:CV,'1. Velsipity Summary'!#REF!,$P88,'1. Velsipity Summary'!$CM:$CM,$G88) -> #REF! | AB88: =SUMIFS('1. Velsipity Summary'!CW:CW,'1. Velsipity Summary'!#REF!,$P88,'1. Velsipity Summary'!$CM:$CM,$G88) -> #REF! | AC88: =SUMIFS('1. Velsipity Summary'!CX:CX,'1. Velsipity Summary'!#REF!,$P88,'1. Velsipity Summary'!$CM:$CM,$G88) -> #REF! | AD88: =SUMIFS('1. Velsipity Summary'!CY:CY,'1. Velsipity Summary'!#REF!,$P88,'1. Velsipity Summary'!$CM:$CM,$G88) -> #REF! | AE88: =SUM(S88:AD88) -> #REF! | AI88: =SUM(S88:U88) -> #REF! | AJ88: =SUM(V88:X88) -> #REF! | AK88: =SUM(Y88:AA88) -> #REF! | AL88: =SUM(AB88:AD88) -> #REF! | AM88: =SUM(AI88:AL88) -> #REF! | AN88: =AM88-AE88 -> #REF! | AP88: =SUM(AI88:AJ88) -> #REF! | AQ88: =SUM(AK88:AL88) -> #REF! | AR88: =AP88+AQ88-AM88 -> #REF!
B89: C110101202 | C89: 10101202 | D89: 北二区-Nefecon | E89: A&P | F89: A&P | G89: Nefecon | H89: 2026 | I89: Budget | J89: Commercial | K89: Mainland | L89: CPO Operations | M89: Sales Team | N89: North 2 | O89: North 2 | P89: 北二区 | Q89: A&P汇总 | R89: A&P汇总 | S89: =SUMIFS('1. Velsipity Summary'!CN:CN,'1. Velsipity Summary'!#REF!,$P89,'1. Velsipity Summary'!$CM:$CM,$G89) -> #REF! | T89: =SUMIFS('1. Velsipity Summary'!CO:CO,'1. Velsipity Summary'!#REF!,$P89,'1. Velsipity Summary'!$CM:$CM,$G89) -> #REF! | U89: =SUMIFS('1. Velsipity Summary'!CP:CP,'1. Velsipity Summary'!#REF!,$P89,'1. Velsipity Summary'!$CM:$CM,$G89) -> #REF! | V89: =SUMIFS('1. Velsipity Summary'!CQ:CQ,'1. Velsipity Summary'!#REF!,$P89,'1. Velsipity Summary'!$CM:$CM,$G89) -> #REF! | W89: =SUMIFS('1. Velsipity Summary'!CR:CR,'1. Velsipity Summary'!#REF!,$P89,'1. Velsipity Summary'!$CM:$CM,$G89) -> #REF! | X89: =SUMIFS('1. Velsipity Summary'!CS:CS,'1. Velsipity Summary'!#REF!,$P89,'1. Velsipity Summary'!$CM:$CM,$G89) -> #REF! | Y89: =SUMIFS('1. Velsipity Summary'!CT:CT,'1. Velsipity Summary'!#REF!,$P89,'1. Velsipity Summary'!$CM:$CM,$G89) -> #REF! | Z89: =SUMIFS('1. Velsipity Summary'!CU:CU,'1. Velsipity Summary'!#REF!,$P89,'1. Velsipity Summary'!$CM:$CM,$G89) -> #REF! | AA89: =SUMIFS('1. Velsipity Summary'!CV:CV,'1. Velsipity Summary'!#REF!,$P89,'1. Velsipity Summary'!$CM:$CM,$G89) -> #REF! | AB89: =SUMIFS('1. Velsipity Summary'!CW:CW,'1. Velsipity Summary'!#REF!,$P89,'1. Velsipity Summary'!$CM:$CM,$G89) -> #REF! | AC89: =SUMIFS('1. Velsipity Summary'!CX:CX,'1. Velsipity Summary'!#REF!,$P89,'1. Velsipity Summary'!$CM:$CM,$G89) -> #REF! | AD89: =SUMIFS('1. Velsipity Summary'!CY:CY,'1. Velsipity Summary'!#REF!,$P89,'1. Velsipity Summary'!$CM:$CM,$G89) -> #REF! | AE89: =SUM(S89:AD89) -> #REF! | AI89: =SUM(S89:U89) -> #REF! | AJ89: =SUM(V89:X89) -> #REF! | AK89: =SUM(Y89:AA89) -> #REF! | AL89: =SUM(AB89:AD89) -> #REF! | AM89: =SUM(AI89:AL89) -> #REF! | AN89: =AM89-AE89 -> #REF! | AP89: =SUM(AI89:AJ89) -> #REF! | AQ89: =SUM(AK89:AL89) -> #REF! | AR89: =AP89+AQ89-AM89 -> #REF!
B90: C110101302 | C90: 10101302 | D90: 北三区-Nefecon | E90: A&P | F90: A&P | G90: Nefecon | H90: 2026 | I90: Budget | J90: Commercial | K90: Mainland | L90: CPO Operations | M90: Sales Team | N90: North 3 | O90: North 3 | P90: 北三区 | Q90: A&P汇总 | R90: A&P汇总 | S90: =SUMIFS('1. Velsipity Summary'!CN:CN,'1. Velsipity Summary'!#REF!,$P90,'1. Velsipity Summary'!$CM:$CM,$G90) -> #REF! | T90: =SUMIFS('1. Velsipity Summary'!CO:CO,'1. Velsipity Summary'!#REF!,$P90,'1. Velsipity Summary'!$CM:$CM,$G90) -> #REF! | U90: =SUMIFS('1. Velsipity Summary'!CP:CP,'1. Velsipity Summary'!#REF!,$P90,'1. Velsipity Summary'!$CM:$CM,$G90) -> #REF! | V90: =SUMIFS('1. Velsipity Summary'!CQ:CQ,'1. Velsipity Summary'!#REF!,$P90,'1. Velsipity Summary'!$CM:$CM,$G90) -> #REF! | W90: =SUMIFS('1. Velsipity Summary'!CR:CR,'1. Velsipity Summary'!#REF!,$P90,'1. Velsipity Summary'!$CM:$CM,$G90) -> #REF! | X90: =SUMIFS('1. Velsipity Summary'!CS:CS,'1. Velsipity Summary'!#REF!,$P90,'1. Velsipity Summary'!$CM:$CM,$G90) -> #REF! | Y90: =SUMIFS('1. Velsipity Summary'!CT:CT,'1. Velsipity Summary'!#REF!,$P90,'1. Velsipity Summary'!$CM:$CM,$G90) -> #REF! | Z90: =SUMIFS('1. Velsipity Summary'!CU:CU,'1. Velsipity Summary'!#REF!,$P90,'1. Velsipity Summary'!$CM:$CM,$G90) -> #REF! | AA90: =SUMIFS('1. Velsipity Summary'!CV:CV,'1. Velsipity Summary'!#REF!,$P90,'1. Velsipity Summary'!$CM:$CM,$G90) -> #REF! | AB90: =SUMIFS('1. Velsipity Summary'!CW:CW,'1. Velsipity Summary'!#REF!,$P90,'1. Velsipity Summary'!$CM:$CM,$G90) -> #REF! | AC90: =SUMIFS('1. Velsipity Summary'!CX:CX,'1. Velsipity Summary'!#REF!,$P90,'1. Velsipity Summary'!$CM:$CM,$G90) -> #REF! | AD90: =SUMIFS('1. Velsipity Summary'!CY:CY,'1. Velsipity Summary'!#REF!,$P90,'1. Velsipity Summary'!$CM:$CM,$G90) -> #REF! | AE90: =SUM(S90:AD90) -> #REF! | AI90: =SUM(S90:U90) -> #REF! | AJ90: =SUM(V90:X90) -> #REF! | AK90: =SUM(Y90:AA90) -> #REF! | AL90: =SUM(AB90:AD90) -> #REF! | AM90: =SUM(AI90:AL90) -> #REF! | AN90: =AM90-AE90 -> #REF! | AP90: =SUM(AI90:AJ90) -> #REF! | AQ90: =SUM(AK90:AL90) -> #REF! | AR90: =AP90+AQ90-AM90 -> #REF!
B91: C110102102 | C91: 10102102 | D91: 东一区-Nefecon | E91: A&P | F91: A&P | G91: Nefecon | H91: 2026 | I91: Budget | J91: Commercial | K91: Mainland | L91: CPO Operations | M91: Sales Team | N91: East 1 | O91: East 1 | P91: 东一区 | Q91: A&P汇总 | R91: A&P汇总 | S91: =SUMIFS('1. Velsipity Summary'!CN:CN,'1. Velsipity Summary'!#REF!,$P91,'1. Velsipity Summary'!$CM:$CM,$G91) -> #REF! | T91: =SUMIFS('1. Velsipity Summary'!CO:CO,'1. Velsipity Summary'!#REF!,$P91,'1. Velsipity Summary'!$CM:$CM,$G91) -> #REF! | U91: =SUMIFS('1. Velsipity Summary'!CP:CP,'1. Velsipity Summary'!#REF!,$P91,'1. Velsipity Summary'!$CM:$CM,$G91) -> #REF! | V91: =SUMIFS('1. Velsipity Summary'!CQ:CQ,'1. Velsipity Summary'!#REF!,$P91,'1. Velsipity Summary'!$CM:$CM,$G91) -> #REF! | W91: =SUMIFS('1. Velsipity Summary'!CR:CR,'1. Velsipity Summary'!#REF!,$P91,'1. Velsipity Summary'!$CM:$CM,$G91) -> #REF! | X91: =SUMIFS('1. Velsipity Summary'!CS:CS,'1. Velsipity Summary'!#REF!,$P91,'1. Velsipity Summary'!$CM:$CM,$G91) -> #REF! | Y91: =SUMIFS('1. Velsipity Summary'!CT:CT,'1. Velsipity Summary'!#REF!,$P91,'1. Velsipity Summary'!$CM:$CM,$G91) -> #REF! | Z91: =SUMIFS('1. Velsipity Summary'!CU:CU,'1. Velsipity Summary'!#REF!,$P91,'1. Velsipity Summary'!$CM:$CM,$G91) -> #REF! | AA91: =SUMIFS('1. Velsipity Summary'!CV:CV,'1. Velsipity Summary'!#REF!,$P91,'1. Velsipity Summary'!$CM:$CM,$G91) -> #REF! | AB91: =SUMIFS('1. Velsipity Summary'!CW:CW,'1. Velsipity Summary'!#REF!,$P91,'1. Velsipity Summary'!$CM:$CM,$G91) -> #REF! | AC91: =SUMIFS('1. Velsipity Summary'!CX:CX,'1. Velsipity Summary'!#REF!,$P91,'1. Velsipity Summary'!$CM:$CM,$G91) -> #REF! | AD91: =SUMIFS('1. Velsipity Summary'!CY:CY,'1. Velsipity Summary'!#REF!,$P91,'1. Velsipity Summary'!$CM:$CM,$G91) -> #REF! | AE91: =SUM(S91:AD91) -> #REF! | AI91: =SUM(S91:U91) -> #REF! | AJ91: =SUM(V91:X91) -> #REF! | AK91: =SUM(Y91:AA91) -> #REF! | AL91: =SUM(AB91:AD91) -> #REF! | AM91: =SUM(AI91:AL91) -> #REF! | AN91: =AM91-AE91 -> #REF! | AP91: =SUM(AI91:AJ91) -> #REF! | AQ91: =SUM(AK91:AL91) -> #REF! | AR91: =AP91+AQ91-AM91 -> #REF!
B92: C110102202 | C92: 10102202 | D92: 东二区-Nefecon | E92: A&P | F92: A&P | G92: Nefecon | H92: 2026 | I92: Budget | J92: Commercial | K92: Mainland | L92: CPO Operations | M92: Sales Team | N92: East 2 | O92: East 2 | P92: 东二区 | Q92: A&P汇总 | R92: A&P汇总 | S92: =SUMIFS('1. Velsipity Summary'!CN:CN,'1. Velsipity Summary'!#REF!,$P92,'1. Velsipity Summary'!$CM:$CM,$G92) -> #REF! | T92: =SUMIFS('1. Velsipity Summary'!CO:CO,'1. Velsipity Summary'!#REF!,$P92,'1. Velsipity Summary'!$CM:$CM,$G92) -> #REF! | U92: =SUMIFS('1. Velsipity Summary'!CP:CP,'1. Velsipity Summary'!#REF!,$P92,'1. Velsipity Summary'!$CM:$CM,$G92) -> #REF! | V92: =SUMIFS('1. Velsipity Summary'!CQ:CQ,'1. Velsipity Summary'!#REF!,$P92,'1. Velsipity Summary'!$CM:$CM,$G92) -> #REF! | W92: =SUMIFS('1. Velsipity Summary'!CR:CR,'1. Velsipity Summary'!#REF!,$P92,'1. Velsipity Summary'!$CM:$CM,$G92) -> #REF! | X92: =SUMIFS('1. Velsipity Summary'!CS:CS,'1. Velsipity Summary'!#REF!,$P92,'1. Velsipity Summary'!$CM:$CM,$G92) -> #REF! | Y92: =SUMIFS('1. Velsipity Summary'!CT:CT,'1. Velsipity Summary'!#REF!,$P92,'1. Velsipity Summary'!$CM:$CM,$G92) -> #REF! | Z92: =SUMIFS('1. Velsipity Summary'!CU:CU,'1. Velsipity Summary'!#REF!,$P92,'1. Velsipity Summary'!$CM:$CM,$G92) -> #REF! | AA92: =SUMIFS('1. Velsipity Summary'!CV:CV,'1. Velsipity Summary'!#REF!,$P92,'1. Velsipity Summary'!$CM:$CM,$G92) -> #REF! | AB92: =SUMIFS('1. Velsipity Summary'!CW:CW,'1. Velsipity Summary'!#REF!,$P92,'1. Velsipity Summary'!$CM:$CM,$G92) -> #REF! | AC92: =SUMIFS('1. Velsipity Summary'!CX:CX,'1. Velsipity Summary'!#REF!,$P92,'1. Velsipity Summary'!$CM:$CM,$G92) -> #REF! | AD92: =SUMIFS('1. Velsipity Summary'!CY:CY,'1. Velsipity Summary'!#REF!,$P92,'1. Velsipity Summary'!$CM:$CM,$G92) -> #REF! | AE92: =SUM(S92:AD92) -> #REF! | AI92: =SUM(S92:U92) -> #REF! | AJ92: =SUM(V92:X92) -> #REF! | AK92: =SUM(Y92:AA92) -> #REF! | AL92: =SUM(AB92:AD92) -> #REF! | AM92: =SUM(AI92:AL92) -> #REF! | AN92: =AM92-AE92 -> #REF! | AP92: =SUM(AI92:AJ92) -> #REF! | AQ92: =SUM(AK92:AL92) -> #REF! | AR92: =AP92+AQ92-AM92 -> #REF!
B93: C110102302 | C93: 10102302 | D93: 东三区-Nefecon | E93: A&P | F93: A&P | G93: Nefecon | H93: 2026 | I93: Budget | J93: Commercial | K93: Mainland | L93: CPO Operations | M93: Sales Team | N93: East 3 | O93: East 3 | P93: 东三区 | Q93: A&P汇总 | R93: A&P汇总 | S93: =SUMIFS('1. Velsipity Summary'!CN:CN,'1. Velsipity Summary'!#REF!,$P93,'1. Velsipity Summary'!$CM:$CM,$G93) -> #REF! | T93: =SUMIFS('1. Velsipity Summary'!CO:CO,'1. Velsipity Summary'!#REF!,$P93,'1. Velsipity Summary'!$CM:$CM,$G93) -> #REF! | U93: =SUMIFS('1. Velsipity Summary'!CP:CP,'1. Velsipity Summary'!#REF!,$P93,'1. Velsipity Summary'!$CM:$CM,$G93) -> #REF! | V93: =SUMIFS('1. Velsipity Summary'!CQ:CQ,'1. Velsipity Summary'!#REF!,$P93,'1. Velsipity Summary'!$CM:$CM,$G93) -> #REF! | W93: =SUMIFS('1. Velsipity Summary'!CR:CR,'1. Velsipity Summary'!#REF!,$P93,'1. Velsipity Summary'!$CM:$CM,$G93) -> #REF! | X93: =SUMIFS('1. Velsipity Summary'!CS:CS,'1. Velsipity Summary'!#REF!,$P93,'1. Velsipity Summary'!$CM:$CM,$G93) -> #REF! | Y93: =SUMIFS('1. Velsipity Summary'!CT:CT,'1. Velsipity Summary'!#REF!,$P93,'1. Velsipity Summary'!$CM:$CM,$G93) -> #REF! | Z93: =SUMIFS('1. Velsipity Summary'!CU:CU,'1. Velsipity Summary'!#REF!,$P93,'1. Velsipity Summary'!$CM:$CM,$G93) -> #REF! | AA93: =SUMIFS('1. Velsipity Summary'!CV:CV,'1. Velsipity Summary'!#REF!,$P93,'1. Velsipity Summary'!$CM:$CM,$G93) -> #REF! | AB93: =SUMIFS('1. Velsipity Summary'!CW:CW,'1. Velsipity Summary'!#REF!,$P93,'1. Velsipity Summary'!$CM:$CM,$G93) -> #REF! | AC93: =SUMIFS('1. Velsipity Summary'!CX:CX,'1. Velsipity Summary'!#REF!,$P93,'1. Velsipity Summary'!$CM:$CM,$G93) -> #REF! | AD93: =SUMIFS('1. Velsipity Summary'!CY:CY,'1. Velsipity Summary'!#REF!,$P93,'1. Velsipity Summary'!$CM:$CM,$G93) -> #REF! | AE93: =SUM(S93:AD93) -> #REF! | AI93: =SUM(S93:U93) -> #REF! | AJ93: =SUM(V93:X93) -> #REF! | AK93: =SUM(Y93:AA93) -> #REF! | AL93: =SUM(AB93:AD93) -> #REF! | AM93: =SUM(AI93:AL93) -> #REF! | AN93: =AM93-AE93 -> #REF! | AP93: =SUM(AI93:AJ93) -> #REF! | AQ93: =SUM(AK93:AL93) -> #REF! | AR93: =AP93+AQ93-AM93 -> #REF!
B94: C110103102 | C94: 10103102 | D94: 华中区-Nefecon | E94: A&P | F94: A&P | G94: Nefecon | H94: 2026 | I94: Budget | J94: Commercial | K94: Mainland | L94: CPO Operations | M94: Sales Team | N94: Central | O94: Central | P94: 华中区 | Q94: A&P汇总 | R94: A&P汇总 | S94: =SUMIFS('1. Velsipity Summary'!CN:CN,'1. Velsipity Summary'!#REF!,$P94,'1. Velsipity Summary'!$CM:$CM,$G94) -> #REF! | T94: =SUMIFS('1. Velsipity Summary'!CO:CO,'1. Velsipity Summary'!#REF!,$P94,'1. Velsipity Summary'!$CM:$CM,$G94) -> #REF! | U94: =SUMIFS('1. Velsipity Summary'!CP:CP,'1. Velsipity Summary'!#REF!,$P94,'1. Velsipity Summary'!$CM:$CM,$G94) -> #REF! | V94: =SUMIFS('1. Velsipity Summary'!CQ:CQ,'1. Velsipity Summary'!#REF!,$P94,'1. Velsipity Summary'!$CM:$CM,$G94) -> #REF! | W94: =SUMIFS('1. Velsipity Summary'!CR:CR,'1. Velsipity Summary'!#REF!,$P94,'1. Velsipity Summary'!$CM:$CM,$G94) -> #REF! | X94: =SUMIFS('1. Velsipity Summary'!CS:CS,'1. Velsipity Summary'!#REF!,$P94,'1. Velsipity Summary'!$CM:$CM,$G94) -> #REF! | Y94: =SUMIFS('1. Velsipity Summary'!CT:CT,'1. Velsipity Summary'!#REF!,$P94,'1. Velsipity Summary'!$CM:$CM,$G94) -> #REF! | Z94: =SUMIFS('1. Velsipity Summary'!CU:CU,'1. Velsipity Summary'!#REF!,$P94,'1. Velsipity Summary'!$CM:$CM,$G94) -> #REF! | AA94: =SUMIFS('1. Velsipity Summary'!CV:CV,'1. Velsipity Summary'!#REF!,$P94,'1. Velsipity Summary'!$CM:$CM,$G94) -> #REF! | AB94: =SUMIFS('1. Velsipity Summary'!CW:CW,'1. Velsipity Summary'!#REF!,$P94,'1. Velsipity Summary'!$CM:$CM,$G94) -> #REF! | AC94: =SUMIFS('1. Velsipity Summary'!CX:CX,'1. Velsipity Summary'!#REF!,$P94,'1. Velsipity Summary'!$CM:$CM,$G94) -> #REF! | AD94: =SUMIFS('1. Velsipity Summary'!CY:CY,'1. Velsipity Summary'!#REF!,$P94,'1. Velsipity Summary'!$CM:$CM,$G94) -> #REF! | AE94: =SUM(S94:AD94) -> #REF! | AI94: =SUM(S94:U94) -> #REF! | AJ94: =SUM(V94:X94) -> #REF! | AK94: =SUM(Y94:AA94) -> #REF! | AL94: =SUM(AB94:AD94) -> #REF! | AM94: =SUM(AI94:AL94) -> #REF! | AN94: =AM94-AE94 -> #REF! | AP94: =SUM(AI94:AJ94) -> #REF! | AQ94: =SUM(AK94:AL94) -> #REF! | AR94: =AP94+AQ94-AM94 -> #REF!
B95: C110106102 | C95: 10106102 | D95: 东北区-Nefecon | E95: A&P | F95: A&P | G95: Nefecon | H95: 2026 | I95: Budget | J95: Commercial | K95: Mainland | L95: CPO Operations | M95: Sales Team | N95: Northeast | O95: Northeast | P95: 东北区 | Q95: A&P汇总 | R95: A&P汇总 | S95: =SUMIFS('1. Velsipity Summary'!CN:CN,'1. Velsipity Summary'!#REF!,$P95,'1. Velsipity Summary'!$CM:$CM,$G95) -> #REF! | T95: =SUMIFS('1. Velsipity Summary'!CO:CO,'1. Velsipity Summary'!#REF!,$P95,'1. Velsipity Summary'!$CM:$CM,$G95) -> #REF! | U95: =SUMIFS('1. Velsipity Summary'!CP:CP,'1. Velsipity Summary'!#REF!,$P95,'1. Velsipity Summary'!$CM:$CM,$G95) -> #REF! | V95: =SUMIFS('1. Velsipity Summary'!CQ:CQ,'1. Velsipity Summary'!#REF!,$P95,'1. Velsipity Summary'!$CM:$CM,$G95) -> #REF! | W95: =SUMIFS('1. Velsipity Summary'!CR:CR,'1. Velsipity Summary'!#REF!,$P95,'1. Velsipity Summary'!$CM:$CM,$G95) -> #REF! | X95: =SUMIFS('1. Velsipity Summary'!CS:CS,'1. Velsipity Summary'!#REF!,$P95,'1. Velsipity Summary'!$CM:$CM,$G95) -> #REF! | Y95: =SUMIFS('1. Velsipity Summary'!CT:CT,'1. Velsipity Summary'!#REF!,$P95,'1. Velsipity Summary'!$CM:$CM,$G95) -> #REF! | Z95: =SUMIFS('1. Velsipity Summary'!CU:CU,'1. Velsipity Summary'!#REF!,$P95,'1. Velsipity Summary'!$CM:$CM,$G95) -> #REF! | AA95: =SUMIFS('1. Velsipity Summary'!CV:CV,'1. Velsipity Summary'!#REF!,$P95,'1. Velsipity Summary'!$CM:$CM,$G95) -> #REF! | AB95: =SUMIFS('1. Velsipity Summary'!CW:CW,'1. Velsipity Summary'!#REF!,$P95,'1. Velsipity Summary'!$CM:$CM,$G95) -> #REF! | AC95: =SUMIFS('1. Velsipity Summary'!CX:CX,'1. Velsipity Summary'!#REF!,$P95,'1. Velsipity Summary'!$CM:$CM,$G95) -> #REF! | AD95: =SUMIFS('1. Velsipity Summary'!CY:CY,'1. Velsipity Summary'!#REF!,$P95,'1. Velsipity Summary'!$CM:$CM,$G95) -> #REF! | AE95: =SUM(S95:AD95) -> #REF! | AI95: =SUM(S95:U95) -> #REF! | AJ95: =SUM(V95:X95) -> #REF! | AK95: =SUM(Y95:AA95) -> #REF! | AL95: =SUM(AB95:AD95) -> #REF! | AM95: =SUM(AI95:AL95) -> #REF! | AN95: =AM95-AE95 -> #REF! | AP95: =SUM(AI95:AJ95) -> #REF! | AQ95: =SUM(AK95:AL95) -> #REF! | AR95: =AP95+AQ95-AM95 -> #REF!
B96: C110105102 | C96: 10105102 | D96: 南区-Nefecon | E96: A&P | F96: A&P | G96: Nefecon | H96: 2026 | I96: Budget | J96: Commercial | K96: Mainland | L96: CPO Operations | M96: Sales Team | N96: South | O96: South | P96: 南区 | Q96: A&P汇总 | R96: A&P汇总 | S96: =SUMIFS('1. Velsipity Summary'!CN:CN,'1. Velsipity Summary'!#REF!,$P96,'1. Velsipity Summary'!$CM:$CM,$G96) -> #REF! | T96: =SUMIFS('1. Velsipity Summary'!CO:CO,'1. Velsipity Summary'!#REF!,$P96,'1. Velsipity Summary'!$CM:$CM,$G96) -> #REF! | U96: =SUMIFS('1. Velsipity Summary'!CP:CP,'1. Velsipity Summary'!#REF!,$P96,'1. Velsipity Summary'!$CM:$CM,$G96) -> #REF! | V96: =SUMIFS('1. Velsipity Summary'!CQ:CQ,'1. Velsipity Summary'!#REF!,$P96,'1. Velsipity Summary'!$CM:$CM,$G96) -> #REF! | W96: =SUMIFS('1. Velsipity Summary'!CR:CR,'1. Velsipity Summary'!#REF!,$P96,'1. Velsipity Summary'!$CM:$CM,$G96) -> #REF! | X96: =SUMIFS('1. Velsipity Summary'!CS:CS,'1. Velsipity Summary'!#REF!,$P96,'1. Velsipity Summary'!$CM:$CM,$G96) -> #REF! | Y96: =SUMIFS('1. Velsipity Summary'!CT:CT,'1. Velsipity Summary'!#REF!,$P96,'1. Velsipity Summary'!$CM:$CM,$G96) -> #REF! | Z96: =SUMIFS('1. Velsipity Summary'!CU:CU,'1. Velsipity Summary'!#REF!,$P96,'1. Velsipity Summary'!$CM:$CM,$G96) -> #REF! | AA96: =SUMIFS('1. Velsipity Summary'!CV:CV,'1. Velsipity Summary'!#REF!,$P96,'1. Velsipity Summary'!$CM:$CM,$G96) -> #REF! | AB96: =SUMIFS('1. Velsipity Summary'!CW:CW,'1. Velsipity Summary'!#REF!,$P96,'1. Velsipity Summary'!$CM:$CM,$G96) -> #REF! | AC96: =SUMIFS('1. Velsipity Summary'!CX:CX,'1. Velsipity Summary'!#REF!,$P96,'1. Velsipity Summary'!$CM:$CM,$G96) -> #REF! | AD96: =SUMIFS('1. Velsipity Summary'!CY:CY,'1. Velsipity Summary'!#REF!,$P96,'1. Velsipity Summary'!$CM:$CM,$G96) -> #REF! | AE96: =SUM(S96:AD96) -> #REF! | AI96: =SUM(S96:U96) -> #REF! | AJ96: =SUM(V96:X96) -> #REF! | AK96: =SUM(Y96:AA96) -> #REF! | AL96: =SUM(AB96:AD96) -> #REF! | AM96: =SUM(AI96:AL96) -> #REF! | AN96: =AM96-AE96 -> #REF! | AP96: =SUM(AI96:AJ96) -> #REF! | AQ96: =SUM(AK96:AL96) -> #REF! | AR96: =AP96+AQ96-AM96 -> #REF!
B97: C110107102 | C97: 10107102 | D97: 西区-Nefecon | E97: A&P | F97: A&P | G97: Nefecon | H97: 2026 | I97: Budget | J97: Commercial | K97: Mainland | L97: CPO Operations | M97: Sales Team | N97: West | O97: West | P97: 西区 | Q97: A&P汇总 | R97: A&P汇总 | S97: =SUMIFS('1. Velsipity Summary'!CN:CN,'1. Velsipity Summary'!#REF!,$P97,'1. Velsipity Summary'!$CM:$CM,$G97) -> #REF! | T97: =SUMIFS('1. Velsipity Summary'!CO:CO,'1. Velsipity Summary'!#REF!,$P97,'1. Velsipity Summary'!$CM:$CM,$G97) -> #REF! | U97: =SUMIFS('1. Velsipity Summary'!CP:CP,'1. Velsipity Summary'!#REF!,$P97,'1. Velsipity Summary'!$CM:$CM,$G97) -> #REF! | V97: =SUMIFS('1. Velsipity Summary'!CQ:CQ,'1. Velsipity Summary'!#REF!,$P97,'1. Velsipity Summary'!$CM:$CM,$G97) -> #REF! | W97: =SUMIFS('1. Velsipity Summary'!CR:CR,'1. Velsipity Summary'!#REF!,$P97,'1. Velsipity Summary'!$CM:$CM,$G97) -> #REF! | X97: =SUMIFS('1. Velsipity Summary'!CS:CS,'1. Velsipity Summary'!#REF!,$P97,'1. Velsipity Summary'!$CM:$CM,$G97) -> #REF! | Y97: =SUMIFS('1. Velsipity Summary'!CT:CT,'1. Velsipity Summary'!#REF!,$P97,'1. Velsipity Summary'!$CM:$CM,$G97) -> #REF! | Z97: =SUMIFS('1. Velsipity Summary'!CU:CU,'1. Velsipity Summary'!#REF!,$P97,'1. Velsipity Summary'!$CM:$CM,$G97) -> #REF! | AA97: =SUMIFS('1. Velsipity Summary'!CV:CV,'1. Velsipity Summary'!#REF!,$P97,'1. Velsipity Summary'!$CM:$CM,$G97) -> #REF! | AB97: =SUMIFS('1. Velsipity Summary'!CW:CW,'1. Velsipity Summary'!#REF!,$P97,'1. Velsipity Summary'!$CM:$CM,$G97) -> #REF! | AC97: =SUMIFS('1. Velsipity Summary'!CX:CX,'1. Velsipity Summary'!#REF!,$P97,'1. Velsipity Summary'!$CM:$CM,$G97) -> #REF! | AD97: =SUMIFS('1. Velsipity Summary'!CY:CY,'1. Velsipity Summary'!#REF!,$P97,'1. Velsipity Summary'!$CM:$CM,$G97) -> #REF! | AE97: =SUM(S97:AD97) -> #REF! | AG97: =SUM(AE88:AE97) -> #REF! | AH97: =AG97-'1. Velsipity Summary'!CZ13 -> #REF! | AI97: =SUM(S97:U97) -> #REF! | AJ97: =SUM(V97:X97) -> #REF! | AK97: =SUM(Y97:AA97) -> #REF! | AL97: =SUM(AB97:AD97) -> #REF! | AM97: =SUM(AI97:AL97) -> #REF! | AN97: =AM97-AE97 -> #REF! | AP97: =SUM(AI97:AJ97) -> #REF! | AQ97: =SUM(AK97:AL97) -> #REF! | AR97: =AP97+AQ97-AM97 -> #REF!
B98: C110110100 | C98: 10110100 | D98: Velsipity Sales | E98: A&P | F98: A&P | G98: Velsipity | H98: 2026 | I98: Budget | J98: Commercial | K98: Mainland | L98: CPO Operations | M98: Sales Team | N98: Velsipity Sales | O98: Velsipity Sales | P98: Velsipity Sales | Q98: A&P汇总 | R98: A&P汇总 | S98: =SUMIFS('1. Velsipity Summary'!CN:CN,'1. Velsipity Summary'!#REF!,$P98,'1. Velsipity Summary'!$CM:$CM,$G98) -> #REF! | T98: =SUMIFS('1. Velsipity Summary'!CO:CO,'1. Velsipity Summary'!#REF!,$P98,'1. Velsipity Summary'!$CM:$CM,$G98) -> #REF! | U98: =SUMIFS('1. Velsipity Summary'!CP:CP,'1. Velsipity Summary'!#REF!,$P98,'1. Velsipity Summary'!$CM:$CM,$G98) -> #REF! | V98: =SUMIFS('1. Velsipity Summary'!CQ:CQ,'1. Velsipity Summary'!#REF!,$P98,'1. Velsipity Summary'!$CM:$CM,$G98) -> #REF! | W98: =SUMIFS('1. Velsipity Summary'!CR:CR,'1. Velsipity Summary'!#REF!,$P98,'1. Velsipity Summary'!$CM:$CM,$G98) -> #REF! | X98: =SUMIFS('1. Velsipity Summary'!CS:CS,'1. Velsipity Summary'!#REF!,$P98,'1. Velsipity Summary'!$CM:$CM,$G98) -> #REF! | Y98: =SUMIFS('1. Velsipity Summary'!CT:CT,'1. Velsipity Summary'!#REF!,$P98,'1. Velsipity Summary'!$CM:$CM,$G98) -> #REF! | Z98: =SUMIFS('1. Velsipity Summary'!CU:CU,'1. Velsipity Summary'!#REF!,$P98,'1. Velsipity Summary'!$CM:$CM,$G98) -> #REF! | AA98: =SUMIFS('1. Velsipity Summary'!CV:CV,'1. Velsipity Summary'!#REF!,$P98,'1. Velsipity Summary'!$CM:$CM,$G98) -> #REF! | AB98: =SUMIFS('1. Velsipity Summary'!CW:CW,'1. Velsipity Summary'!#REF!,$P98,'1. Velsipity Summary'!$CM:$CM,$G98) -> #REF! | AC98: =SUMIFS('1. Velsipity Summary'!CX:CX,'1. Velsipity Summary'!#REF!,$P98,'1. Velsipity Summary'!$CM:$CM,$G98) -> #REF! | AD98: =SUMIFS('1. Velsipity Summary'!CY:CY,'1. Velsipity Summary'!#REF!,$P98,'1. Velsipity Summary'!$CM:$CM,$G98) -> #REF! | AE98: =SUM(S98:AD98) -> #REF! | AG98: =AE98 -> #REF! | AH98: =AG98-'1. Velsipity Summary'!CZ27 -> #REF! | AI98: =SUM(S98:U98) -> #REF! | AJ98: =SUM(V98:X98) -> #REF! | AK98: =SUM(Y98:AA98) -> #REF! | AL98: =SUM(AB98:AD98) -> #REF! | AM98: =SUM(AI98:AL98) -> #REF! | AN98: =AM98-AE98 -> #REF! | AP98: =SUM(AI98:AJ98) -> #REF! | AQ98: =SUM(AK98:AL98) -> #REF! | AR98: =AP98+AQ98-AM98 -> #REF!

Sheet Sales HC by Dept & T&E Segment
A1: 行标签 | B1: Department 2 | C1: Department 3 | D1: Department 4 | E1: Department 5 | F1: 中文区域名称 | G1: 产品 | H1: 岗位标签 | I1: 求和项:202603 | J1: 求和项:202606 | K1: 求和项:202609 | L1: 求和项:202612 | N1: Q1 T&E | O1: Q2 T&E | P1: Q3 T&E | Q1: Q4 T&E | R1: FY | S1: Total | T1: check | V1: Jan | W1: Feb | X1: Mar | Y1: Apr | Z1: May | AA1: Jun | AB1: Jul | AC1: Aug | AD1: Sep | AE1: Oct | AF1: Nov | AG1: Dec | AH1: FY | AI1: check | AK1: 科室会 | AL1: Jan | AM1: Feb | AN1: Mar | AO1: Apr | AP1: May | AQ1: Jun | AR1: Jul | AS1: Aug | AT1: Sep | AU1: Oct | AV1: Nov | AW1: Dec | AX1: FY | AZ1: 其他会
A2: Commercial | B2: Etrasimod Sales | F2: Velsipity Sales | G2: Velsipity | H2: DSM | I2: 23 | J2: 23 | K2: 23 | L2: 23 | N2: =SUMIFS('Sales T&E & 科室会WP'!$N:$N,'Sales T&E & 科室会WP'!$L:$L,$G2,'Sales T&E & 科室会WP'!$M:$M,$H2)*3*I2 -> 621000 | O2: =SUMIFS('Sales T&E & 科室会WP'!$N:$N,'Sales T&E & 科室会WP'!$L:$L,$G2,'Sales T&E & 科室会WP'!$M:$M,$H2)*3*J2 -> 621000 | P2: =SUMIFS('Sales T&E & 科室会WP'!$N:$N,'Sales T&E & 科室会WP'!$L:$L,$G2,'Sales T&E & 科室会WP'!$M:$M,$H2)*3*K2 -> 621000 | Q2: =SUMIFS('Sales T&E & 科室会WP'!$N:$N,'Sales T&E & 科室会WP'!$L:$L,$G2,'Sales T&E & 科室会WP'!$M:$M,$H2)*3*L2 -> 621000 | R2: =SUM(N2:Q2) -> 2484000 | V2: =$N2/3 -> 207000 | W2: =$N2/3 -> 207000 | X2: =$N2/3 -> 207000 | Y2: =$O2/3 -> 207000 | Z2: =$O2/3 -> 207000 | AA2: =$O2/3 -> 207000 | AB2: =$P2/3 -> 207000 | AC2: =$P2/3 -> 207000 | AD2: =$P2/3 -> 207000 | AE2: =$Q2/3 -> 207000 | AF2: =$Q2/3 -> 207000 | AG2: =$Q2/3 -> 207000 | AH2: =SUM(V2:AG2) -> 2484000 | AI2: =AH2-R2 -> 0 | AO2: =SUMIFS('Sales T&E & 科室会WP'!$T:$T,'Sales T&E & 科室会WP'!$Q:$Q,$H2)*$J2 -> 69000 | AP2: =SUMIFS('Sales T&E & 科室会WP'!$T:$T,'Sales T&E & 科室会WP'!$Q:$Q,$H2)*$J2 -> 69000 | AQ2: =SUMIFS('Sales T&E & 科室会WP'!$T:$T,'Sales T&E & 科室会WP'!$Q:$Q,$H2)*$J2 -> 69000 | AR2: =SUMIFS('Sales T&E & 科室会WP'!$T:$T,'Sales T&E & 科室会WP'!$Q:$Q,$H2)*$K2 -> 69000 | AS2: =SUMIFS('Sales T&E & 科室会WP'!$T:$T,'Sales T&E & 科室会WP'!$Q:$Q,$H2)*$K2 -> 69000 | AT2: =SUMIFS('Sales T&E & 科室会WP'!$T:$T,'Sales T&E & 科室会WP'!$Q:$Q,$H2)*$K2 -> 69000 | AU2: =SUMIFS('Sales T&E & 科室会WP'!$T:$T,'Sales T&E & 科室会WP'!$Q:$Q,$H2)*$L2 -> 69000 | AV2: =SUMIFS('Sales T&E & 科室会WP'!$T:$T,'Sales T&E & 科室会WP'!$Q:$Q,$H2)*$L2 -> 69000 | AW2: =SUMIFS('Sales T&E & 科室会WP'!$T:$T,'Sales T&E & 科室会WP'!$Q:$Q,$H2)*$L2 -> 69000 | AX2: =SUM(AL2:AW2) -> 621000
A3: Commercial | B3: Etrasimod Sales | F3: Velsipity Sales | G3: Velsipity | H3: NSD | I3: 1 | J3: 1 | K3: 1 | L3: 1 | N3: =SUMIFS('Sales T&E & 科室会WP'!$N:$N,'Sales T&E & 科室会WP'!$L:$L,$G3,'Sales T&E & 科室会WP'!$M:$M,$H3)*3*I3 -> 66000 | O3: =SUMIFS('Sales T&E & 科室会WP'!$N:$N,'Sales T&E & 科室会WP'!$L:$L,$G3,'Sales T&E & 科室会WP'!$M:$M,$H3)*3*J3 -> 66000 | P3: =SUMIFS('Sales T&E & 科室会WP'!$N:$N,'Sales T&E & 科室会WP'!$L:$L,$G3,'Sales T&E & 科室会WP'!$M:$M,$H3)*3*K3 -> 66000 | Q3: =SUMIFS('Sales T&E & 科室会WP'!$N:$N,'Sales T&E & 科室会WP'!$L:$L,$G3,'Sales T&E & 科室会WP'!$M:$M,$H3)*3*L3 -> 66000 | R3: =SUM(N3:Q3) -> 264000 | V3: =$N3/3 -> 22000 | W3: =$N3/3 -> 22000 | X3: =$N3/3 -> 22000 | Y3: =$O3/3 -> 22000 | Z3: =$O3/3 -> 22000 | AA3: =$O3/3 -> 22000 | AB3: =$P3/3 -> 22000 | AC3: =$P3/3 -> 22000 | AD3: =$P3/3 -> 22000 | AE3: =$Q3/3 -> 22000 | AF3: =$Q3/3 -> 22000 | AG3: =$Q3/3 -> 22000 | AH3: =SUM(V3:AG3) -> 264000 | AI3: =AH3-R3 -> 0 | AO3: =SUMIFS('Sales T&E & 科室会WP'!$T:$T,'Sales T&E & 科室会WP'!$Q:$Q,$H3)*$J3 -> 0 | AP3: =SUMIFS('Sales T&E & 科室会WP'!$T:$T,'Sales T&E & 科室会WP'!$Q:$Q,$H3)*$J3 -> 0 | AQ3: =SUMIFS('Sales T&E & 科室会WP'!$T:$T,'Sales T&E & 科室会WP'!$Q:$Q,$H3)*$J3 -> 0 | AR3: =SUMIFS('Sales T&E & 科室会WP'!$T:$T,'Sales T&E & 科室会WP'!$Q:$Q,$H3)*$K3 -> 0 | AS3: =SUMIFS('Sales T&E & 科室会WP'!$T:$T,'Sales T&E & 科室会WP'!$Q:$Q,$H3)*$K3 -> 0 | AT3: =SUMIFS('Sales T&E & 科室会WP'!$T:$T,'Sales T&E & 科室会WP'!$Q:$Q,$H3)*$K3 -> 0 | AU3: =SUMIFS('Sales T&E & 科室会WP'!$T:$T,'Sales T&E & 科室会WP'!$Q:$Q,$H3)*$L3 -> 0 | AV3: =SUMIFS('Sales T&E & 科室会WP'!$T:$T,'Sales T&E & 科室会WP'!$Q:$Q,$H3)*$L3 -> 0 | AW3: =SUMIFS('Sales T&E & 科室会WP'!$T:$T,'Sales T&E & 科室会WP'!$Q:$Q,$H3)*$L3 -> 0 | AX3: =SUM(AL3:AW3) -> 0
A4: Commercial | B4: Etrasimod Sales | F4: Velsipity Sales | G4: Velsipity | H4: RSD | I4: 5 | J4: 5 | K4: 5 | L4: 5 | N4: =SUMIFS('Sales T&E & 科室会WP'!$N:$N,'Sales T&E & 科室会WP'!$L:$L,$G4,'Sales T&E & 科室会WP'!$M:$M,$H4)*3*I4 -> 330000 | O4: =SUMIFS('Sales T&E & 科室会WP'!$N:$N,'Sales T&E & 科室会WP'!$L:$L,$G4,'Sales T&E & 科室会WP'!$M:$M,$H4)*3*J4 -> 330000 | P4: =SUMIFS('Sales T&E & 科室会WP'!$N:$N,'Sales T&E & 科室会WP'!$L:$L,$G4,'Sales T&E & 科室会WP'!$M:$M,$H4)*3*K4 -> 330000 | Q4: =SUMIFS('Sales T&E & 科室会WP'!$N:$N,'Sales T&E & 科室会WP'!$L:$L,$G4,'Sales T&E & 科室会WP'!$M:$M,$H4)*3*L4 -> 330000 | R4: =SUM(N4:Q4) -> 1320000 | V4: =$N4/3 -> 110000 | W4: =$N4/3 -> 110000 | X4: =$N4/3 -> 110000 | Y4: =$O4/3 -> 110000 | Z4: =$O4/3 -> 110000 | AA4: =$O4/3 -> 110000 | AB4: =$P4/3 -> 110000 | AC4: =$P4/3 -> 110000 | AD4: =$P4/3 -> 110000 | AE4: =$Q4/3 -> 110000 | AF4: =$Q4/3 -> 110000 | AG4: =$Q4/3 -> 110000 | AH4: =SUM(V4:AG4) -> 1320000 | AI4: =AH4-R4 -> 0 | AO4: =SUMIFS('Sales T&E & 科室会WP'!$T:$T,'Sales T&E & 科室会WP'!$Q:$Q,$H4)*$J4 -> 7500 | AP4: =SUMIFS('Sales T&E & 科室会WP'!$T:$T,'Sales T&E & 科室会WP'!$Q:$Q,$H4)*$J4 -> 7500 | AQ4: =SUMIFS('Sales T&E & 科室会WP'!$T:$T,'Sales T&E & 科室会WP'!$Q:$Q,$H4)*$J4 -> 7500 | AR4: =SUMIFS('Sales T&E & 科室会WP'!$T:$T,'Sales T&E & 科室会WP'!$Q:$Q,$H4)*$K4 -> 7500 | AS4: =SUMIFS('Sales T&E & 科室会WP'!$T:$T,'Sales T&E & 科室会WP'!$Q:$Q,$H4)*$K4 -> 7500 | AT4: =SUMIFS('Sales T&E & 科室会WP'!$T:$T,'Sales T&E & 科室会WP'!$Q:$Q,$H4)*$K4 -> 7500 | AU4: =SUMIFS('Sales T&E & 科室会WP'!$T:$T,'Sales T&E & 科室会WP'!$Q:$Q,$H4)*$L4 -> 7500 | AV4: =SUMIFS('Sales T&E & 科室会WP'!$T:$T,'Sales T&E & 科室会WP'!$Q:$Q,$H4)*$L4 -> 7500 | AW4: =SUMIFS('Sales T&E & 科室会WP'!$T:$T,'Sales T&E & 科室会WP'!$Q:$Q,$H4)*$L4 -> 7500 | AX4: =SUM(AL4:AW4) -> 67500
A5: Commercial | B5: Etrasimod Sales | C5: (空白) | D5: (空白) | E5: (空白) | F5: Velsipity Sales | G5: Velsipity | H5: MR | I5: 40 | J5: 60 | K5: 100 | L5: 180 | N5: =SUMIFS('Sales T&E & 科室会WP'!$N:$N,'Sales T&E & 科室会WP'!$L:$L,$G5,'Sales T&E & 科室会WP'!$M:$M,$H5)*3*I5 -> 600000 | O5: =SUMIFS('Sales T&E & 科室会WP'!$N:$N,'Sales T&E & 科室会WP'!$L:$L,$G5,'Sales T&E & 科室会WP'!$M:$M,$H5)*3*J5 -> 900000 | P5: =SUMIFS('Sales T&E & 科室会WP'!$N:$N,'Sales T&E & 科室会WP'!$L:$L,$G5,'Sales T&E & 科室会WP'!$M:$M,$H5)*3*K5 -> 1500000 | Q5: =SUMIFS('Sales T&E & 科室会WP'!$N:$N,'Sales T&E & 科室会WP'!$L:$L,$G5,'Sales T&E & 科室会WP'!$M:$M,$H5)*3*L5 -> 2700000 | R5: =SUM(N5:Q5) -> 5700000 | S5: =SUM(R2:R5) -> 9768000 | T5: =S5-SUM('Sales T&E & 科室会WP'!P51) -> 2118000 | V5: =$N5/3 -> 200000 | W5: =$N5/3 -> 200000 | X5: =$N5/3 -> 200000 | Y5: =$O5/3 -> 300000 | Z5: =$O5/3 -> 300000 | AA5: =$O5/3 -> 300000 | AB5: =$P5/3 -> 500000 | AC5: =$P5/3 -> 500000 | AD5: =$P5/3 -> 500000 | AE5: =$Q5/3 -> 900000 | AF5: =$Q5/3 -> 900000 | AG5: =$Q5/3 -> 900000 | AH5: =SUM(V5:AG5) -> 5700000 | AI5: =AH5-R5 -> 0 | AO5: =SUMIFS('Sales T&E & 科室会WP'!$T:$T,'Sales T&E & 科室会WP'!$Q:$Q,$H5)*$J5 -> 180000 | AP5: =SUMIFS('Sales T&E & 科室会WP'!$T:$T,'Sales T&E & 科室会WP'!$Q:$Q,$H5)*$J5 -> 180000 | AQ5: =SUMIFS('Sales T&E & 科室会WP'!$T:$T,'Sales T&E & 科室会WP'!$Q:$Q,$H5)*$J5 -> 180000 | AR5: =SUMIFS('Sales T&E & 科室会WP'!$T:$T,'Sales T&E & 科室会WP'!$Q:$Q,$H5)*$K5 -> 300000 | AS5: =SUMIFS('Sales T&E & 科室会WP'!$T:$T,'Sales T&E & 科室会WP'!$Q:$Q,$H5)*$K5 -> 300000 | AT5: =SUMIFS('Sales T&E & 科室会WP'!$T:$T,'Sales T&E & 科室会WP'!$Q:$Q,$H5)*$K5 -> 300000 | AU5: =SUMIFS('Sales T&E & 科室会WP'!$T:$T,'Sales T&E & 科室会WP'!$Q:$Q,$H5)*$L5 -> 540000 | AV5: =SUMIFS('Sales T&E & 科室会WP'!$T:$T,'Sales T&E & 科室会WP'!$Q:$Q,$H5)*$L5 -> 540000 | AW5: =SUMIFS('Sales T&E & 科室会WP'!$T:$T,'Sales T&E & 科室会WP'!$Q:$Q,$H5)*$L5 -> 540000 | AX5: =SUM(AL5:AW5) -> 3060000
A6: Commercial | B6: ID & IM BU | C6: ID - Sales | D6: ID - Xerava | E6: Central | F6: 华中区 | G6: Xerava | V6: =$N6/3 -> 0 | W6: =$N6/3 -> 0 | X6: =$N6/3 -> 0 | Y6: =$O6/3 -> 0 | Z6: =$O6/3 -> 0 | AA6: =$O6/3 -> 0 | AB6: =$P6/3 -> 0 | AC6: =$P6/3 -> 0 | AD6: =$P6/3 -> 0 | AE6: =$Q6/3 -> 0 | AF6: =$Q6/3 -> 0 | AG6: =$Q6/3 -> 0 | AH6: =SUM(V6:AG6) -> 0 | AI6: =AH6-R6 -> 0 | AL6: =SUMIFS('Sales T&E & 科室会WP'!$T:$T,'Sales T&E & 科室会WP'!$Q:$Q,$H6)*$I6 -> 0 | AM6: =SUMIFS('Sales T&E & 科室会WP'!$T:$T,'Sales T&E & 科室会WP'!$Q:$Q,$H6)*$I6 -> 0 | AN6: =SUMIFS('Sales T&E & 科室会WP'!$T:$T,'Sales T&E & 科室会WP'!$Q:$Q,$H6)*$I6 -> 0 | AO6: =SUMIFS('Sales T&E & 科室会WP'!$T:$T,'Sales T&E & 科室会WP'!$Q:$Q,$H6)*$J6 -> 0 | AP6: =SUMIFS('Sales T&E & 科室会WP'!$T:$T,'Sales T&E & 科室会WP'!$Q:$Q,$H6)*$J6 -> 0 | AQ6: =SUMIFS('Sales T&E & 科室会WP'!$T:$T,'Sales T&E & 科室会WP'!$Q:$Q,$H6)*$J6 -> 0 | AR6: =SUMIFS('Sales T&E & 科室会WP'!$T:$T,'Sales T&E & 科室会WP'!$Q:$Q,$H6)*$K6 -> 0 | AS6: =SUMIFS('Sales T&E & 科室会WP'!$T:$T,'Sales T&E & 科室会WP'!$Q:$Q,$H6)*$K6 -> 0 | AT6: =SUMIFS('Sales T&E & 科室会WP'!$T:$T,'Sales T&E & 科室会WP'!$Q:$Q,$H6)*$K6 -> 0 | AU6: =SUMIFS('Sales T&E & 科室会WP'!$T:$T,'Sales T&E & 科室会WP'!$Q:$Q,$H6)*$L6 -> 0 | AV6: =SUMIFS('Sales T&E & 科室会WP'!$T:$T,'Sales T&E & 科室会WP'!$Q:$Q,$H6)*$L6 -> 0 | AW6: =SUMIFS('Sales T&E & 科室会WP'!$T:$T,'Sales T&E & 科室会WP'!$Q:$Q,$H6)*$L6 -> 0 | AX6: =SUM(AL6:AW6) -> 0
A7: Commercial | B7: ID & IM BU | C7: ID - Sales | D7: ID - Xerava | E7: Central | F7: 华中区 | G7: Xerava | H7: DSM | I7: 4 | J7: 4 | K7: 4 | L7: 4 | N7: =SUMIFS('Sales T&E & 科室会WP'!$N:$N,'Sales T&E & 科室会WP'!$L:$L,$G7,'Sales T&E & 科室会WP'!$M:$M,$H7)*3*I7 -> 96000 | O7: =SUMIFS('Sales T&E & 科室会WP'!$N:$N,'Sales T&E & 科室会WP'!$L:$L,$G7,'Sales T&E & 科室会WP'!$M:$M,$H7)*3*J7 -> 96000 | P7: =SUMIFS('Sales T&E & 科室会WP'!$N:$N,'Sales T&E & 科室会WP'!$L:$L,$G7,'Sales T&E & 科室会WP'!$M:$M,$H7)*3*K7 -> 96000 | Q7: =SUMIFS('Sales T&E & 科室会WP'!$N:$N,'Sales T&E & 科室会WP'!$L:$L,$G7,'Sales T&E & 科室会WP'!$M:$M,$H7)*3*L7 -> 96000 | R7: =SUM(N7:Q7) -> 384000 | V7: =$N7/3 -> 32000 | W7: =$N7/3 -> 32000 | X7: =$N7/3 -> 32000 | Y7: =$O7/3 -> 32000 | Z7: =$O7/3 -> 32000 | AA7: =$O7/3 -> 32000 | AB7: =$P7/3 -> 32000 | AC7: =$P7/3 -> 32000 | AD7: =$P7/3 -> 32000 | AE7: =$Q7/3 -> 32000 | AF7: =$Q7/3 -> 32000 | AG7: =$Q7/3 -> 32000 | AH7: =SUM(V7:AG7) -> 384000 | AI7: =AH7-R7 -> 0 | AL7: =SUMIFS('Sales T&E & 科室会WP'!$T:$T,'Sales T&E & 科室会WP'!$Q:$Q,$H7)*$I7 -> 12000 | AM7: =SUMIFS('Sales T&E & 科室会WP'!$T:$T,'Sales T&E & 科室会WP'!$Q:$Q,$H7)*$I7 -> 12000 | AN7: =SUMIFS('Sales T&E & 科室会WP'!$T:$T,'Sales T&E & 科室会WP'!$Q:$Q,$H7)*$I7 -> 12000 | AO7: =SUMIFS('Sales T&E & 科室会WP'!$T:$T,'Sales T&E & 科室会WP'!$Q:$Q,$H7)*$J7 -> 12000 | AP7: =SUMIFS('Sales T&E & 科室会WP'!$T:$T,'Sales T&E & 科室会WP'!$Q:$Q,$H7)*$J7 -> 12000 | AQ7: =SUMIFS('Sales T&E & 科室会WP'!$T:$T,'Sales T&E & 科室会WP'!$Q:$Q,$H7)*$J7 -> 12000 | AR7: =SUMIFS('Sales T&E & 科室会WP'!$T:$T,'Sales T&E & 科室会WP'!$Q:$Q,$H7)*$K7 -> 12000 | AS7: =SUMIFS('Sales T&E & 科室会WP'!$T:$T,'Sales T&E & 科室会WP'!$Q:$Q,$H7)*$K7 -> 12000 | AT7: =SUMIFS('Sales T&E & 科室会WP'!$T:$T,'Sales T&E & 科室会WP'!$Q:$Q,$H7)*$K7 -> 12000 | AU7: =SUMIFS('Sales T&E & 科室会WP'!$T:$T,'Sales T&E & 科室会WP'!$Q:$Q,$H7)*$L7 -> 12000 | AV7: =SUMIFS('Sales T&E & 科室会WP'!$T:$T,'Sales T&E & 科室会WP'!$Q:$Q,$H7)*$L7 -> 12000 | AW7: =SUMIFS('Sales T&E & 科室会WP'!$T:$T,'Sales T&E & 科室会WP'!$Q:$Q,$H7)*$L7 -> 12000 | AX7: =SUM(AL7:AW7) -> 144000
A8: Commercial | B8: ID & IM BU | C8: ID - Sales | D8: ID - Xerava | E8: Central | F8: 华中区 | G8: Xerava | H8: MR | I8: 12 | J8: 12 | K8: 12 | L8: 12 | N8: =SUMIFS('Sales T&E & 科室会WP'!$N:$N,'Sales T&E & 科室会WP'!$L:$L,$G8,'Sales T&E & 科室会WP'!$M:$M,$H8)*3*I8 -> 180000 | O8: =SUMIFS('Sales T&E & 科室会WP'!$N:$N,'Sales T&E & 科室会WP'!$L:$L,$G8,'Sales T&E & 科室会WP'!$M:$M,$H8)*3*J8 -> 180000 | P8: =SUMIFS('Sales T&E & 科室会WP'!$N:$N,'Sales T&E & 科室会WP'!$L:$L,$G8,'Sales T&E & 科室会WP'!$M:$M,$H8)*3*K8 -> 180000 | Q8: =SUMIFS('Sales T&E & 科室会WP'!$N:$N,'Sales T&E & 科室会WP'!$L:$L,$G8,'Sales T&E & 科室会WP'!$M:$M,$H8)*3*L8 -> 180000 | R8: =SUM(N8:Q8) -> 720000 | V8: =$N8/3 -> 60000 | W8: =$N8/3 -> 60000 | X8: =$N8/3 -> 60000 | Y8: =$O8/3 -> 60000 | Z8: =$O8/3 -> 60000 | AA8: =$O8/3 -> 60000 | AB8: =$P8/3 -> 60000 | AC8: =$P8/3 -> 60000 | AD8: =$P8/3 -> 60000 | AE8: =$Q8/3 -> 60000 | AF8: =$Q8/3 -> 60000 | AG8: =$Q8/3 -> 60000 | AH8: =SUM(V8:AG8) -> 720000 | AI8: =AH8-R8 -> 0 | AL8: =SUMIFS('Sales T&E & 科室会WP'!$T:$T,'Sales T&E & 科室会WP'!$Q:$Q,$H8)*$I8 -> 36000 | AM8: =SUMIFS('Sales T&E & 科室会WP'!$T:$T,'Sales T&E & 科室会WP'!$Q:$Q,$H8)*$I8 -> 36000 | AN8: =SUMIFS('Sales T&E & 科室会WP'!$T:$T,'Sales T&E & 科室会WP'!$Q:$Q,$H8)*$I8 -> 36000 | AO8: =SUMIFS('Sales T&E & 科室会WP'!$T:$T,'Sales T&E & 科室会WP'!$Q:$Q,$H8)*$J8 -> 36000 | AP8: =SUMIFS('Sales T&E & 科室会WP'!$T:$T,'Sales T&E & 科室会WP'!$Q:$Q,$H8)*$J8 -> 36000 | AQ8: =SUMIFS('Sales T&E & 科室会WP'!$T:$T,'Sales T&E & 科室会WP'!$Q:$Q,$H8)*$J8 -> 36000 | AR8: =SUMIFS('Sales T&E & 科室会WP'!$T:$T,'Sales T&E & 科室会WP'!$Q:$Q,$H8)*$K8 -> 36000 | AS8: =SUMIFS('Sales T&E & 科室会WP'!$T:$T,'Sales T&E & 科室会WP'!$Q:$Q,$H8)*$K8 -> 36000 | AT8: =SUMIFS('Sales T&E & 科室会WP'!$T:$T,'Sales T&E & 科室会WP'!$Q:$Q,$H8)*$K8 -> 36000 | AU8: =SUMIFS('Sales T&E & 科室会WP'!$T:$T,'Sales T&E & 科室会WP'!$Q:$Q,$H8)*$L8 -> 36000 | AV8: =SUMIFS('Sales T&E & 科室会WP'!$T:$T,'Sales T&E & 科室会WP'!$Q:$Q,$H8)*$L8 -> 36000 | AW8: =SUMIFS('Sales T&E & 科室会WP'!$T:$T,'Sales T&E & 科室会WP'!$Q:$Q,$H8)*$L8 -> 36000 | AX8: =SUM(AL8:AW8) -> 432000
A9: Commercial | B9: ID & IM BU | C9: ID - Sales | D9: ID - Xerava | E9: Central | F9: 华中区 | G9: Xerava | H9: RMM | I9: 1 | J9: 1 | K9: 1 | L9: 1 | N9: =SUMIFS('Sales T&E & 科室会WP'!$N:$N,'Sales T&E & 科室会WP'!$L:$L,$G9,'Sales T&E & 科室会WP'!$M:$M,$H9)*3*I9 -> 24000 | O9: =SUMIFS('Sales T&E & 科室会WP'!$N:$N,'Sales T&E & 科室会WP'!$L:$L,$G9,'Sales T&E & 科室会WP'!$M:$M,$H9)*3*J9 -> 24000 | P9: =SUMIFS('Sales T&E & 科室会WP'!$N:$N,'Sales T&E & 科室会WP'!$L:$L,$G9,'Sales T&E & 科室会WP'!$M:$M,$H9)*3*K9 -> 24000 | Q9: =SUMIFS('Sales T&E & 科室会WP'!$N:$N,'Sales T&E & 科室会WP'!$L:$L,$G9,'Sales T&E & 科室会WP'!$M:$M,$H9)*3*L9 -> 24000 | R9: =SUM(N9:Q9) -> 96000 | V9: =$N9/3 -> 8000 | W9: =$N9/3 -> 8000 | X9: =$N9/3 -> 8000 | Y9: =$O9/3 -> 8000 | Z9: =$O9/3 -> 8000 | AA9: =$O9/3 -> 8000 | AB9: =$P9/3 -> 8000 | AC9: =$P9/3 -> 8000 | AD9: =$P9/3 -> 8000 | AE9: =$Q9/3 -> 8000 | AF9: =$Q9/3 -> 8000 | AG9: =$Q9/3 -> 8000 | AH9: =SUM(V9:AG9) -> 96000 | AI9: =AH9-R9 -> 0 | AL9: =SUMIFS('Sales T&E & 科室会WP'!$T:$T,'Sales T&E & 科室会WP'!$Q:$Q,$H9)*$I9 -> 3000 | AM9: =SUMIFS('Sales T&E & 科室会WP'!$T:$T,'Sales T&E & 科室会WP'!$Q:$Q,$H9)*$I9 -> 3000 | AN9: =SUMIFS('Sales T&E & 科室会WP'!$T:$T,'Sales T&E & 科室会WP'!$Q:$Q,$H9)*$I9 -> 3000 | AO9: =SUMIFS('Sales T&E & 科室会WP'!$T:$T,'Sales T&E & 科室会WP'!$Q:$Q,$H9)*$J9 -> 3000 | AP9: =SUMIFS('Sales T&E & 科室会WP'!$T:$T,'Sales T&E & 科室会WP'!$Q:$Q,$H9)*$J9 -> 3000 | AQ9: =SUMIFS('Sales T&E & 科室会WP'!$T:$T,'Sales T&E & 科室会WP'!$Q:$Q,$H9)*$J9 -> 3000 | AR9: =SUMIFS('Sales T&E & 科室会WP'!$T:$T,'Sales T&E & 科室会WP'!$Q:$Q,$H9)*$K9 -> 3000 | AS9: =SUMIFS('Sales T&E & 科室会WP'!$T:$T,'Sales T&E & 科室会WP'!$Q:$Q,$H9)*$K9 -> 3000 | AT9: =SUMIFS('Sales T&E & 科室会WP'!$T:$T,'Sales T&E & 科室会WP'!$Q:$Q,$H9)*$K9 -> 3000 | AU9: =SUMIFS('Sales T&E & 科室会WP'!$T:$T,'Sales T&E & 科室会WP'!$Q:$Q,$H9)*$L9 -> 3000 | AV9: =SUMIFS('Sales T&E & 科室会WP'!$T:$T,'Sales T&E & 科室会WP'!$Q:$Q,$H9)*$L9 -> 3000 | AW9: =SUMIFS('Sales T&E & 科室会WP'!$T:$T,'Sales T&E & 科室会WP'!$Q:$Q,$H9)*$L9 -> 3000 | AX9: =SUM(AL9:AW9) -> 36000
A10: Commercial | B10: ID & IM BU | C10: ID - Sales | D10: ID - Xerava | E10: East I | F10: 东一区 | G10: Xerava | V10: =$N10/3 -> 0 | W10: =$N10/3 -> 0 | X10: =$N10/3 -> 0 | Y10: =$O10/3 -> 0 | Z10: =$O10/3 -> 0 | AA10: =$O10/3 -> 0 | AB10: =$P10/3 -> 0 | AC10: =$P10/3 -> 0 | AD10: =$P10/3 -> 0 | AE10: =$Q10/3 -> 0 | AF10: =$Q10/3 -> 0 | AG10: =$Q10/3 -> 0 | AH10: =SUM(V10:AG10) -> 0 | AI10: =AH10-R10 -> 0 | AL10: =SUMIFS('Sales T&E & 科室会WP'!$T:$T,'Sales T&E & 科室会WP'!$Q:$Q,$H10)*$I10 -> 0 | AM10: =SUMIFS('Sales T&E & 科室会WP'!$T:$T,'Sales T&E & 科室会WP'!$Q:$Q,$H10)*$I10 -> 0 | AN10: =SUMIFS('Sales T&E & 科室会WP'!$T:$T,'Sales T&E & 科室会WP'!$Q:$Q,$H10)*$I10 -> 0 | AO10: =SUMIFS('Sales T&E & 科室会WP'!$T:$T,'Sales T&E & 科室会WP'!$Q:$Q,$H10)*$J10 -> 0 | AP10: =SUMIFS('Sales T&E & 科室会WP'!$T:$T,'Sales T&E & 科室会WP'!$Q:$Q,$H10)*$J10 -> 0 | AQ10: =SUMIFS('Sales T&E & 科室会WP'!$T:$T,'Sales T&E & 科室会WP'!$Q:$Q,$H10)*$J10 -> 0 | AR10: =SUMIFS('Sales T&E & 科室会WP'!$T:$T,'Sales T&E & 科室会WP'!$Q:$Q,$H10)*$K10 -> 0 | AS10: =SUMIFS('Sales T&E & 科室会WP'!$T:$T,'Sales T&E & 科室会WP'!$Q:$Q,$H10)*$K10 -> 0 | AT10: =SUMIFS('Sales T&E & 科室会WP'!$T:$T,'Sales T&E & 科室会WP'!$Q:$Q,$H10)*$K10 -> 0 | AU10: =SUMIFS('Sales T&E & 科室会WP'!$T:$T,'Sales T&E & 科室会WP'!$Q:$Q,$H10)*$L10 -> 0 | AV10: =SUMIFS('Sales T&E & 科室会WP'!$T:$T,'Sales T&E & 科室会WP'!$Q:$Q,$H10)*$L10 -> 0 | AW10: =SUMIFS('Sales T&E & 科室会WP'!$T:$T,'Sales T&E & 科室会WP'!$Q:$Q,$H10)*$L10 -> 0 | AX10: =SUM(AL10:AW10) -> 0
A11: Commercial | B11: ID & IM BU | C11: ID - Sales | D11: ID - Xerava | E11: East I | F11: 东一区 | G11: Xerava | H11: DSM | I11: 3 | J11: 3 | K11: 3 | L11: 3 | N11: =SUMIFS('Sales T&E & 科室会WP'!$N:$N,'Sales T&E & 科室会WP'!$L:$L,$G11,'Sales T&E & 科室会WP'!$M:$M,$H11)*3*I11 -> 72000 | O11: =SUMIFS('Sales T&E & 科室会WP'!$N:$N,'Sales T&E & 科室会WP'!$L:$L,$G11,'Sales T&E & 科室会WP'!$M:$M,$H11)*3*J11 -> 72000 | P11: =SUMIFS('Sales T&E & 科室会WP'!$N:$N,'Sales T&E & 科室会WP'!$L:$L,$G11,'Sales T&E & 科室会WP'!$M:$M,$H11)*3*K11 -> 72000 | Q11: =SUMIFS('Sales T&E & 科室会WP'!$N:$N,'Sales T&E & 科室会WP'!$L:$L,$G11,'Sales T&E & 科室会WP'!$M:$M,$H11)*3*L11 -> 72000 | R11: =SUM(N11:Q11) -> 288000 | V11: =$N11/3 -> 24000 | W11: =$N11/3 -> 24000 | X11: =$N11/3 -> 24000 | Y11: =$O11/3 -> 24000 | Z11: =$O11/3 -> 24000 | AA11: =$O11/3 -> 24000 | AB11: =$P11/3 -> 24000 | AC11: =$P11/3 -> 24000 | AD11: =$P11/3 -> 24000 | AE11: =$Q11/3 -> 24000 | AF11: =$Q11/3 -> 24000 | AG11: =$Q11/3 -> 24000 | AH11: =SUM(V11:AG11) -> 288000 | AI11: =AH11-R11 -> 0 | AL11: =SUMIFS('Sales T&E & 科室会WP'!$T:$T,'Sales T&E & 科室会WP'!$Q:$Q,$H11)*$I11 -> 9000 | AM11: =SUMIFS('Sales T&E & 科室会WP'!$T:$T,'Sales T&E & 科室会WP'!$Q:$Q,$H11)*$I11 -> 9000 | AN11: =SUMIFS('Sales T&E & 科室会WP'!$T:$T,'Sales T&E & 科室会WP'!$Q:$Q,$H11)*$I11 -> 9000 | AO11: =SUMIFS('Sales T&E & 科室会WP'!$T:$T,'Sales T&E & 科室会WP'!$Q:$Q,$H11)*$J11 -> 9000 | AP11: =SUMIFS('Sales T&E & 科室会WP'!$T:$T,'Sales T&E & 科室会WP'!$Q:$Q,$H11)*$J11 -> 9000 | AQ11: =SUMIFS('Sales T&E & 科室会WP'!$T:$T,'Sales T&E & 科室会WP'!$Q:$Q,$H11)*$J11 -> 9000 | AR11: =SUMIFS('Sales T&E & 科室会WP'!$T:$T,'Sales T&E & 科室会WP'!$Q:$Q,$H11)*$K11 -> 9000 | AS11: =SUMIFS('Sales T&E & 科室会WP'!$T:$T,'Sales T&E & 科室会WP'!$Q:$Q,$H11)*$K11 -> 9000 | AT11: =SUMIFS('Sales T&E & 科室会WP'!$T:$T,'Sales T&E & 科室会WP'!$Q:$Q,$H11)*$K11 -> 9000 | AU11: =SUMIFS('Sales T&E & 科室会WP'!$T:$T,'Sales T&E & 科室会WP'!$Q:$Q,$H11)*$L11 -> 9000 | AV11: =SUMIFS('Sales T&E & 科室会WP'!$T:$T,'Sales T&E & 科室会WP'!$Q:$Q,$H11)*$L11 -> 9000 | AW11: =SUMIFS('Sales T&E & 科室会WP'!$T:$T,'Sales T&E & 科室会WP'!$Q:$Q,$H11)*$L11 -> 9000 | AX11: =SUM(AL11:AW11) -> 108000
A12: Commercial | B12: ID & IM BU | C12: ID - Sales | D12: ID - Xerava | E12: East I | F12: 东一区 | G12: Xerava | H12: MR | I12: 14 | J12: 14 | K12: 14 | L12: 14 | N12: =SUMIFS('Sales T&E & 科室会WP'!$N:$N,'Sales T&E & 科室会WP'!$L:$L,$G12,'Sales T&E & 科室会WP'!$M:$M,$H12)*3*I12 -> 210000 | O12: =SUMIFS('Sales T&E & 科室会WP'!$N:$N,'Sales T&E & 科室会WP'!$L:$L,$G12,'Sales T&E & 科室会WP'!$M:$M,$H12)*3*J12 -> 210000 | P12: =SUMIFS('Sales T&E & 科室会WP'!$N:$N,'Sales T&E & 科室会WP'!$L:$L,$G12,'Sales T&E & 科室会WP'!$M:$M,$H12)*3*K12 -> 210000 | Q12: =SUMIFS('Sales T&E & 科室会WP'!$N:$N,'Sales T&E & 科室会WP'!$L:$L,$G12,'Sales T&E & 科室会WP'!$M:$M,$H12)*3*L12 -> 210000 | R12: =SUM(N12:Q12) -> 840000 | V12: =$N12/3 -> 70000 | W12: =$N12/3 -> 70000 | X12: =$N12/3 -> 70000 | Y12: =$O12/3 -> 70000 | Z12: =$O12/3 -> 70000 | AA12: =$O12/3 -> 70000 | AB12: =$P12/3 -> 70000 | AC12: =$P12/3 -> 70000 | AD12: =$P12/3 -> 70000 | AE12: =$Q12/3 -> 70000 | AF12: =$Q12/3 -> 70000 | AG12: =$Q12/3 -> 70000 | AH12: =SUM(V12:AG12) -> 840000 | AI12: =AH12-R12 -> 0 | AL12: =SUMIFS('Sales T&E & 科室会WP'!$T:$T,'Sales T&E & 科室会WP'!$Q:$Q,$H12)*$I12 -> 42000 | AM12: =SUMIFS('Sales T&E & 科室会WP'!$T:$T,'Sales T&E & 科室会WP'!$Q:$Q,$H12)*$I12 -> 42000 | AN12: =SUMIFS('Sales T&E & 科室会WP'!$T:$T,'Sales T&E & 科室会WP'!$Q:$Q,$H12)*$I12 -> 42000 | AO12: =SUMIFS('Sales T&E & 科室会WP'!$T:$T,'Sales T&E & 科室会WP'!$Q:$Q,$H12)*$J12 -> 42000 | AP12: =SUMIFS('Sales T&E & 科室会WP'!$T:$T,'Sales T&E & 科室会WP'!$Q:$Q,$H12)*$J12 -> 42000 | AQ12: =SUMIFS('Sales T&E & 科室会WP'!$T:$T,'Sales T&E & 科室会WP'!$Q:$Q,$H12)*$J12 -> 42000 | AR12: =SUMIFS('Sales T&E & 科室会WP'!$T:$T,'Sales T&E & 科室会WP'!$Q:$Q,$H12)*$K12 -> 42000 | AS12: =SUMIFS('Sales T&E & 科室会WP'!$T:$T,'Sales T&E & 科室会WP'!$Q:$Q,$H12)*$K12 -> 42000 | AT12: =SUMIFS('Sales T&E & 科室会WP'!$T:$T,'Sales T&E & 科室会WP'!$Q:$Q,$H12)*$K12 -> 42000 | AU12: =SUMIFS('Sales T&E & 科室会WP'!$T:$T,'Sales T&E & 科室会WP'!$Q:$Q,$H12)*$L12 -> 42000 | AV12: =SUMIFS('Sales T&E & 科室会WP'!$T:$T,'Sales T&E & 科室会WP'!$Q:$Q,$H12)*$L12 -> 42000 | AW12: =SUMIFS('Sales T&E & 科室会WP'!$T:$T,'Sales T&E & 科室会WP'!$Q:$Q,$H12)*$L12 -> 42000 | AX12: =SUM(AL12:AW12) -> 504000
A13: Commercial | B13: ID & IM BU | C13: ID - Sales | D13: ID - Xerava | E13: East I | F13: 东一区 | G13: Xerava | H13: RMM | I13: 1 | J13: 1 | K13: 1 | L13: 1 | N13: =SUMIFS('Sales T&E & 科室会WP'!$N:$N,'Sales T&E & 科室会WP'!$L:$L,$G13,'Sales T&E & 科室会WP'!$M:$M,$H13)*3*I13 -> 24000 | O13: =SUMIFS('Sales T&E & 科室会WP'!$N:$N,'Sales T&E & 科室会WP'!$L:$L,$G13,'Sales T&E & 科室会WP'!$M:$M,$H13)*3*J13 -> 24000 | P13: =SUMIFS('Sales T&E & 科室会WP'!$N:$N,'Sales T&E & 科室会WP'!$L:$L,$G13,'Sales T&E & 科室会WP'!$M:$M,$H13)*3*K13 -> 24000 | Q13: =SUMIFS('Sales T&E & 科室会WP'!$N:$N,'Sales T&E & 科室会WP'!$L:$L,$G13,'Sales T&E & 科室会WP'!$M:$M,$H13)*3*L13 -> 24000 | R13: =SUM(N13:Q13) -> 96000 | V13: =$N13/3 -> 8000 | W13: =$N13/3 -> 8000 | X13: =$N13/3 -> 8000 | Y13: =$O13/3 -> 8000 | Z13: =$O13/3 -> 8000 | AA13: =$O13/3 -> 8000 | AB13: =$P13/3 -> 8000 | AC13: =$P13/3 -> 8000 | AD13: =$P13/3 -> 8000 | AE13: =$Q13/3 -> 8000 | AF13: =$Q13/3 -> 8000 | AG13: =$Q13/3 -> 8000 | AH13: =SUM(V13:AG13) -> 96000 | AI13: =AH13-R13 -> 0 | AL13: =SUMIFS('Sales T&E & 科室会WP'!$T:$T,'Sales T&E & 科室会WP'!$Q:$Q,$H13)*$I13 -> 3000 | AM13: =SUMIFS('Sales T&E & 科室会WP'!$T:$T,'Sales T&E & 科室会WP'!$Q:$Q,$H13)*$I13 -> 3000 | AN13: =SUMIFS('Sales T&E & 科室会WP'!$T:$T,'Sales T&E & 科室会WP'!$Q:$Q,$H13)*$I13 -> 3000 | AO13: =SUMIFS('Sales T&E & 科室会WP'!$T:$T,'Sales T&E & 科室会WP'!$Q:$Q,$H13)*$J13 -> 3000 | AP13: =SUMIFS('Sales T&E & 科室会WP'!$T:$T,'Sales T&E & 科室会WP'!$Q:$Q,$H13)*$J13 -> 3000 | AQ13: =SUMIFS('Sales T&E & 科室会WP'!$T:$T,'Sales T&E & 科室会WP'!$Q:$Q,$H13)*$J13 -> 3000 | AR13: =SUMIFS('Sales T&E & 科室会WP'!$T:$T,'Sales T&E & 科室会WP'!$Q:$Q,$H13)*$K13 -> 3000 | AS13: =SUMIFS('Sales T&E & 科室会WP'!$T:$T,'Sales T&E & 科室会WP'!$Q:$Q,$H13)*$K13 -> 3000 | AT13: =SUMIFS('Sales T&E & 科室会WP'!$T:$T,'Sales T&E & 科室会WP'!$Q:$Q,$H13)*$K13 -> 3000 | AU13: =SUMIFS('Sales T&E & 科室会WP'!$T:$T,'Sales T&E & 科室会WP'!$Q:$Q,$H13)*$L13 -> 3000 | AV13: =SUMIFS('Sales T&E & 科室会WP'!$T:$T,'Sales T&E & 科室会WP'!$Q:$Q,$H13)*$L13 -> 3000 | AW13: =SUMIFS('Sales T&E & 科室会WP'!$T:$T,'Sales T&E & 科室会WP'!$Q:$Q,$H13)*$L13 -> 3000 | AX13: =SUM(AL13:AW13) -> 36000
A14: Commercial | B14: ID & IM BU | C14: ID - Sales | D14: ID - Xerava | E14: East II | F14: 东二区 | G14: Xerava | H14: DSM | I14: 3 | J14: 3 | K14: 3 | L14: 3 | N14: =SUMIFS('Sales T&E & 科室会WP'!$N:$N,'Sales T&E & 科室会WP'!$L:$L,$G14,'Sales T&E & 科室会WP'!$M:$M,$H14)*3*I14 -> 72000 | O14: =SUMIFS('Sales T&E & 科室会WP'!$N:$N,'Sales T&E & 科室会WP'!$L:$L,$G14,'Sales T&E & 科室会WP'!$M:$M,$H14)*3*J14 -> 72000 | P14: =SUMIFS('Sales T&E & 科室会WP'!$N:$N,'Sales T&E & 科室会WP'!$L:$L,$G14,'Sales T&E & 科室会WP'!$M:$M,$H14)*3*K14 -> 72000 | Q14: =SUMIFS('Sales T&E & 科室会WP'!$N:$N,'Sales T&E & 科室会WP'!$L:$L,$G14,'Sales T&E & 科室会WP'!$M:$M,$H14)*3*L14 -> 72000 | R14: =SUM(N14:Q14) -> 288000 | V14: =$N14/3 -> 24000 | W14: =$N14/3 -> 24000 | X14: =$N14/3 -> 24000 | Y14: =$O14/3 -> 24000 | Z14: =$O14/3 -> 24000 | AA14: =$O14/3 -> 24000 | AB14: =$P14/3 -> 24000 | AC14: =$P14/3 -> 24000 | AD14: =$P14/3 -> 24000 | AE14: =$Q14/3 -> 24000 | AF14: =$Q14/3 -> 24000 | AG14: =$Q14/3 -> 24000 | AH14: =SUM(V14:AG14) -> 288000 | AI14: =AH14-R14 -> 0 | AL14: =SUMIFS('Sales T&E & 科室会WP'!$T:$T,'Sales T&E & 科室会WP'!$Q:$Q,$H14)*$I14 -> 9000 | AM14: =SUMIFS('Sales T&E & 科室会WP'!$T:$T,'Sales T&E & 科室会WP'!$Q:$Q,$H14)*$I14 -> 9000 | AN14: =SUMIFS('Sales T&E & 科室会WP'!$T:$T,'Sales T&E & 科室会WP'!$Q:$Q,$H14)*$I14 -> 9000 | AO14: =SUMIFS('Sales T&E & 科室会WP'!$T:$T,'Sales T&E & 科室会WP'!$Q:$Q,$H14)*$J14 -> 9000 | AP14: =SUMIFS('Sales T&E & 科室会WP'!$T:$T,'Sales T&E & 科室会WP'!$Q:$Q,$H14)*$J14 -> 9000 | AQ14: =SUMIFS('Sales T&E & 科室会WP'!$T:$T,'Sales T&E & 科室会WP'!$Q:$Q,$H14)*$J14 -> 9000 | AR14: =SUMIFS('Sales T&E & 科室会WP'!$T:$T,'Sales T&E & 科室会WP'!$Q:$Q,$H14)*$K14 -> 9000 | AS14: =SUMIFS('Sales T&E & 科室会WP'!$T:$T,'Sales T&E & 科室会WP'!$Q:$Q,$H14)*$K14 -> 9000 | AT14: =SUMIFS('Sales T&E & 科室会WP'!$T:$T,'Sales T&E & 科室会WP'!$Q:$Q,$H14)*$K14 -> 9000 | AU14: =SUMIFS('Sales T&E & 科室会WP'!$T:$T,'Sales T&E & 科室会WP'!$Q:$Q,$H14)*$L14 -> 9000 | AV14: =SUMIFS('Sales T&E & 科室会WP'!$T:$T,'Sales T&E & 科室会WP'!$Q:$Q,$H14)*$L14 -> 9000 | AW14: =SUMIFS('Sales T&E & 科室会WP'!$T:$T,'Sales T&E & 科室会WP'!$Q:$Q,$H14)*$L14 -> 9000 | AX14: =SUM(AL14:AW14) -> 108000
A15: Commercial | B15: ID & IM BU | C15: ID - Sales | D15: ID - Xerava | E15: East II | F15: 东二区 | G15: Xerava | H15: MR | I15: 15 | J15: 15 | K15: 15 | L15: 15 | N15: =SUMIFS('Sales T&E & 科室会WP'!$N:$N,'Sales T&E & 科室会WP'!$L:$L,$G15,'Sales T&E & 科室会WP'!$M:$M,$H15)*3*I15 -> 225000 | O15: =SUMIFS('Sales T&E & 科室会WP'!$N:$N,'Sales T&E & 科室会WP'!$L:$L,$G15,'Sales T&E & 科室会WP'!$M:$M,$H15)*3*J15 -> 225000 | P15: =SUMIFS('Sales T&E & 科室会WP'!$N:$N,'Sales T&E & 科室会WP'!$L:$L,$G15,'Sales T&E & 科室会WP'!$M:$M,$H15)*3*K15 -> 225000 | Q15: =SUMIFS('Sales T&E & 科室会WP'!$N:$N,'Sales T&E & 科室会WP'!$L:$L,$G15,'Sales T&E & 科室会WP'!$M:$M,$H15)*3*L15 -> 225000 | R15: =SUM(N15:Q15) -> 900000 | V15: =$N15/3 -> 75000 | W15: =$N15/3 -> 75000 | X15: =$N15/3 -> 75000 | Y15: =$O15/3 -> 75000 | Z15: =$O15/3 -> 75000 | AA15: =$O15/3 -> 75000 | AB15: =$P15/3 -> 75000 | AC15: =$P15/3 -> 75000 | AD15: =$P15/3 -> 75000 | AE15: =$Q15/3 -> 75000 | AF15: =$Q15/3 -> 75000 | AG15: =$Q15/3 -> 75000 | AH15: =SUM(V15:AG15) -> 900000 | AI15: =AH15-R15 -> 0 | AL15: =SUMIFS('Sales T&E & 科室会WP'!$T:$T,'Sales T&E & 科室会WP'!$Q:$Q,$H15)*$I15 -> 45000 | AM15: =SUMIFS('Sales T&E & 科室会WP'!$T:$T,'Sales T&E & 科室会WP'!$Q:$Q,$H15)*$I15 -> 45000 | AN15: =SUMIFS('Sales T&E & 科室会WP'!$T:$T,'Sales T&E & 科室会WP'!$Q:$Q,$H15)*$I15 -> 45000 | AO15: =SUMIFS('Sales T&E & 科室会WP'!$T:$T,'Sales T&E & 科室会WP'!$Q:$Q,$H15)*$J15 -> 45000 | AP15: =SUMIFS('Sales T&E & 科室会WP'!$T:$T,'Sales T&E & 科室会WP'!$Q:$Q,$H15)*$J15 -> 45000 | AQ15: =SUMIFS('Sales T&E & 科室会WP'!$T:$T,'Sales T&E & 科室会WP'!$Q:$Q,$H15)*$J15 -> 45000 | AR15: =SUMIFS('Sales T&E & 科室会WP'!$T:$T,'Sales T&E & 科室会WP'!$Q:$Q,$H15)*$K15 -> 45000 | AS15: =SUMIFS('Sales T&E & 科室会WP'!$T:$T,'Sales T&E & 科室会WP'!$Q:$Q,$H15)*$K15 -> 45000 | AT15: =SUMIFS('Sales T&E & 科室会WP'!$T:$T,'Sales T&E & 科室会WP'!$Q:$Q,$H15)*$K15 -> 45000 | AU15: =SUMIFS('Sales T&E & 科室会WP'!$T:$T,'Sales T&E & 科室会WP'!$Q:$Q,$H15)*$L15 -> 45000 | AV15: =SUMIFS('Sales T&E & 科室会WP'!$T:$T,'Sales T&E & 科室会WP'!$Q:$Q,$H15)*$L15 -> 45000 | AW15: =SUMIFS('Sales T&E & 科室会WP'!$T:$T,'Sales T&E & 科室会WP'!$Q:$Q,$H15)*$L15 -> 45000 | AX15: =SUM(AL15:AW15) -> 540000
A16: Commercial | B16: ID & IM BU | C16: ID - Sales | D16: ID - Xerava | E16: East II | F16: 东二区 | G16: Xerava | H16: RMM | I16: 1 | J16: 1 | K16: 1 | L16: 1 | N16: =SUMIFS('Sales T&E & 科室会WP'!$N:$N,'Sales T&E & 科室会WP'!$L:$L,$G16,'Sales T&E & 科室会WP'!$M:$M,$H16)*3*I16 -> 24000 | O16: =SUMIFS('Sales T&E & 科室会WP'!$N:$N,'Sales T&E & 科室会WP'!$L:$L,$G16,'Sales T&E & 科室会WP'!$M:$M,$H16)*3*J16 -> 24000 | P16: =SUMIFS('Sales T&E & 科室会WP'!$N:$N,'Sales T&E & 科室会WP'!$L:$L,$G16,'Sales T&E & 科室会WP'!$M:$M,$H16)*3*K16 -> 24000 | Q16: =SUMIFS('Sales T&E & 科室会WP'!$N:$N,'Sales T&E & 科室会WP'!$L:$L,$G16,'Sales T&E & 科室会WP'!$M:$M,$H16)*3*L16 -> 24000 | R16: =SUM(N16:Q16) -> 96000 | V16: =$N16/3 -> 8000 | W16: =$N16/3 -> 8000 | X16: =$N16/3 -> 8000 | Y16: =$O16/3 -> 8000 | Z16: =$O16/3 -> 8000 | AA16: =$O16/3 -> 8000 | AB16: =$P16/3 -> 8000 | AC16: =$P16/3 -> 8000 | AD16: =$P16/3 -> 8000 | AE16: =$Q16/3 -> 8000 | AF16: =$Q16/3 -> 8000 | AG16: =$Q16/3 -> 8000 | AH16: =SUM(V16:AG16) -> 96000 | AI16: =AH16-R16 -> 0 | AL16: =SUMIFS('Sales T&E & 科室会WP'!$T:$T,'Sales T&E & 科室会WP'!$Q:$Q,$H16)*$I16 -> 3000 | AM16: =SUMIFS('Sales T&E & 科室会WP'!$T:$T,'Sales T&E & 科室会WP'!$Q:$Q,$H16)*$I16 -> 3000 | AN16: =SUMIFS('Sales T&E & 科室会WP'!$T:$T,'Sales T&E & 科室会WP'!$Q:$Q,$H16)*$I16 -> 3000 | AO16: =SUMIFS('Sales T&E & 科室会WP'!$T:$T,'Sales T&E & 科室会WP'!$Q:$Q,$H16)*$J16 -> 3000 | AP16: =SUMIFS('Sales T&E & 科室会WP'!$T:$T,'Sales T&E & 科室会WP'!$Q:$Q,$H16)*$J16 -> 3000 | AQ16: =SUMIFS('Sales T&E & 科室会WP'!$T:$T,'Sales T&E & 科室会WP'!$Q:$Q,$H16)*$J16 -> 3000 | AR16: =SUMIFS('Sales T&E & 科室会WP'!$T:$T,'Sales T&E & 科室会WP'!$Q:$Q,$H16)*$K16 -> 3000 | AS16: =SUMIFS('Sales T&E & 科室会WP'!$T:$T,'Sales T&E & 科室会WP'!$Q:$Q,$H16)*$K16 -> 3000 | AT16: =SUMIFS('Sales T&E & 科室会WP'!$T:$T,'Sales T&E & 科室会WP'!$Q:$Q,$H16)*$K16 -> 3000 | AU16: =SUMIFS('Sales T&E & 科室会WP'!$T:$T,'Sales T&E & 科室会WP'!$Q:$Q,$H16)*$L16 -> 3000 | AV16: =SUMIFS('Sales T&E & 科室会WP'!$T:$T,'Sales T&E & 科室会WP'!$Q:$Q,$H16)*$L16 -> 3000 | AW16: =SUMIFS('Sales T&E & 科室会WP'!$T:$T,'Sales T&E & 科室会WP'!$Q:$Q,$H16)*$L16 -> 3000 | AX16: =SUM(AL16:AW16) -> 36000
A17: Commercial | B17: ID & IM BU | C17: ID - Sales | D17: ID - Xerava | E17: East III | F17: 东三区 | G17: Xerava | N17: =SUMIFS('Sales T&E & 科室会WP'!$N:$N,'Sales T&E & 科室会WP'!$L:$L,$G17,'Sales T&E & 科室会WP'!$M:$M,$H17)*3*I17 -> 0 | O17: =SUMIFS('Sales T&E & 科室会WP'!$N:$N,'Sales T&E & 科室会WP'!$L:$L,$G17,'Sales T&E & 科室会WP'!$M:$M,$H17)*3*J17 -> 0 | P17: =SUMIFS('Sales T&E & 科室会WP'!$N:$N,'Sales T&E & 科室会WP'!$L:$L,$G17,'Sales T&E & 科室会WP'!$M:$M,$H17)*3*K17 -> 0 | Q17: =SUMIFS('Sales T&E & 科室会WP'!$N:$N,'Sales T&E & 科室会WP'!$L:$L,$G17,'Sales T&E & 科室会WP'!$M:$M,$H17)*3*L17 -> 0 | R17: =SUM(N17:Q17) -> 0 | V17: =$N17/3 -> 0 | W17: =$N17/3 -> 0 | X17: =$N17/3 -> 0 | Y17: =$O17/3 -> 0 | Z17: =$O17/3 -> 0 | AA17: =$O17/3 -> 0 | AB17: =$P17/3 -> 0 | AC17: =$P17/3 -> 0 | AD17: =$P17/3 -> 0 | AE17: =$Q17/3 -> 0 | AF17: =$Q17/3 -> 0 | AG17: =$Q17/3 -> 0 | AH17: =SUM(V17:AG17) -> 0 | AI17: =AH17-R17 -> 0 | AL17: =SUMIFS('Sales T&E & 科室会WP'!$T:$T,'Sales T&E & 科室会WP'!$Q:$Q,$H17)*$I17 -> 0 | AM17: =SUMIFS('Sales T&E & 科室会WP'!$T:$T,'Sales T&E & 科室会WP'!$Q:$Q,$H17)*$I17 -> 0 | AN17: =SUMIFS('Sales T&E & 科室会WP'!$T:$T,'Sales T&E & 科室会WP'!$Q:$Q,$H17)*$I17 -> 0 | AO17: =SUMIFS('Sales T&E & 科室会WP'!$T:$T,'Sales T&E & 科室会WP'!$Q:$Q,$H17)*$J17 -> 0 | AP17: =SUMIFS('Sales T&E & 科室会WP'!$T:$T,'Sales T&E & 科室会WP'!$Q:$Q,$H17)*$J17 -> 0 | AQ17: =SUMIFS('Sales T&E & 科室会WP'!$T:$T,'Sales T&E & 科室会WP'!$Q:$Q,$H17)*$J17 -> 0 | AR17: =SUMIFS('Sales T&E & 科室会WP'!$T:$T,'Sales T&E & 科室会WP'!$Q:$Q,$H17)*$K17 -> 0 | AS17: =SUMIFS('Sales T&E & 科室会WP'!$T:$T,'Sales T&E & 科室会WP'!$Q:$Q,$H17)*$K17 -> 0 | AT17: =SUMIFS('Sales T&E & 科室会WP'!$T:$T,'Sales T&E & 科室会WP'!$Q:$Q,$H17)*$K17 -> 0 | AU17: =SUMIFS('Sales T&E & 科室会WP'!$T:$T,'Sales T&E & 科室会WP'!$Q:$Q,$H17)*$L17 -> 0 | AV17: =SUMIFS('Sales T&E & 科室会WP'!$T:$T,'Sales T&E & 科室会WP'!$Q:$Q,$H17)*$L17 -> 0 | AW17: =SUMIFS('Sales T&E & 科室会WP'!$T:$T,'Sales T&E & 科室会WP'!$Q:$Q,$H17)*$L17 -> 0 | AX17: =SUM(AL17:AW17) -> 0
A18: Commercial | B18: ID & IM BU | C18: ID - Sales | D18: ID - Xerava | E18: East III | F18: 东三区 | G18: Xerava | H18: DSM | I18: 2 | J18: 2 | K18: 2 | L18: 2 | N18: =SUMIFS('Sales T&E & 科室会WP'!$N:$N,'Sales T&E & 科室会WP'!$L:$L,$G18,'Sales T&E & 科室会WP'!$M:$M,$H18)*3*I18 -> 48000 | O18: =SUMIFS('Sales T&E & 科室会WP'!$N:$N,'Sales T&E & 科室会WP'!$L:$L,$G18,'Sales T&E & 科室会WP'!$M:$M,$H18)*3*J18 -> 48000 | P18: =SUMIFS('Sales T&E & 科室会WP'!$N:$N,'Sales T&E & 科室会WP'!$L:$L,$G18,'Sales T&E & 科室会WP'!$M:$M,$H18)*3*K18 -> 48000 | Q18: =SUMIFS('Sales T&E & 科室会WP'!$N:$N,'Sales T&E & 科室会WP'!$L:$L,$G18,'Sales T&E & 科室会WP'!$M:$M,$H18)*3*L18 -> 48000 | R18: =SUM(N18:Q18) -> 192000 | V18: =$N18/3 -> 16000 | W18: =$N18/3 -> 16000 | X18: =$N18/3 -> 16000 | Y18: =$O18/3 -> 16000 | Z18: =$O18/3 -> 16000 | AA18: =$O18/3 -> 16000 | AB18: =$P18/3 -> 16000 | AC18: =$P18/3 -> 16000 | AD18: =$P18/3 -> 16000 | AE18: =$Q18/3 -> 16000 | AF18: =$Q18/3 -> 16000 | AG18: =$Q18/3 -> 16000 | AH18: =SUM(V18:AG18) -> 192000 | AI18: =AH18-R18 -> 0 | AL18: =SUMIFS('Sales T&E & 科室会WP'!$T:$T,'Sales T&E & 科室会WP'!$Q:$Q,$H18)*$I18 -> 6000 | AM18: =SUMIFS('Sales T&E & 科室会WP'!$T:$T,'Sales T&E & 科室会WP'!$Q:$Q,$H18)*$I18 -> 6000 | AN18: =SUMIFS('Sales T&E & 科室会WP'!$T:$T,'Sales T&E & 科室会WP'!$Q:$Q,$H18)*$I18 -> 6000 | AO18: =SUMIFS('Sales T&E & 科室会WP'!$T:$T,'Sales T&E & 科室会WP'!$Q:$Q,$H18)*$J18 -> 6000 | AP18: =SUMIFS('Sales T&E & 科室会WP'!$T:$T,'Sales T&E & 科室会WP'!$Q:$Q,$H18)*$J18 -> 6000 | AQ18: =SUMIFS('Sales T&E & 科室会WP'!$T:$T,'Sales T&E & 科室会WP'!$Q:$Q,$H18)*$J18 -> 6000 | AR18: =SUMIFS('Sales T&E & 科室会WP'!$T:$T,'Sales T&E & 科室会WP'!$Q:$Q,$H18)*$K18 -> 6000 | AS18: =SUMIFS('Sales T&E & 科室会WP'!$T:$T,'Sales T&E & 科室会WP'!$Q:$Q,$H18)*$K18 -> 6000 | AT18: =SUMIFS('Sales T&E & 科室会WP'!$T:$T,'Sales T&E & 科室会WP'!$Q:$Q,$H18)*$K18 -> 6000 | AU18: =SUMIFS('Sales T&E & 科室会WP'!$T:$T,'Sales T&E & 科室会WP'!$Q:$Q,$H18)*$L18 -> 6000 | AV18: =SUMIFS('Sales T&E & 科室会WP'!$T:$T,'Sales T&E & 科室会WP'!$Q:$Q,$H18)*$L18 -> 6000 | AW18: =SUMIFS('Sales T&E & 科室会WP'!$T:$T,'Sales T&E & 科室会WP'!$Q:$Q,$H18)*$L18 -> 6000 | AX18: =SUM(AL18:AW18) -> 72000
A19: Commercial | B19: ID & IM BU | C19: ID - Sales | D19: ID - Xerava | E19: East III | F19: 东三区 | G19: Xerava | H19: MR | I19: 13 | J19: 13 | K19: 13 | L19: 13 | N19: =SUMIFS('Sales T&E & 科室会WP'!$N:$N,'Sales T&E & 科室会WP'!$L:$L,$G19,'Sales T&E & 科室会WP'!$M:$M,$H19)*3*I19 -> 195000 | O19: =SUMIFS('Sales T&E & 科室会WP'!$N:$N,'Sales T&E & 科室会WP'!$L:$L,$G19,'Sales T&E & 科室会WP'!$M:$M,$H19)*3*J19 -> 195000 | P19: =SUMIFS('Sales T&E & 科室会WP'!$N:$N,'Sales T&E & 科室会WP'!$L:$L,$G19,'Sales T&E & 科室会WP'!$M:$M,$H19)*3*K19 -> 195000 | Q19: =SUMIFS('Sales T&E & 科室会WP'!$N:$N,'Sales T&E & 科室会WP'!$L:$L,$G19,'Sales T&E & 科室会WP'!$M:$M,$H19)*3*L19 -> 195000 | R19: =SUM(N19:Q19) -> 780000 | V19: =$N19/3 -> 65000 | W19: =$N19/3 -> 65000 | X19: =$N19/3 -> 65000 | Y19: =$O19/3 -> 65000 | Z19: =$O19/3 -> 65000 | AA19: =$O19/3 -> 65000 | AB19: =$P19/3 -> 65000 | AC19: =$P19/3 -> 65000 | AD19: =$P19/3 -> 65000 | AE19: =$Q19/3 -> 65000 | AF19: =$Q19/3 -> 65000 | AG19: =$Q19/3 -> 65000 | AH19: =SUM(V19:AG19) -> 780000 | AI19: =AH19-R19 -> 0 | AL19: =SUMIFS('Sales T&E & 科室会WP'!$T:$T,'Sales T&E & 科室会WP'!$Q:$Q,$H19)*$I19 -> 39000 | AM19: =SUMIFS('Sales T&E & 科室会WP'!$T:$T,'Sales T&E & 科室会WP'!$Q:$Q,$H19)*$I19 -> 39000 | AN19: =SUMIFS('Sales T&E & 科室会WP'!$T:$T,'Sales T&E & 科室会WP'!$Q:$Q,$H19)*$I19 -> 39000 | AO19: =SUMIFS('Sales T&E & 科室会WP'!$T:$T,'Sales T&E & 科室会WP'!$Q:$Q,$H19)*$J19 -> 39000 | AP19: =SUMIFS('Sales T&E & 科室会WP'!$T:$T,'Sales T&E & 科室会WP'!$Q:$Q,$H19)*$J19 -> 39000 | AQ19: =SUMIFS('Sales T&E & 科室会WP'!$T:$T,'Sales T&E & 科室会WP'!$Q:$Q,$H19)*$J19 -> 39000 | AR19: =SUMIFS('Sales T&E & 科室会WP'!$T:$T,'Sales T&E & 科室会WP'!$Q:$Q,$H19)*$K19 -> 39000 | AS19: =SUMIFS('Sales T&E & 科室会WP'!$T:$T,'Sales T&E & 科室会WP'!$Q:$Q,$H19)*$K19 -> 39000 | AT19: =SUMIFS('Sales T&E & 科室会WP'!$T:$T,'Sales T&E & 科室会WP'!$Q:$Q,$H19)*$K19 -> 39000 | AU19: =SUMIFS('Sales T&E & 科室会WP'!$T:$T,'Sales T&E & 科室会WP'!$Q:$Q,$H19)*$L19 -> 39000 | AV19: =SUMIFS('Sales T&E & 科室会WP'!$T:$T,'Sales T&E & 科室会WP'!$Q:$Q,$H19)*$L19 -> 39000 | AW19: =SUMIFS('Sales T&E & 科室会WP'!$T:$T,'Sales T&E & 科室会WP'!$Q:$Q,$H19)*$L19 -> 39000 | AX19: =SUM(AL19:AW19) -> 468000
A20: Commercial | B20: ID & IM BU | C20: ID - Sales | D20: ID - Xerava | E20: East III | F20: 东三区 | G20: Xerava | H20: RMM | I20: 1 | J20: 1 | K20: 1 | L20: 1 | N20: =SUMIFS('Sales T&E & 科室会WP'!$N:$N,'Sales T&E & 科室会WP'!$L:$L,$G20,'Sales T&E & 科室会WP'!$M:$M,$H20)*3*I20 -> 24000 | O20: =SUMIFS('Sales T&E & 科室会WP'!$N:$N,'Sales T&E & 科室会WP'!$L:$L,$G20,'Sales T&E & 科室会WP'!$M:$M,$H20)*3*J20 -> 24000 | P20: =SUMIFS('Sales T&E & 科室会WP'!$N:$N,'Sales T&E & 科室会WP'!$L:$L,$G20,'Sales T&E & 科室会WP'!$M:$M,$H20)*3*K20 -> 24000 | Q20: =SUMIFS('Sales T&E & 科室会WP'!$N:$N,'Sales T&E & 科室会WP'!$L:$L,$G20,'Sales T&E & 科室会WP'!$M:$M,$H20)*3*L20 -> 24000 | R20: =SUM(N20:Q20) -> 96000 | V20: =$N20/3 -> 8000 | W20: =$N20/3 -> 8000 | X20: =$N20/3 -> 8000 | Y20: =$O20/3 -> 8000 | Z20: =$O20/3 -> 8000 | AA20: =$O20/3 -> 8000 | AB20: =$P20/3 -> 8000 | AC20: =$P20/3 -> 8000 | AD20: =$P20/3 -> 8000 | AE20: =$Q20/3 -> 8000 | AF20: =$Q20/3 -> 8000 | AG20: =$Q20/3 -> 8000 | AH20: =SUM(V20:AG20) -> 96000 | AI20: =AH20-R20 -> 0 | AL20: =SUMIFS('Sales T&E & 科室会WP'!$T:$T,'Sales T&E & 科室会WP'!$Q:$Q,$H20)*$I20 -> 3000 | AM20: =SUMIFS('Sales T&E & 科室会WP'!$T:$T,'Sales T&E & 科室会WP'!$Q:$Q,$H20)*$I20 -> 3000 | AN20: =SUMIFS('Sales T&E & 科室会WP'!$T:$T,'Sales T&E & 科室会WP'!$Q:$Q,$H20)*$I20 -> 3000 | AO20: =SUMIFS('Sales T&E & 科室会WP'!$T:$T,'Sales T&E & 科室会WP'!$Q:$Q,$H20)*$J20 -> 3000 | AP20: =SUMIFS('Sales T&E & 科室会WP'!$T:$T,'Sales T&E & 科室会WP'!$Q:$Q,$H20)*$J20 -> 3000 | AQ20: =SUMIFS('Sales T&E & 科室会WP'!$T:$T,'Sales T&E & 科室会WP'!$Q:$Q,$H20)*$J20 -> 3000 | AR20: =SUMIFS('Sales T&E & 科室会WP'!$T:$T,'Sales T&E & 科室会WP'!$Q:$Q,$H20)*$K20 -> 3000 | AS20: =SUMIFS('Sales T&E & 科室会WP'!$T:$T,'Sales T&E & 科室会WP'!$Q:$Q,$H20)*$K20 -> 3000 | AT20: =SUMIFS('Sales T&E & 科室会WP'!$T:$T,'Sales T&E & 科室会WP'!$Q:$Q,$H20)*$K20 -> 3000 | AU20: =SUMIFS('Sales T&E & 科室会WP'!$T:$T,'Sales T&E & 科室会WP'!$Q:$Q,$H20)*$L20 -> 3000 | AV20: =SUMIFS('Sales T&E & 科室会WP'!$T:$T,'Sales T&E & 科室会WP'!$Q:$Q,$H20)*$L20 -> 3000 | AW20: =SUMIFS('Sales T&E & 科室会WP'!$T:$T,'Sales T&E & 科室会WP'!$Q:$Q,$H20)*$L20 -> 3000 | AX20: =SUM(AL20:AW20) -> 36000
A21: Commercial | B21: ID & IM BU | C21: ID - Sales | D21: ID - Xerava | E21: North I | F21: 北一区 | G21: Xerava | N21: =SUMIFS('Sales T&E & 科室会WP'!$N:$N,'Sales T&E & 科室会WP'!$L:$L,$G21,'Sales T&E & 科室会WP'!$M:$M,$H21)*3*I21 -> 0 | O21: =SUMIFS('Sales T&E & 科室会WP'!$N:$N,'Sales T&E & 科室会WP'!$L:$L,$G21,'Sales T&E & 科室会WP'!$M:$M,$H21)*3*J21 -> 0 | P21: =SUMIFS('Sales T&E & 科室会WP'!$N:$N,'Sales T&E & 科室会WP'!$L:$L,$G21,'Sales T&E & 科室会WP'!$M:$M,$H21)*3*K21 -> 0 | Q21: =SUMIFS('Sales T&E & 科室会WP'!$N:$N,'Sales T&E & 科室会WP'!$L:$L,$G21,'Sales T&E & 科室会WP'!$M:$M,$H21)*3*L21 -> 0 | R21: =SUM(N21:Q21) -> 0 | V21: =$N21/3 -> 0 | W21: =$N21/3 -> 0 | X21: =$N21/3 -> 0 | Y21: =$O21/3 -> 0 | Z21: =$O21/3 -> 0 | AA21: =$O21/3 -> 0 | AB21: =$P21/3 -> 0 | AC21: =$P21/3 -> 0 | AD21: =$P21/3 -> 0 | AE21: =$Q21/3 -> 0 | AF21: =$Q21/3 -> 0 | AG21: =$Q21/3 -> 0 | AH21: =SUM(V21:AG21) -> 0 | AI21: =AH21-R21 -> 0 | AL21: =SUMIFS('Sales T&E & 科室会WP'!$T:$T,'Sales T&E & 科室会WP'!$Q:$Q,$H21)*$I21 -> 0 | AM21: =SUMIFS('Sales T&E & 科室会WP'!$T:$T,'Sales T&E & 科室会WP'!$Q:$Q,$H21)*$I21 -> 0 | AN21: =SUMIFS('Sales T&E & 科室会WP'!$T:$T,'Sales T&E & 科室会WP'!$Q:$Q,$H21)*$I21 -> 0 | AO21: =SUMIFS('Sales T&E & 科室会WP'!$T:$T,'Sales T&E & 科室会WP'!$Q:$Q,$H21)*$J21 -> 0 | AP21: =SUMIFS('Sales T&E & 科室会WP'!$T:$T,'Sales T&E & 科室会WP'!$Q:$Q,$H21)*$J21 -> 0 | AQ21: =SUMIFS('Sales T&E & 科室会WP'!$T:$T,'Sales T&E & 科室会WP'!$Q:$Q,$H21)*$J21 -> 0 | AR21: =SUMIFS('Sales T&E & 科室会WP'!$T:$T,'Sales T&E & 科室会WP'!$Q:$Q,$H21)*$K21 -> 0 | AS21: =SUMIFS('Sales T&E & 科室会WP'!$T:$T,'Sales T&E & 科室会WP'!$Q:$Q,$H21)*$K21 -> 0 | AT21: =SUMIFS('Sales T&E & 科室会WP'!$T:$T,'Sales T&E & 科室会WP'!$Q:$Q,$H21)*$K21 -> 0 | AU21: =SUMIFS('Sales T&E & 科室会WP'!$T:$T,'Sales T&E & 科室会WP'!$Q:$Q,$H21)*$L21 -> 0 | AV21: =SUMIFS('Sales T&E & 科室会WP'!$T:$T,'Sales T&E & 科室会WP'!$Q:$Q,$H21)*$L21 -> 0 | AW21: =SUMIFS('Sales T&E & 科室会WP'!$T:$T,'Sales T&E & 科室会WP'!$Q:$Q,$H21)*$L21 -> 0 | AX21: =SUM(AL21:AW21) -> 0
A22: Commercial | B22: ID & IM BU | C22: ID - Sales | D22: ID - Xerava | E22: North I | F22: 北一区 | G22: Xerava | H22: DSM | I22: 4 | J22: 4 | K22: 4 | L22: 4 | N22: =SUMIFS('Sales T&E & 科室会WP'!$N:$N,'Sales T&E & 科室会WP'!$L:$L,$G22,'Sales T&E & 科室会WP'!$M:$M,$H22)*3*I22 -> 96000 | O22: =SUMIFS('Sales T&E & 科室会WP'!$N:$N,'Sales T&E & 科室会WP'!$L:$L,$G22,'Sales T&E & 科室会WP'!$M:$M,$H22)*3*J22 -> 96000 | P22: =SUMIFS('Sales T&E & 科室会WP'!$N:$N,'Sales T&E & 科室会WP'!$L:$L,$G22,'Sales T&E & 科室会WP'!$M:$M,$H22)*3*K22 -> 96000 | Q22: =SUMIFS('Sales T&E & 科室会WP'!$N:$N,'Sales T&E & 科室会WP'!$L:$L,$G22,'Sales T&E & 科室会WP'!$M:$M,$H22)*3*L22 -> 96000 | R22: =SUM(N22:Q22) -> 384000 | V22: =$N22/3 -> 32000 | W22: =$N22/3 -> 32000 | X22: =$N22/3 -> 32000 | Y22: =$O22/3 -> 32000 | Z22: =$O22/3 -> 32000 | AA22: =$O22/3 -> 32000 | AB22: =$P22/3 -> 32000 | AC22: =$P22/3 -> 32000 | AD22: =$P22/3 -> 32000 | AE22: =$Q22/3 -> 32000 | AF22: =$Q22/3 -> 32000 | AG22: =$Q22/3 -> 32000 | AH22: =SUM(V22:AG22) -> 384000 | AI22: =AH22-R22 -> 0 | AL22: =SUMIFS('Sales T&E & 科室会WP'!$T:$T,'Sales T&E & 科室会WP'!$Q:$Q,$H22)*$I22 -> 12000 | AM22: =SUMIFS('Sales T&E & 科室会WP'!$T:$T,'Sales T&E & 科室会WP'!$Q:$Q,$H22)*$I22 -> 12000 | AN22: =SUMIFS('Sales T&E & 科室会WP'!$T:$T,'Sales T&E & 科室会WP'!$Q:$Q,$H22)*$I22 -> 12000 | AO22: =SUMIFS('Sales T&E & 科室会WP'!$T:$T,'Sales T&E & 科室会WP'!$Q:$Q,$H22)*$J22 -> 12000 | AP22: =SUMIFS('Sales T&E & 科室会WP'!$T:$T,'Sales T&E & 科室会WP'!$Q:$Q,$H22)*$J22 -> 12000 | AQ22: =SUMIFS('Sales T&E & 科室会WP'!$T:$T,'Sales T&E & 科室会WP'!$Q:$Q,$H22)*$J22 -> 12000 | AR22: =SUMIFS('Sales T&E & 科室会WP'!$T:$T,'Sales T&E & 科室会WP'!$Q:$Q,$H22)*$K22 -> 12000 | AS22: =SUMIFS('Sales T&E & 科室会WP'!$T:$T,'Sales T&E & 科室会WP'!$Q:$Q,$H22)*$K22 -> 12000 | AT22: =SUMIFS('Sales T&E & 科室会WP'!$T:$T,'Sales T&E & 科室会WP'!$Q:$Q,$H22)*$K22 -> 12000 | AU22: =SUMIFS('Sales T&E & 科室会WP'!$T:$T,'Sales T&E & 科室会WP'!$Q:$Q,$H22)*$L22 -> 12000 | AV22: =SUMIFS('Sales T&E & 科室会WP'!$T:$T,'Sales T&E & 科室会WP'!$Q:$Q,$H22)*$L22 -> 12000 | AW22: =SUMIFS('Sales T&E & 科室会WP'!$T:$T,'Sales T&E & 科室会WP'!$Q:$Q,$H22)*$L22 -> 12000 | AX22: =SUM(AL22:AW22) -> 144000
A23: Commercial | B23: ID & IM BU | C23: ID - Sales | D23: ID - Xerava | E23: North I | F23: 北一区 | G23: Xerava | H23: MR | I23: 20 | J23: 20 | K23: 20 | L23: 20 | N23: =SUMIFS('Sales T&E & 科室会WP'!$N:$N,'Sales T&E & 科室会WP'!$L:$L,$G23,'Sales T&E & 科室会WP'!$M:$M,$H23)*3*I23 -> 300000 | O23: =SUMIFS('Sales T&E & 科室会WP'!$N:$N,'Sales T&E & 科室会WP'!$L:$L,$G23,'Sales T&E & 科室会WP'!$M:$M,$H23)*3*J23 -> 300000 | P23: =SUMIFS('Sales T&E & 科室会WP'!$N:$N,'Sales T&E & 科室会WP'!$L:$L,$G23,'Sales T&E & 科室会WP'!$M:$M,$H23)*3*K23 -> 300000 | Q23: =SUMIFS('Sales T&E & 科室会WP'!$N:$N,'Sales T&E & 科室会WP'!$L:$L,$G23,'Sales T&E & 科室会WP'!$M:$M,$H23)*3*L23 -> 300000 | R23: =SUM(N23:Q23) -> 1200000 | V23: =$N23/3 -> 100000 | W23: =$N23/3 -> 100000 | X23: =$N23/3 -> 100000 | Y23: =$O23/3 -> 100000 | Z23: =$O23/3 -> 100000 | AA23: =$O23/3 -> 100000 | AB23: =$P23/3 -> 100000 | AC23: =$P23/3 -> 100000 | AD23: =$P23/3 -> 100000 | AE23: =$Q23/3 -> 100000 | AF23: =$Q23/3 -> 100000 | AG23: =$Q23/3 -> 100000 | AH23: =SUM(V23:AG23) -> 1200000 | AI23: =AH23-R23 -> 0 | AL23: =SUMIFS('Sales T&E & 科室会WP'!$T:$T,'Sales T&E & 科室会WP'!$Q:$Q,$H23)*$I23 -> 60000 | AM23: =SUMIFS('Sales T&E & 科室会WP'!$T:$T,'Sales T&E & 科室会WP'!$Q:$Q,$H23)*$I23 -> 60000 | AN23: =SUMIFS('Sales T&E & 科室会WP'!$T:$T,'Sales T&E & 科室会WP'!$Q:$Q,$H23)*$I23 -> 60000 | AO23: =SUMIFS('Sales T&E & 科室会WP'!$T:$T,'Sales T&E & 科室会WP'!$Q:$Q,$H23)*$J23 -> 60000 | AP23: =SUMIFS('Sales T&E & 科室会WP'!$T:$T,'Sales T&E & 科室会WP'!$Q:$Q,$H23)*$J23 -> 60000 | AQ23: =SUMIFS('Sales T&E & 科室会WP'!$T:$T,'Sales T&E & 科室会WP'!$Q:$Q,$H23)*$J23 -> 60000 | AR23: =SUMIFS('Sales T&E & 科室会WP'!$T:$T,'Sales T&E & 科室会WP'!$Q:$Q,$H23)*$K23 -> 60000 | AS23: =SUMIFS('Sales T&E & 科室会WP'!$T:$T,'Sales T&E & 科室会WP'!$Q:$Q,$H23)*$K23 -> 60000 | AT23: =SUMIFS('Sales T&E & 科室会WP'!$T:$T,'Sales T&E & 科室会WP'!$Q:$Q,$H23)*$K23 -> 60000 | AU23: =SUMIFS('Sales T&E & 科室会WP'!$T:$T,'Sales T&E & 科室会WP'!$Q:$Q,$H23)*$L23 -> 60000 | AV23: =SUMIFS('Sales T&E & 科室会WP'!$T:$T,'Sales T&E & 科室会WP'!$Q:$Q,$H23)*$L23 -> 60000 | AW23: =SUMIFS('Sales T&E & 科室会WP'!$T:$T,'Sales T&E & 科室会WP'!$Q:$Q,$H23)*$L23 -> 60000 | AX23: =SUM(AL23:AW23) -> 720000
A24: Commercial | B24: ID & IM BU | C24: ID - Sales | D24: ID - Xerava | E24: North I | F24: 北一区 | G24: Xerava | H24: RMM | I24: 1 | J24: 1 | K24: 1 | L24: 1 | N24: =SUMIFS('Sales T&E & 科室会WP'!$N:$N,'Sales T&E & 科室会WP'!$L:$L,$G24,'Sales T&E & 科室会WP'!$M:$M,$H24)*3*I24 -> 24000 | O24: =SUMIFS('Sales T&E & 科室会WP'!$N:$N,'Sales T&E & 科室会WP'!$L:$L,$G24,'Sales T&E & 科室会WP'!$M:$M,$H24)*3*J24 -> 24000 | P24: =SUMIFS('Sales T&E & 科室会WP'!$N:$N,'Sales T&E & 科室会WP'!$L:$L,$G24,'Sales T&E & 科室会WP'!$M:$M,$H24)*3*K24 -> 24000 | Q24: =SUMIFS('Sales T&E & 科室会WP'!$N:$N,'Sales T&E & 科室会WP'!$L:$L,$G24,'Sales T&E & 科室会WP'!$M:$M,$H24)*3*L24 -> 24000 | R24: =SUM(N24:Q24) -> 96000 | V24: =$N24/3 -> 8000 | W24: =$N24/3 -> 8000 | X24: =$N24/3 -> 8000 | Y24: =$O24/3 -> 8000 | Z24: =$O24/3 -> 8000 | AA24: =$O24/3 -> 8000 | AB24: =$P24/3 -> 8000 | AC24: =$P24/3 -> 8000 | AD24: =$P24/3 -> 8000 | AE24: =$Q24/3 -> 8000 | AF24: =$Q24/3 -> 8000 | AG24: =$Q24/3 -> 8000 | AH24: =SUM(V24:AG24) -> 96000 | AI24: =AH24-R24 -> 0 | AL24: =SUMIFS('Sales T&E & 科室会WP'!$T:$T,'Sales T&E & 科室会WP'!$Q:$Q,$H24)*$I24 -> 3000 | AM24: =SUMIFS('Sales T&E & 科室会WP'!$T:$T,'Sales T&E & 科室会WP'!$Q:$Q,$H24)*$I24 -> 3000 | AN24: =SUMIFS('Sales T&E & 科室会WP'!$T:$T,'Sales T&E & 科室会WP'!$Q:$Q,$H24)*$I24 -> 3000 | AO24: =SUMIFS('Sales T&E & 科室会WP'!$T:$T,'Sales T&E & 科室会WP'!$Q:$Q,$H24)*$J24 -> 3000 | AP24: =SUMIFS('Sales T&E & 科室会WP'!$T:$T,'Sales T&E & 科室会WP'!$Q:$Q,$H24)*$J24 -> 3000 | AQ24: =SUMIFS('Sales T&E & 科室会WP'!$T:$T,'Sales T&E & 科室会WP'!$Q:$Q,$H24)*$J24 -> 3000 | AR24: =SUMIFS('Sales T&E & 科室会WP'!$T:$T,'Sales T&E & 科室会WP'!$Q:$Q,$H24)*$K24 -> 3000 | AS24: =SUMIFS('Sales T&E & 科室会WP'!$T:$T,'Sales T&E & 科室会WP'!$Q:$Q,$H24)*$K24 -> 3000 | AT24: =SUMIFS('Sales T&E & 科室会WP'!$T:$T,'Sales T&E & 科室会WP'!$Q:$Q,$H24)*$K24 -> 3000 | AU24: =SUMIFS('Sales T&E & 科室会WP'!$T:$T,'Sales T&E & 科室会WP'!$Q:$Q,$H24)*$L24 -> 3000 | AV24: =SUMIFS('Sales T&E & 科室会WP'!$T:$T,'Sales T&E & 科室会WP'!$Q:$Q,$H24)*$L24 -> 3000 | AW24: =SUMIFS('Sales T&E & 科室会WP'!$T:$T,'Sales T&E & 科室会WP'!$Q:$Q,$H24)*$L24 -> 3000 | AX24: =SUM(AL24:AW24) -> 36000
A25: Commercial | B25: ID & IM BU | C25: ID - Sales | D25: ID - Xerava | E25: North II | F25: 北二区 | G25: Xerava | H25: DSM | I25: 1 | J25: 1 | K25: 1 | L25: 1 | N25: =SUMIFS('Sales T&E & 科室会WP'!$N:$N,'Sales T&E & 科室会WP'!$L:$L,$G25,'Sales T&E & 科室会WP'!$M:$M,$H25)*3*I25 -> 24000 | O25: =SUMIFS('Sales T&E & 科室会WP'!$N:$N,'Sales T&E & 科室会WP'!$L:$L,$G25,'Sales T&E & 科室会WP'!$M:$M,$H25)*3*J25 -> 24000 | P25: =SUMIFS('Sales T&E & 科室会WP'!$N:$N,'Sales T&E & 科室会WP'!$L:$L,$G25,'Sales T&E & 科室会WP'!$M:$M,$H25)*3*K25 -> 24000 | Q25: =SUMIFS('Sales T&E & 科室会WP'!$N:$N,'Sales T&E & 科室会WP'!$L:$L,$G25,'Sales T&E & 科室会WP'!$M:$M,$H25)*3*L25 -> 24000 | R25: =SUM(N25:Q25) -> 96000 | V25: =$N25/3 -> 8000 | W25: =$N25/3 -> 8000 | X25: =$N25/3 -> 8000 | Y25: =$O25/3 -> 8000 | Z25: =$O25/3 -> 8000 | AA25: =$O25/3 -> 8000 | AB25: =$P25/3 -> 8000 | AC25: =$P25/3 -> 8000 | AD25: =$P25/3 -> 8000 | AE25: =$Q25/3 -> 8000 | AF25: =$Q25/3 -> 8000 | AG25: =$Q25/3 -> 8000 | AH25: =SUM(V25:AG25) -> 96000 | AI25: =AH25-R25 -> 0 | AL25: =SUMIFS('Sales T&E & 科室会WP'!$T:$T,'Sales T&E & 科室会WP'!$Q:$Q,$H25)*$I25 -> 3000 | AM25: =SUMIFS('Sales T&E & 科室会WP'!$T:$T,'Sales T&E & 科室会WP'!$Q:$Q,$H25)*$I25 -> 3000 | AN25: =SUMIFS('Sales T&E & 科室会WP'!$T:$T,'Sales T&E & 科室会WP'!$Q:$Q,$H25)*$I25 -> 3000 | AO25: =SUMIFS('Sales T&E & 科室会WP'!$T:$T,'Sales T&E & 科室会WP'!$Q:$Q,$H25)*$J25 -> 3000 | AP25: =SUMIFS('Sales T&E & 科室会WP'!$T:$T,'Sales T&E & 科室会WP'!$Q:$Q,$H25)*$J25 -> 3000 | AQ25: =SUMIFS('Sales T&E & 科室会WP'!$T:$T,'Sales T&E & 科室会WP'!$Q:$Q,$H25)*$J25 -> 3000 | AR25: =SUMIFS('Sales T&E & 科室会WP'!$T:$T,'Sales T&E & 科室会WP'!$Q:$Q,$H25)*$K25 -> 3000 | AS25: =SUMIFS('Sales T&E & 科室会WP'!$T:$T,'Sales T&E & 科室会WP'!$Q:$Q,$H25)*$K25 -> 3000 | AT25: =SUMIFS('Sales T&E & 科室会WP'!$T:$T,'Sales T&E & 科室会WP'!$Q:$Q,$H25)*$K25 -> 3000 | AU25: =SUMIFS('Sales T&E & 科室会WP'!$T:$T,'Sales T&E & 科室会WP'!$Q:$Q,$H25)*$L25 -> 3000 | AV25: =SUMIFS('Sales T&E & 科室会WP'!$T:$T,'Sales T&E & 科室会WP'!$Q:$Q,$H25)*$L25 -> 3000 | AW25: =SUMIFS('Sales T&E & 科室会WP'!$T:$T,'Sales T&E & 科室会WP'!$Q:$Q,$H25)*$L25 -> 3000 | AX25: =SUM(AL25:AW25) -> 36000
A26: Commercial | B26: ID & IM BU | C26: ID - Sales | D26: ID - Xerava | E26: North II | F26: 北二区 | G26: Xerava | H26: MR | I26: 8 | J26: 8 | K26: 8 | L26: 8 | N26: =SUMIFS('Sales T&E & 科室会WP'!$N:$N,'Sales T&E & 科室会WP'!$L:$L,$G26,'Sales T&E & 科室会WP'!$M:$M,$H26)*3*I26 -> 120000 | O26: =SUMIFS('Sales T&E & 科室会WP'!$N:$N,'Sales T&E & 科室会WP'!$L:$L,$G26,'Sales T&E & 科室会WP'!$M:$M,$H26)*3*J26 -> 120000 | P26: =SUMIFS('Sales T&E & 科室会WP'!$N:$N,'Sales T&E & 科室会WP'!$L:$L,$G26,'Sales T&E & 科室会WP'!$M:$M,$H26)*3*K26 -> 120000 | Q26: =SUMIFS('Sales T&E & 科室会WP'!$N:$N,'Sales T&E & 科室会WP'!$L:$L,$G26,'Sales T&E & 科室会WP'!$M:$M,$H26)*3*L26 -> 120000 | R26: =SUM(N26:Q26) -> 480000 | V26: =$N26/3 -> 40000 | W26: =$N26/3 -> 40000 | X26: =$N26/3 -> 40000 | Y26: =$O26/3 -> 40000 | Z26: =$O26/3 -> 40000 | AA26: =$O26/3 -> 40000 | AB26: =$P26/3 -> 40000 | AC26: =$P26/3 -> 40000 | AD26: =$P26/3 -> 40000 | AE26: =$Q26/3 -> 40000 | AF26: =$Q26/3 -> 40000 | AG26: =$Q26/3 -> 40000 | AH26: =SUM(V26:AG26) -> 480000 | AI26: =AH26-R26 -> 0 | AL26: =SUMIFS('Sales T&E & 科室会WP'!$T:$T,'Sales T&E & 科室会WP'!$Q:$Q,$H26)*$I26 -> 24000 | AM26: =SUMIFS('Sales T&E & 科室会WP'!$T:$T,'Sales T&E & 科室会WP'!$Q:$Q,$H26)*$I26 -> 24000 | AN26: =SUMIFS('Sales T&E & 科室会WP'!$T:$T,'Sales T&E & 科室会WP'!$Q:$Q,$H26)*$I26 -> 24000 | AO26: =SUMIFS('Sales T&E & 科室会WP'!$T:$T,'Sales T&E & 科室会WP'!$Q:$Q,$H26)*$J26 -> 24000 | AP26: =SUMIFS('Sales T&E & 科室会WP'!$T:$T,'Sales T&E & 科室会WP'!$Q:$Q,$H26)*$J26 -> 24000 | AQ26: =SUMIFS('Sales T&E & 科室会WP'!$T:$T,'Sales T&E & 科室会WP'!$Q:$Q,$H26)*$J26 -> 24000 | AR26: =SUMIFS('Sales T&E & 科室会WP'!$T:$T,'Sales T&E & 科室会WP'!$Q:$Q,$H26)*$K26 -> 24000 | AS26: =SUMIFS('Sales T&E & 科室会WP'!$T:$T,'Sales T&E & 科室会WP'!$Q:$Q,$H26)*$K26 -> 24000 | AT26: =SUMIFS('Sales T&E & 科室会WP'!$T:$T,'Sales T&E & 科室会WP'!$Q:$Q,$H26)*$K26 -> 24000 | AU26: =SUMIFS('Sales T&E & 科室会WP'!$T:$T,'Sales T&E & 科室会WP'!$Q:$Q,$H26)*$L26 -> 24000 | AV26: =SUMIFS('Sales T&E & 科室会WP'!$T:$T,'Sales T&E & 科室会WP'!$Q:$Q,$H26)*$L26 -> 24000 | AW26: =SUMIFS('Sales T&E & 科室会WP'!$T:$T,'Sales T&E & 科室会WP'!$Q:$Q,$H26)*$L26 -> 24000 | AX26: =SUM(AL26:AW26) -> 288000
A27: Commercial | B27: ID & IM BU | C27: ID - Sales | D27: ID - Xerava | E27: North II | F27: 北二区 | G27: Xerava | H27: RMM | I27: 1 | J27: 1 | K27: 1 | L27: 1 | N27: =SUMIFS('Sales T&E & 科室会WP'!$N:$N,'Sales T&E & 科室会WP'!$L:$L,$G27,'Sales T&E & 科室会WP'!$M:$M,$H27)*3*I27 -> 24000 | O27: =SUMIFS('Sales T&E & 科室会WP'!$N:$N,'Sales T&E & 科室会WP'!$L:$L,$G27,'Sales T&E & 科室会WP'!$M:$M,$H27)*3*J27 -> 24000 | P27: =SUMIFS('Sales T&E & 科室会WP'!$N:$N,'Sales T&E & 科室会WP'!$L:$L,$G27,'Sales T&E & 科室会WP'!$M:$M,$H27)*3*K27 -> 24000 | Q27: =SUMIFS('Sales T&E & 科室会WP'!$N:$N,'Sales T&E & 科室会WP'!$L:$L,$G27,'Sales T&E & 科室会WP'!$M:$M,$H27)*3*L27 -> 24000 | R27: =SUM(N27:Q27) -> 96000 | V27: =$N27/3 -> 8000 | W27: =$N27/3 -> 8000 | X27: =$N27/3 -> 8000 | Y27: =$O27/3 -> 8000 | Z27: =$O27/3 -> 8000 | AA27: =$O27/3 -> 8000 | AB27: =$P27/3 -> 8000 | AC27: =$P27/3 -> 8000 | AD27: =$P27/3 -> 8000 | AE27: =$Q27/3 -> 8000 | AF27: =$Q27/3 -> 8000 | AG27: =$Q27/3 -> 8000 | AH27: =SUM(V27:AG27) -> 96000 | AI27: =AH27-R27 -> 0 | AL27: =SUMIFS('Sales T&E & 科室会WP'!$T:$T,'Sales T&E & 科室会WP'!$Q:$Q,$H27)*$I27 -> 3000 | AM27: =SUMIFS('Sales T&E & 科室会WP'!$T:$T,'Sales T&E & 科室会WP'!$Q:$Q,$H27)*$I27 -> 3000 | AN27: =SUMIFS('Sales T&E & 科室会WP'!$T:$T,'Sales T&E & 科室会WP'!$Q:$Q,$H27)*$I27 -> 3000 | AO27: =SUMIFS('Sales T&E & 科室会WP'!$T:$T,'Sales T&E & 科室会WP'!$Q:$Q,$H27)*$J27 -> 3000 | AP27: =SUMIFS('Sales T&E & 科室会WP'!$T:$T,'Sales T&E & 科室会WP'!$Q:$Q,$H27)*$J27 -> 3000 | AQ27: =SUMIFS('Sales T&E & 科室会WP'!$T:$T,'Sales T&E & 科室会WP'!$Q:$Q,$H27)*$J27 -> 3000 | AR27: =SUMIFS('Sales T&E & 科室会WP'!$T:$T,'Sales T&E & 科室会WP'!$Q:$Q,$H27)*$K27 -> 3000 | AS27: =SUMIFS('Sales T&E & 科室会WP'!$T:$T,'Sales T&E & 科室会WP'!$Q:$Q,$H27)*$K27 -> 3000 | AT27: =SUMIFS('Sales T&E & 科室会WP'!$T:$T,'Sales T&E & 科室会WP'!$Q:$Q,$H27)*$K27 -> 3000 | AU27: =SUMIFS('Sales T&E & 科室会WP'!$T:$T,'Sales T&E & 科室会WP'!$Q:$Q,$H27)*$L27 -> 3000 | AV27: =SUMIFS('Sales T&E & 科室会WP'!$T:$T,'Sales T&E & 科室会WP'!$Q:$Q,$H27)*$L27 -> 3000 | AW27: =SUMIFS('Sales T&E & 科室会WP'!$T:$T,'Sales T&E & 科室会WP'!$Q:$Q,$H27)*$L27 -> 3000 | AX27: =SUM(AL27:AW27) -> 36000
A28: Commercial | B28: ID & IM BU | C28: ID - Sales | D28: ID - Xerava | E28: North III | F28: 北三区 | G28: Xerava | N28: =SUMIFS('Sales T&E & 科室会WP'!$N:$N,'Sales T&E & 科室会WP'!$L:$L,$G28,'Sales T&E & 科室会WP'!$M:$M,$H28)*3*I28 -> 0 | O28: =SUMIFS('Sales T&E & 科室会WP'!$N:$N,'Sales T&E & 科室会WP'!$L:$L,$G28,'Sales T&E & 科室会WP'!$M:$M,$H28)*3*J28 -> 0 | P28: =SUMIFS('Sales T&E & 科室会WP'!$N:$N,'Sales T&E & 科室会WP'!$L:$L,$G28,'Sales T&E & 科室会WP'!$M:$M,$H28)*3*K28 -> 0 | Q28: =SUMIFS('Sales T&E & 科室会WP'!$N:$N,'Sales T&E & 科室会WP'!$L:$L,$G28,'Sales T&E & 科室会WP'!$M:$M,$H28)*3*L28 -> 0 | R28: =SUM(N28:Q28) -> 0 | V28: =$N28/3 -> 0 | W28: =$N28/3 -> 0 | X28: =$N28/3 -> 0 | Y28: =$O28/3 -> 0 | Z28: =$O28/3 -> 0 | AA28: =$O28/3 -> 0 | AB28: =$P28/3 -> 0 | AC28: =$P28/3 -> 0 | AD28: =$P28/3 -> 0 | AE28: =$Q28/3 -> 0 | AF28: =$Q28/3 -> 0 | AG28: =$Q28/3 -> 0 | AH28: =SUM(V28:AG28) -> 0 | AI28: =AH28-R28 -> 0 | AL28: =SUMIFS('Sales T&E & 科室会WP'!$T:$T,'Sales T&E & 科室会WP'!$Q:$Q,$H28)*$I28 -> 0 | AM28: =SUMIFS('Sales T&E & 科室会WP'!$T:$T,'Sales T&E & 科室会WP'!$Q:$Q,$H28)*$I28 -> 0 | AN28: =SUMIFS('Sales T&E & 科室会WP'!$T:$T,'Sales T&E & 科室会WP'!$Q:$Q,$H28)*$I28 -> 0 | AO28: =SUMIFS('Sales T&E & 科室会WP'!$T:$T,'Sales T&E & 科室会WP'!$Q:$Q,$H28)*$J28 -> 0 | AP28: =SUMIFS('Sales T&E & 科室会WP'!$T:$T,'Sales T&E & 科室会WP'!$Q:$Q,$H28)*$J28 -> 0 | AQ28: =SUMIFS('Sales T&E & 科室会WP'!$T:$T,'Sales T&E & 科室会WP'!$Q:$Q,$H28)*$J28 -> 0 | AR28: =SUMIFS('Sales T&E & 科室会WP'!$T:$T,'Sales T&E & 科室会WP'!$Q:$Q,$H28)*$K28 -> 0 | AS28: =SUMIFS('Sales T&E & 科室会WP'!$T:$T,'Sales T&E & 科室会WP'!$Q:$Q,$H28)*$K28 -> 0 | AT28: =SUMIFS('Sales T&E & 科室会WP'!$T:$T,'Sales T&E & 科室会WP'!$Q:$Q,$H28)*$K28 -> 0 | AU28: =SUMIFS('Sales T&E & 科室会WP'!$T:$T,'Sales T&E & 科室会WP'!$Q:$Q,$H28)*$L28 -> 0 | AV28: =SUMIFS('Sales T&E & 科室会WP'!$T:$T,'Sales T&E & 科室会WP'!$Q:$Q,$H28)*$L28 -> 0 | AW28: =SUMIFS('Sales T&E & 科室会WP'!$T:$T,'Sales T&E & 科室会WP'!$Q:$Q,$H28)*$L28 -> 0 | AX28: =SUM(AL28:AW28) -> 0
A29: Commercial | B29: ID & IM BU | C29: ID - Sales | D29: ID - Xerava | E29: North III | F29: 北三区 | G29: Xerava | H29: DSM | I29: 3 | J29: 3 | K29: 3 | L29: 3 | N29: =SUMIFS('Sales T&E & 科室会WP'!$N:$N,'Sales T&E & 科室会WP'!$L:$L,$G29,'Sales T&E & 科室会WP'!$M:$M,$H29)*3*I29 -> 72000 | O29: =SUMIFS('Sales T&E & 科室会WP'!$N:$N,'Sales T&E & 科室会WP'!$L:$L,$G29,'Sales T&E & 科室会WP'!$M:$M,$H29)*3*J29 -> 72000 | P29: =SUMIFS('Sales T&E & 科室会WP'!$N:$N,'Sales T&E & 科室会WP'!$L:$L,$G29,'Sales T&E & 科室会WP'!$M:$M,$H29)*3*K29 -> 72000 | Q29: =SUMIFS('Sales T&E & 科室会WP'!$N:$N,'Sales T&E & 科室会WP'!$L:$L,$G29,'Sales T&E & 科室会WP'!$M:$M,$H29)*3*L29 -> 72000 | R29: =SUM(N29:Q29) -> 288000 | V29: =$N29/3 -> 24000 | W29: =$N29/3 -> 24000 | X29: =$N29/3 -> 24000 | Y29: =$O29/3 -> 24000 | Z29: =$O29/3 -> 24000 | AA29: =$O29/3 -> 24000 | AB29: =$P29/3 -> 24000 | AC29: =$P29/3 -> 24000 | AD29: =$P29/3 -> 24000 | AE29: =$Q29/3 -> 24000 | AF29: =$Q29/3 -> 24000 | AG29: =$Q29/3 -> 24000 | AH29: =SUM(V29:AG29) -> 288000 | AI29: =AH29-R29 -> 0 | AL29: =SUMIFS('Sales T&E & 科室会WP'!$T:$T,'Sales T&E & 科室会WP'!$Q:$Q,$H29)*$I29 -> 9000 | AM29: =SUMIFS('Sales T&E & 科室会WP'!$T:$T,'Sales T&E & 科室会WP'!$Q:$Q,$H29)*$I29 -> 9000 | AN29: =SUMIFS('Sales T&E & 科室会WP'!$T:$T,'Sales T&E & 科室会WP'!$Q:$Q,$H29)*$I29 -> 9000 | AO29: =SUMIFS('Sales T&E & 科室会WP'!$T:$T,'Sales T&E & 科室会WP'!$Q:$Q,$H29)*$J29 -> 9000 | AP29: =SUMIFS('Sales T&E & 科室会WP'!$T:$T,'Sales T&E & 科室会WP'!$Q:$Q,$H29)*$J29 -> 9000 | AQ29: =SUMIFS('Sales T&E & 科室会WP'!$T:$T,'Sales T&E & 科室会WP'!$Q:$Q,$H29)*$J29 -> 9000 | AR29: =SUMIFS('Sales T&E & 科室会WP'!$T:$T,'Sales T&E & 科室会WP'!$Q:$Q,$H29)*$K29 -> 9000 | AS29: =SUMIFS('Sales T&E & 科室会WP'!$T:$T,'Sales T&E & 科室会WP'!$Q:$Q,$H29)*$K29 -> 9000 | AT29: =SUMIFS('Sales T&E & 科室会WP'!$T:$T,'Sales T&E & 科室会WP'!$Q:$Q,$H29)*$K29 -> 9000 | AU29: =SUMIFS('Sales T&E & 科室会WP'!$T:$T,'Sales T&E & 科室会WP'!$Q:$Q,$H29)*$L29 -> 9000 | AV29: =SUMIFS('Sales T&E & 科室会WP'!$T:$T,'Sales T&E & 科室会WP'!$Q:$Q,$H29)*$L29 -> 9000 | AW29: =SUMIFS('Sales T&E & 科室会WP'!$T:$T,'Sales T&E & 科室会WP'!$Q:$Q,$H29)*$L29 -> 9000 | AX29: =SUM(AL29:AW29) -> 108000
A30: Commercial | B30: ID & IM BU | C30: ID - Sales | D30: ID - Xerava | E30: North III | F30: 北三区 | G30: Xerava | H30: MR | I30: 12 | J30: 12 | K30: 12 | L30: 12 | N30: =SUMIFS('Sales T&E & 科室会WP'!$N:$N,'Sales T&E & 科室会WP'!$L:$L,$G30,'Sales T&E & 科室会WP'!$M:$M,$H30)*3*I30 -> 180000 | O30: =SUMIFS('Sales T&E & 科室会WP'!$N:$N,'Sales T&E & 科室会WP'!$L:$L,$G30,'Sales T&E & 科室会WP'!$M:$M,$H30)*3*J30 -> 180000 | P30: =SUMIFS('Sales T&E & 科室会WP'!$N:$N,'Sales T&E & 科室会WP'!$L:$L,$G30,'Sales T&E & 科室会WP'!$M:$M,$H30)*3*K30 -> 180000 | Q30: =SUMIFS('Sales T&E & 科室会WP'!$N:$N,'Sales T&E & 科室会WP'!$L:$L,$G30,'Sales T&E & 科室会WP'!$M:$M,$H30)*3*L30 -> 180000 | R30: =SUM(N30:Q30) -> 720000 | V30: =$N30/3 -> 60000 | W30: =$N30/3 -> 60000 | X30: =$N30/3 -> 60000 | Y30: =$O30/3 -> 60000 | Z30: =$O30/3 -> 60000 | AA30: =$O30/3 -> 60000 | AB30: =$P30/3 -> 60000 | AC30: =$P30/3 -> 60000 | AD30: =$P30/3 -> 60000 | AE30: =$Q30/3 -> 60000 | AF30: =$Q30/3 -> 60000 | AG30: =$Q30/3 -> 60000 | AH30: =SUM(V30:AG30) -> 720000 | AI30: =AH30-R30 -> 0 | AL30: =SUMIFS('Sales T&E & 科室会WP'!$T:$T,'Sales T&E & 科室会WP'!$Q:$Q,$H30)*$I30 -> 36000 | AM30: =SUMIFS('Sales T&E & 科室会WP'!$T:$T,'Sales T&E & 科室会WP'!$Q:$Q,$H30)*$I30 -> 36000 | AN30: =SUMIFS('Sales T&E & 科室会WP'!$T:$T,'Sales T&E & 科室会WP'!$Q:$Q,$H30)*$I30 -> 36000 | AO30: =SUMIFS('Sales T&E & 科室会WP'!$T:$T,'Sales T&E & 科室会WP'!$Q:$Q,$H30)*$J30 -> 36000 | AP30: =SUMIFS('Sales T&E & 科室会WP'!$T:$T,'Sales T&E & 科室会WP'!$Q:$Q,$H30)*$J30 -> 36000 | AQ30: =SUMIFS('Sales T&E & 科室会WP'!$T:$T,'Sales T&E & 科室会WP'!$Q:$Q,$H30)*$J30 -> 36000 | AR30: =SUMIFS('Sales T&E & 科室会WP'!$T:$T,'Sales T&E & 科室会WP'!$Q:$Q,$H30)*$K30 -> 36000 | AS30: =SUMIFS('Sales T&E & 科室会WP'!$T:$T,'Sales T&E & 科室会WP'!$Q:$Q,$H30)*$K30 -> 36000 | AT30: =SUMIFS('Sales T&E & 科室会WP'!$T:$T,'Sales T&E & 科室会WP'!$Q:$Q,$H30)*$K30 -> 36000 | AU30: =SUMIFS('Sales T&E & 科室会WP'!$T:$T,'Sales T&E & 科室会WP'!$Q:$Q,$H30)*$L30 -> 36000 | AV30: =SUMIFS('Sales T&E & 科室会WP'!$T:$T,'Sales T&E & 科室会WP'!$Q:$Q,$H30)*$L30 -> 36000 | AW30: =SUMIFS('Sales T&E & 科室会WP'!$T:$T,'Sales T&E & 科室会WP'!$Q:$Q,$H30)*$L30 -> 36000 | AX30: =SUM(AL30:AW30) -> 432000
A31: Commercial | B31: ID & IM BU | C31: ID - Sales | D31: ID - Xerava | E31: North III | F31: 北三区 | G31: Xerava | H31: RMM | I31: 1 | J31: 1 | K31: 1 | L31: 1 | N31: =SUMIFS('Sales T&E & 科室会WP'!$N:$N,'Sales T&E & 科室会WP'!$L:$L,$G31,'Sales T&E & 科室会WP'!$M:$M,$H31)*3*I31 -> 24000 | O31: =SUMIFS('Sales T&E & 科室会WP'!$N:$N,'Sales T&E & 科室会WP'!$L:$L,$G31,'Sales T&E & 科室会WP'!$M:$M,$H31)*3*J31 -> 24000 | P31: =SUMIFS('Sales T&E & 科室会WP'!$N:$N,'Sales T&E & 科室会WP'!$L:$L,$G31,'Sales T&E & 科室会WP'!$M:$M,$H31)*3*K31 -> 24000 | Q31: =SUMIFS('Sales T&E & 科室会WP'!$N:$N,'Sales T&E & 科室会WP'!$L:$L,$G31,'Sales T&E & 科室会WP'!$M:$M,$H31)*3*L31 -> 24000 | R31: =SUM(N31:Q31) -> 96000 | V31: =$N31/3 -> 8000 | W31: =$N31/3 -> 8000 | X31: =$N31/3 -> 8000 | Y31: =$O31/3 -> 8000 | Z31: =$O31/3 -> 8000 | AA31: =$O31/3 -> 8000 | AB31: =$P31/3 -> 8000 | AC31: =$P31/3 -> 8000 | AD31: =$P31/3 -> 8000 | AE31: =$Q31/3 -> 8000 | AF31: =$Q31/3 -> 8000 | AG31: =$Q31/3 -> 8000 | AH31: =SUM(V31:AG31) -> 96000 | AI31: =AH31-R31 -> 0 | AL31: =SUMIFS('Sales T&E & 科室会WP'!$T:$T,'Sales T&E & 科室会WP'!$Q:$Q,$H31)*$I31 -> 3000 | AM31: =SUMIFS('Sales T&E & 科室会WP'!$T:$T,'Sales T&E & 科室会WP'!$Q:$Q,$H31)*$I31 -> 3000 | AN31: =SUMIFS('Sales T&E & 科室会WP'!$T:$T,'Sales T&E & 科室会WP'!$Q:$Q,$H31)*$I31 -> 3000 | AO31: =SUMIFS('Sales T&E & 科室会WP'!$T:$T,'Sales T&E & 科室会WP'!$Q:$Q,$H31)*$J31 -> 3000 | AP31: =SUMIFS('Sales T&E & 科室会WP'!$T:$T,'Sales T&E & 科室会WP'!$Q:$Q,$H31)*$J31 -> 3000 | AQ31: =SUMIFS('Sales T&E & 科室会WP'!$T:$T,'Sales T&E & 科室会WP'!$Q:$Q,$H31)*$J31 -> 3000 | AR31: =SUMIFS('Sales T&E & 科室会WP'!$T:$T,'Sales T&E & 科室会WP'!$Q:$Q,$H31)*$K31 -> 3000 | AS31: =SUMIFS('Sales T&E & 科室会WP'!$T:$T,'Sales T&E & 科室会WP'!$Q:$Q,$H31)*$K31 -> 3000 | AT31: =SUMIFS('Sales T&E & 科室会WP'!$T:$T,'Sales T&E & 科室会WP'!$Q:$Q,$H31)*$K31 -> 3000 | AU31: =SUMIFS('Sales T&E & 科室会WP'!$T:$T,'Sales T&E & 科室会WP'!$Q:$Q,$H31)*$L31 -> 3000 | AV31: =SUMIFS('Sales T&E & 科室会WP'!$T:$T,'Sales T&E & 科室会WP'!$Q:$Q,$H31)*$L31 -> 3000 | AW31: =SUMIFS('Sales T&E & 科室会WP'!$T:$T,'Sales T&E & 科室会WP'!$Q:$Q,$H31)*$L31 -> 3000 | AX31: =SUM(AL31:AW31) -> 36000
